Workbook
Name NativeTimeline_Order_Date: #N/A
Name Slicer_on_time: #N/A
Name Slicer_order_status: #N/A
Name Slicer_Rain_mode_updated: #N/A

Sheet Swiggy Orders
A1: order_id | B1: is_coupon_applied | C1: coupon_applied | D1: offers_data | E1: order_time | F1: confirmed_time | G1: customer_id | H1: order_status | I1: delivery_boy.name | J1: restaurant_id | K1: restaurant_name | L1: restaurant_address | M1: restaurant_locality | N1: restaurant_city_name | O1: delivery_time_in_seconds | P1: order_total | Q1: order_total_with_tip | R1: net_total | S1: item_total | T1: free_delivery_discount_hit | U1: restaurant_order_rating | V1: restaurant_lat_lng | W1: restaurant_customer_distance | X1: coupon_code | Y1: order_payment_method | Z1: restaurant_area_name | AA1: on_time | AB1: rain_mode | AC1: Coupon_Code_Updated | AD1: restaurant_name_updated | AE1: restaurant_area_name_updated | AF1: Discount | AG1: Order_Date | AH1: Time | AI1: Weekday | AJ1: Day_Seg | AK1: Rain_mode_updated | AQ1: Hrs | AR1: Segments
A2: 175244332362622 | B2: TRUE | C2: SWIGGYIT | D2: [{"id":"7740ff94-cc8f-41cf-b6ec-d4c97cbd0060","super_type":"SUPERTYPE_UNSPECIFIED","total_offer_discount":120,"discount_share":{"swiggy_discount":67.2,"store_discount":52.8,"alliance_discount":0},"discount_type":"PERCENTAGE","description":"60% off","fixed_charges":{"gp":{"id":"","final_price":0}}}] | E2: 2024-05-21 12:28:52 | F2: 2024-05-21 12:29:13 | G2: 21191609 | H2: Delivered | I2: NARREDDY NAGESWARA REDDY | J2: 434304 | K2: Paris Panini - Gourmet Sandwiches & Wraps | L2: No.690/A, 14th Main, 100ft Road, JP Nagar 2nd Phase, Bangalore 560078. | M2: JP Nagar | N2: Bangalore | O2: 1587 | P2: 146 | Q2: 146 | R2: 146 | S2: 225 | T2: 43 | U2: 0 | V2: 12.90649867,77.59165435 | W2: 2.2 | X2: SWIGGYIT | Y2: UPICollect | Z2: JP Nagar | AA2: FALSE | AB2: 0 | AC2: =IF(X2="","No Coupon Applied",X2) -> SWIGGYIT | AD2: =VLOOKUP(K2,'restaurant name correction'!$A$1:$B$44,2,0) -> Paris Panini | AE2: =VLOOKUP(Z2,restaurant_area_correction!$A$1:$B$18,2,0) -> JP Nagar | AF2: =VALUE(IFERROR(MID(D2,FIND(":",D2,FIND("total_offer_discount",D2))+1,FIND(",",D2,FIND("total_offer_discount",D2)) - FIND(":",D2,FIND("total_offer_discount",D2))-1),0)) -> 120 | AG2: =DATEVALUE(E2) -> 45433 | AH2: =TIMEVALUE(E2) -> 0.5200463 | AI2: =TEXT(AG2,"dddd") -> Tuesday | AJ2: =VLOOKUP(HOUR(Orders[[#This Row],[Time]]),$AQ$1:$AR$7,2,1) -> Afternoon | AK2: =IF(Orders[[#This Row],[rain_mode]]=0,"Sunny","Rainy") -> Sunny | AQ2: 0 | AR2: Early Morning
A3: 175167017704058 | B3: FALSE | E3: 2024-05-20 15:00:17 | F3: 2024-05-20 15:00:38 | G3: 21191609 | H3: Delivered | I3: Kesavamoorthi | J3: 12804 | K3: Nandhana Palace | L3: JP nagar, 147, 24th Main Rd, R.K Colony, Marenahalli, 2nd Phase, J. P. Nagar, Bengaluru, Karnataka 560078 | M3: JP Nagar | N3: Bangalore | O3: 1853 | P3: 555 | Q3: 555 | R3: 555 | S3: 480 | T3: 41 | U3: 0 | V3: 12.914599,77.585509 | W3: 2.2 | Y3: UPICollect | Z3: JP Nagar | AA3: FALSE | AB3: 0 | AC3: =IF(X3="","No Coupon Applied",X3) -> No Coupon Applied | AD3: =VLOOKUP(K3,'restaurant name correction'!$A$1:$B$44,2,0) -> Nandhana Palace | AE3: =VLOOKUP(Z3,restaurant_area_correction!$A$1:$B$18,2,0) -> JP Nagar | AF3: =VALUE(IFERROR(MID(D3,FIND(":",D3,FIND("total_offer_discount",D3))+1,FIND(",",D3,FIND("total_offer_discount",D3)) - FIND(":",D3,FIND("total_offer_discount",D3))-1),0)) -> 0 | AG3: =DATEVALUE(E3) -> 45432 | AH3: =TIMEVALUE(E3) -> 0.62519676 | AI3: =TEXT(AG3,"dddd") -> Monday | AJ3: =VLOOKUP(HOUR(Orders[[#This Row],[Time]]),$AQ$1:$AR$7,2,1) -> Afternoon | AK3: =IF(Orders[[#This Row],[rain_mode]]=0,"Sunny","Rainy") -> Sunny | AQ3: 4 | AR3: Morning
A4: 175017114796029 | B4: TRUE | C4: MISSEDYOU | D4: [{"id":"c1399a7d-65f4-486a-ba3e-72a9d9c70cad","super_type":"SUPERTYPE_UNSPECIFIED","total_offer_discount":80,"discount_share":{"swiggy_discount":16,"store_discount":64,"alliance_discount":0},"discount_type":"PERCENTAGE","description":"40% off","fixed_charges":{"gp":{"id":"","final_price":0}}}] | E4: 2024-05-18 21:21:54 | F4: 2024-05-18 21:22:15 | G4: 21191609 | H4: Delivered | I4: Safiul Ansari | J4: 15250 | K4: The Ganache Factory - Cakes & Desserts | L4: #156, 43rd Cross, 8th Block, Next to Udupi Hub Resto, Jayanagar, Bangalore | M4: 8th Block | N4: Bangalore | O4: 1559 | P4: 382 | Q4: 382 | R4: 382 | S4: 400 | T4: 69 | U4: 0 | V4: 12.91835714,77.578127 | W4: 3.6 | X4: MISSEDYOU | Y4: UPICollect | Z4: Jayanagar | AA4: TRUE | AB4: 0 | AC4: =IF(X4="","No Coupon Applied",X4) -> MISSEDYOU | AD4: =VLOOKUP(K4,'restaurant name correction'!$A$1:$B$44,2,0) -> The Ganache Factory | AE4: =VLOOKUP(Z4,restaurant_area_correction!$A$1:$B$18,2,0) -> Jayanagar | AF4: =VALUE(IFERROR(MID(D4,FIND(":",D4,FIND("total_offer_discount",D4))+1,FIND(",",D4,FIND("total_offer_discount",D4)) - FIND(":",D4,FIND("total_offer_discount",D4))-1),0)) -> 80 | AG4: =DATEVALUE(E4) -> 45430 | AH4: =TIMEVALUE(E4) -> 0.89020833 | AI4: =TEXT(AG4,"dddd") -> Saturday | AJ4: =VLOOKUP(HOUR(Orders[[#This Row],[Time]]),$AQ$1:$AR$7,2,1) -> Night | AK4: =IF(Orders[[#This Row],[rain_mode]]=0,"Sunny","Rainy") -> Sunny | AQ4: 8 | AR4: Late Morning
A5: 174973046023416 | B5: TRUE | C5: SWIGGYIT | D5: [{"id":"28bf3ebb-4a69-4a92-88a4-f491a5f86e17","super_type":"SUPERTYPE_UNSPECIFIED","total_offer_discount":39.99,"discount_share":{"swiggy_discount":0,"store_discount":39.99,"alliance_discount":0},"discount_type":"PERCENTAGE","description":"10% off","fixed_charges":{"gp":{"id":"","final_price":0}}}] | E5: 2024-05-18 09:07:26 | F5: 2024-05-18 09:07:44 | G5: 21191609 | H5: Delivered | I5: Rama Krishna | J5: 630473 | K5: Rasayan | L5: 652,13th cross,29th main road BTM 2nd stage,560078, Bangalore Karnataka | M5: Health Bar | N5: Bangalore | O5: 3760 | P5: 421 | Q5: 421 | R5: 421 | S5: 415 | T5: 46 | U5: 0 | V5: 12.907799,77.613487 | W5: 2.5 | X5: SWIGGYIT | Y5: UPICollect | Z5: BTM 2nd Stage | AA5: FALSE | AB5: 0 | AC5: =IF(X5="","No Coupon Applied",X5) -> SWIGGYIT | AD5: =VLOOKUP(K5,'restaurant name correction'!$A$1:$B$44,2,0) -> Rasayan | AE5: =VLOOKUP(Z5,restaurant_area_correction!$A$1:$B$18,2,0) -> BTM | AF5: =VALUE(IFERROR(MID(D5,FIND(":",D5,FIND("total_offer_discount",D5))+1,FIND(",",D5,FIND("total_offer_discount",D5)) - FIND(":",D5,FIND("total_offer_discount",D5))-1),0)) -> 39.99 | AG5: =DATEVALUE(E5) -> 45430 | AH5: =TIMEVALUE(E5) -> 0.38016204 | AI5: =TEXT(AG5,"dddd") -> Saturday | AJ5: =VLOOKUP(HOUR(Orders[[#This Row],[Time]]),$AQ$1:$AR$7,2,1) -> Late Morning | AK5: =IF(Orders[[#This Row],[rain_mode]]=0,"Sunny","Rainy") -> Sunny | AQ5: 12 | AR5: Afternoon
A6: 174906705849277 | B6: TRUE | C6: DEALICIOUS | D6: [{"id":"91e6269d-640b-443e-a7d4-46089c0574f6","super_type":"SUPERTYPE_UNSPECIFIED","total_offer_discount":124.99,"discount_share":{"swiggy_discount":0,"store_discount":124.99,"alliance_discount":0},"discount_type":"FLAT","description":"FLAT125 off","fixed_charges":{"gp":{"id":"","final_price":0}}}] | E6: 2024-05-17 14:41:45 | F6: 2024-05-17 14:42:09 | G6: 21191609 | H6: Delivered | I6: Tapan Nayak | J6: 34363 | K6: Firangi Bake | L6: Shop No.4, Frist Floor, NGK Complex, Tavarekere Main Rd, 1st Stage, BTM Layout, Bengaluru, Karnataka 560029 ( Above DMart Ready) | M6: NGK Complex | N6: Bangalore | O6: 2257 | P6: 556 | Q6: 556 | R6: 556 | S6: 624 | T6: 35 | U6: 0 | V6: 12.920219,77.610520 | W6: 2.2 | X6: DEALICIOUS | Y6: UPICollect | Z6: BTM 1st Stage | AA6: FALSE | AB6: 0 | AC6: =IF(X6="","No Coupon Applied",X6) -> DEALICIOUS | AD6: =VLOOKUP(K6,'restaurant name correction'!$A$1:$B$44,2,0) -> Firangi Bake | AE6: =VLOOKUP(Z6,restaurant_area_correction!$A$1:$B$18,2,0) -> BTM | AF6: =VALUE(IFERROR(MID(D6,FIND(":",D6,FIND("total_offer_discount",D6))+1,FIND(",",D6,FIND("total_offer_discount",D6)) - FIND(":",D6,FIND("total_offer_discount",D6))-1),0)) -> 124.99 | AG6: =DATEVALUE(E6) -> 45429 | AH6: =TIMEVALUE(E6) -> 0.61232639 | AI6: =TEXT(AG6,"dddd") -> Friday | AJ6: =VLOOKUP(HOUR(Orders[[#This Row],[Time]]),$AQ$1:$AR$7,2,1) -> Afternoon | AK6: =IF(Orders[[#This Row],[rain_mode]]=0,"Sunny","Rainy") -> Sunny | AQ6: 16 | AR6: Evening
A7: 174329455765789 | B7: TRUE | C7: MDM150 | D7: [{"id":"60d51c5f-a27d-407c-9d72-c55f498dea78","super_type":"SUPERTYPE_UNSPECIFIED","total_offer_discount":149.99,"discount_share":{"swiggy_discount":15,"store_discount":134.99,"alliance_discount":0},"discount_type":"FLAT","description":"Flat ₹150 off","fixed_charges":{"gp":{"id":"","final_price":0}}}] | E7: 2024-05-10 22:20:55 | F7: 2024-05-10 22:21:01 | G7: 21191609 | H7: Delivered | I7: ARUN DYAVANAKATTI | J7: 474244 | K7: Daily Sushi | L7: No.5, 1st Floor, 9th Main Road, 5th block, Jayanagar, 560041 | M7: 5th Block | N7: Bangalore | O7: 3262 | P7: 1062 | Q7: 1062 | R7: 1062 | S7: 1050 | T7: 45 | U7: 0 | V7: 12.92243257,77.58390586 | W7: 3.2 | X7: MDM150 | Y7: Cash | Z7: Jayanagar | AA7: FALSE | AB7: 0 | AC7: =IF(X7="","No Coupon Applied",X7) -> MDM150 | AD7: =VLOOKUP(K7,'restaurant name correction'!$A$1:$B$44,2,0) -> Daily Sushi | AE7: =VLOOKUP(Z7,restaurant_area_correction!$A$1:$B$18,2,0) -> Jayanagar | AF7: =VALUE(IFERROR(MID(D7,FIND(":",D7,FIND("total_offer_discount",D7))+1,FIND(",",D7,FIND("total_offer_discount",D7)) - FIND(":",D7,FIND("total_offer_discount",D7))-1),0)) -> 149.99 | AG7: =DATEVALUE(E7) -> 45422 | AH7: =TIMEVALUE(E7) -> 0.93119213 | AI7: =TEXT(AG7,"dddd") -> Friday | AJ7: =VLOOKUP(HOUR(Orders[[#This Row],[Time]]),$AQ$1:$AR$7,2,1) -> Night | AK7: =IF(Orders[[#This Row],[rain_mode]]=0,"Sunny","Rainy") -> Sunny | AQ7: 20 | AR7: Night
A8: 174318296922309 | B8: TRUE | C8: SWIGGYIT | D8: [{"id":"7740ff94-cc8f-41cf-b6ec-d4c97cbd0060","super_type":"SUPERTYPE_UNSPECIFIED","total_offer_discount":120,"discount_share":{"swiggy_discount":67.2,"store_discount":52.8,"alliance_discount":0},"discount_type":"PERCENTAGE","description":"60% off","fixed_charges":{"gp":{"id":"","final_price":0}}}] | E8: 2024-05-10 19:14:56 | F8: 2024-05-10 19:15:01 | G8: 21191609 | H8: Delivered | I8: PARASH | J8: 434304 | K8: Paris Panini - Gourmet Sandwiches & Wraps | L8: No.690/A, 14th Main, 100ft Road, JP Nagar 2nd Phase, Bangalore 560078. | M8: JP Nagar | N8: Bangalore | O8: 2401 | P8: 440 | Q8: 440 | R8: 440 | S8: 480 | T8: 45 | U8: 0 | V8: 12.90649867,77.59165435 | W8: 2.1 | X8: SWIGGYIT | Y8: Cash | Z8: JP Nagar | AA8: FALSE | AB8: 0 | AC8: =IF(X8="","No Coupon Applied",X8) -> SWIGGYIT | AD8: =VLOOKUP(K8,'restaurant name correction'!$A$1:$B$44,2,0) -> Paris Panini | AE8: =VLOOKUP(Z8,restaurant_area_correction!$A$1:$B$18,2,0) -> JP Nagar | AF8: =VALUE(IFERROR(MID(D8,FIND(":",D8,FIND("total_offer_discount",D8))+1,FIND(",",D8,FIND("total_offer_discount",D8)) - FIND(":",D8,FIND("total_offer_discount",D8))-1),0)) -> 120 | AG8: =DATEVALUE(E8) -> 45422 | AH8: =TIMEVALUE(E8) -> 0.80203704 | AI8: =TEXT(AG8,"dddd") -> Friday | AJ8: =VLOOKUP(HOUR(Orders[[#This Row],[Time]]),$AQ$1:$AR$7,2,1) -> Evening | AK8: =IF(Orders[[#This Row],[rain_mode]]=0,"Sunny","Rainy") -> Sunny
A9: 174118005152904 | B9: TRUE | C9: SWIGGYIT | D9: [{"id":"8a02a1ac-9efe-46ea-9649-fc635c7c8618","super_type":"SUPERTYPE_UNSPECIFIED","total_offer_discount":35,"discount_share":{"swiggy_discount":0,"store_discount":35,"alliance_discount":0},"discount_type":"PERCENTAGE","description":"10% off","fixed_charges":{"gp":{"id":"","final_price":0}}}] | E9: 2024-05-08 11:36:45 | F9: 2024-05-08 11:37:28 | G9: 21191609 | H9: Delivered | I9: Sanjay Kumar Mohanty | J9: 534276 | K9: Naalnaad Mane | L9: 16,2ND FLOOR GOWRY'S BUILDING,ABOVE DOMINO'S,SY NO 13 OF AREKERE VILLAGE,BANNERGHATTA,BANGLAORE,jayanagar,B.B.M.PM south, karnataka - 560076 | M9: Mico Layout | N9: Bangalore | O9: 2824 | P9: 352 | Q9: 352 | R9: 352 | S9: 350 | T9: 36 | U9: 0 | V9: 12.89009167,77.5976944 | W9: 3.2 | X9: SWIGGYIT | Y9: UPICollect | Z9: Arekere | AA9: TRUE | AB9: 0 | AC9: =IF(X9="","No Coupon Applied",X9) -> SWIGGYIT | AD9: =VLOOKUP(K9,'restaurant name correction'!$A$1:$B$44,2,0) -> Naalnaad Mane | AE9: =VLOOKUP(Z9,restaurant_area_correction!$A$1:$B$18,2,0) -> Arekere | AF9: =VALUE(IFERROR(MID(D9,FIND(":",D9,FIND("total_offer_discount",D9))+1,FIND(",",D9,FIND("total_offer_discount",D9)) - FIND(":",D9,FIND("total_offer_discount",D9))-1),0)) -> 35 | AG9: =DATEVALUE(E9) -> 45420 | AH9: =TIMEVALUE(E9) -> 0.48385417 | AI9: =TEXT(AG9,"dddd") -> Wednesday | AJ9: =VLOOKUP(HOUR(Orders[[#This Row],[Time]]),$AQ$1:$AR$7,2,1) -> Late Morning | AK9: =IF(Orders[[#This Row],[rain_mode]]=0,"Sunny","Rainy") -> Sunny
A10: 174075356745024 | B10: FALSE | E10: 2024-05-07 23:45:56 | F10: 2024-05-07 23:46:17 | G10: 21191609 | H10: Delivered | I10: DIDAR HUSSAIN LASKAR | J10: 524936 | K10: Theobroma | L10: SHOP NO-39,SHABARI ARCADE,14TH MAIN ROAD,OPP MAX SHOWROOM, HSR LAYOUT,BANGALORE-560102, BTM Layout , B.B.M.P South, Karnataka-560102 | M10: 7th Sector | N10: Bangalore | O10: 2011 | P10: 644 | Q10: 644 | R10: 644 | S10: 275 | T10: 71 | U10: 0 | V10: 12.91135428,77.6380469 | W10: 5.2 | Y10: UPICollect | Z10: HSR Layout | AA10: TRUE | AB10: 0 | AC10: =IF(X10="","No Coupon Applied",X10) -> No Coupon Applied | AD10: =VLOOKUP(K10,'restaurant name correction'!$A$1:$B$44,2,0) -> Theobroma | AE10: =VLOOKUP(Z10,restaurant_area_correction!$A$1:$B$18,2,0) -> HSR | AF10: =VALUE(IFERROR(MID(D10,FIND(":",D10,FIND("total_offer_discount",D10))+1,FIND(",",D10,FIND("total_offer_discount",D10)) - FIND(":",D10,FIND("total_offer_discount",D10))-1),0)) -> 0 | AG10: =DATEVALUE(E10) -> 45419 | AH10: =TIMEVALUE(E10) -> 0.99023148 | AI10: =TEXT(AG10,"dddd") -> Tuesday | AJ10: =VLOOKUP(HOUR(Orders[[#This Row],[Time]]),$AQ$1:$AR$7,2,1) -> Night | AK10: =IF(Orders[[#This Row],[rain_mode]]=0,"Sunny","Rainy") -> Sunny
A11: 174067299373268 | B11: FALSE | E11: 2024-05-07 21:31:39 | F11: 2024-05-07 21:31:57 | G11: 21191609 | H11: Delivered | I11: Vijayakumar V | J11: 437065 | K11: Theobroma | L11: SHOP NO. 475, GROUND FLOOR, 39TH "C" CROSS, 9TH MAIN, 5THBLOCK, JAYANAGAR,BANGALORE, Jayanagar ,B.B.M.P South, Karnataka,560041 | M11: 5th block | N11: Bangalore | O11: 1455 | P11: 387 | Q11: 387 | R11: 387 | S11: 275 | T11: 0 | U11: 0 | V11: 12.92017647,77.5836421 | W11: 3.2 | Y11: UPICollect | Z11: Jayanagar | AA11: TRUE | AB11: 0 | AC11: =IF(X11="","No Coupon Applied",X11) -> No Coupon Applied | AD11: =VLOOKUP(K11,'restaurant name correction'!$A$1:$B$44,2,0) -> Theobroma | AE11: =VLOOKUP(Z11,restaurant_area_correction!$A$1:$B$18,2,0) -> Jayanagar | AF11: =VALUE(IFERROR(MID(D11,FIND(":",D11,FIND("total_offer_discount",D11))+1,FIND(",",D11,FIND("total_offer_discount",D11)) - FIND(":",D11,FIND("total_offer_discount",D11))-1),0)) -> 0 | AG11: =DATEVALUE(E11) -> 45419 | AH11: =TIMEVALUE(E11) -> 0.89697917 | AI11: =TEXT(AG11,"dddd") -> Tuesday | AJ11: =VLOOKUP(HOUR(Orders[[#This Row],[Time]]),$AQ$1:$AR$7,2,1) -> Night | AK11: =IF(Orders[[#This Row],[rain_mode]]=0,"Sunny","Rainy") -> Sunny
A12: 174058332503576 | B12: TRUE | C12: SWIGGYIT | D12: [{"id":"8a02a1ac-9efe-46ea-9649-fc635c7c8618","super_type":"SUPERTYPE_UNSPECIFIED","total_offer_discount":28,"discount_share":{"swiggy_discount":0,"store_discount":28,"alliance_discount":0},"discount_type":"PERCENTAGE","description":"10% off","fixed_charges":{"gp":{"id":"","final_price":0}}}] | E12: 2024-05-07 19:02:12 | F12: 2024-05-07 19:02:53 | G12: 21191609 | H12: Delivered | I12: Gangi Reddy | J12: 534276 | K12: Naalnaad Mane | L12: 16,2ND FLOOR GOWRY'S BUILDING,ABOVE DOMINO'S,SY NO 13 OF AREKERE VILLAGE,BANNERGHATTA,BANGLAORE,jayanagar,B.B.M.PM south, karnataka - 560076 | M12: Mico Layout | N12: Bangalore | O12: 4292 | P12: 320 | Q12: 320 | R12: 320 | S12: 280 | T12: 0 | U12: 0 | V12: 12.89009167,77.5976944 | W12: 3.2 | X12: SWIGGYIT | Y12: UPICollect | Z12: Arekere | AA12: FALSE | AB12: 0 | AC12: =IF(X12="","No Coupon Applied",X12) -> SWIGGYIT | AD12: =VLOOKUP(K12,'restaurant name correction'!$A$1:$B$44,2,0) -> Naalnaad Mane | AE12: =VLOOKUP(Z12,restaurant_area_correction!$A$1:$B$18,2,0) -> Arekere | AF12: =VALUE(IFERROR(MID(D12,FIND(":",D12,FIND("total_offer_discount",D12))+1,FIND(",",D12,FIND("total_offer_discount",D12)) - FIND(":",D12,FIND("total_offer_discount",D12))-1),0)) -> 28 | AG12: =DATEVALUE(E12) -> 45419 | AH12: =TIMEVALUE(E12) -> 0.79319444 | AI12: =TEXT(AG12,"dddd") -> Tuesday | AJ12: =VLOOKUP(HOUR(Orders[[#This Row],[Time]]),$AQ$1:$AR$7,2,1) -> Evening | AK12: =IF(Orders[[#This Row],[rain_mode]]=0,"Sunny","Rainy") -> Sunny
A13: 174037702433562 | B13: TRUE | C13: TRYNEW | D13: [{"id":"5c8d9a7d-f899-4dcc-998e-d3e0b2960661","super_type":"SUPERTYPE_UNSPECIFIED","total_offer_discount":80,"discount_share":{"swiggy_discount":0,"store_discount":80,"alliance_discount":0},"discount_type":"PERCENTAGE","description":"40% off","fixed_charges":{"gp":{"id":"","final_price":0}}}] | E13: 2024-05-07 13:18:22 | F13: 2024-05-07 13:18:44 | G13: 21191609 | H13: Delivered | I13: Shiba Kairi | J13: 34363 | K13: Firangi Bake | L13: Shop No.4, Frist Floor, NGK Complex, Tavarekere Main Rd, 1st Stage, BTM Layout, Bengaluru, Karnataka 560029 ( Above DMart Ready) | M13: NGK Complex | N13: Bangalore | O13: 2730 | P13: 320 | Q13: 320 | R13: 320 | S13: 325 | T13: 0 | U13: 0 | V13: 12.920219,77.610520 | W13: 2.2 | X13: TRYNEW | Y13: UPICollect | Z13: BTM 1st Stage | AA13: FALSE | AB13: 0 | AC13: =IF(X13="","No Coupon Applied",X13) -> TRYNEW | AD13: =VLOOKUP(K13,'restaurant name correction'!$A$1:$B$44,2,0) -> Firangi Bake | AE13: =VLOOKUP(Z13,restaurant_area_correction!$A$1:$B$18,2,0) -> BTM | AF13: =VALUE(IFERROR(MID(D13,FIND(":",D13,FIND("total_offer_discount",D13))+1,FIND(",",D13,FIND("total_offer_discount",D13)) - FIND(":",D13,FIND("total_offer_discount",D13))-1),0)) -> 80 | AG13: =DATEVALUE(E13) -> 45419 | AH13: =TIMEVALUE(E13) -> 0.5544213 | AI13: =TEXT(AG13,"dddd") -> Tuesday | AJ13: =VLOOKUP(HOUR(Orders[[#This Row],[Time]]),$AQ$1:$AR$7,2,1) -> Afternoon | AK13: =IF(Orders[[#This Row],[rain_mode]]=0,"Sunny","Rainy") -> Sunny
A14: 174026206595017 | B14: TRUE | C14: SWIGGYIT | D14: [{"id":"28bf3ebb-4a69-4a92-88a4-f491a5f86e17","super_type":"SUPERTYPE_UNSPECIFIED","total_offer_discount":23.9,"discount_share":{"swiggy_discount":0,"store_discount":23.9,"alliance_discount":0},"discount_type":"PERCENTAGE","description":"10% off","fixed_charges":{"gp":{"id":"","final_price":0}}}] | E14: 2024-05-07 10:06:46 | F14: 2024-05-07 10:07:00 | G14: 21191609 | H14: Delivered | I14: Harikrishna R | J14: 630473 | K14: Rasayan | L14: 652,13th cross,29th main road BTM 2nd stage,560078, Bangalore Karnataka | M14: Health Bar | N14: Bangalore | O14: 1927 | P14: 275 | Q14: 275 | R14: 275 | S14: 239 | T14: 10 | U14: 0 | V14: 12.907799,77.613487 | W14: 2.5 | X14: SWIGGYIT | Y14: UPICollect | Z14: BTM 2nd Stage | AA14: TRUE | AB14: 0 | AC14: =IF(X14="","No Coupon Applied",X14) -> SWIGGYIT | AD14: =VLOOKUP(K14,'restaurant name correction'!$A$1:$B$44,2,0) -> Rasayan | AE14: =VLOOKUP(Z14,restaurant_area_correction!$A$1:$B$18,2,0) -> BTM | AF14: =VALUE(IFERROR(MID(D14,FIND(":",D14,FIND("total_offer_discount",D14))+1,FIND(",",D14,FIND("total_offer_discount",D14)) - FIND(":",D14,FIND("total_offer_discount",D14))-1),0)) -> 23.9 | AG14: =DATEVALUE(E14) -> 45419 | AH14: =TIMEVALUE(E14) -> 0.42136574 | AI14: =TEXT(AG14,"dddd") -> Tuesday | AJ14: =VLOOKUP(HOUR(Orders[[#This Row],[Time]]),$AQ$1:$AR$7,2,1) -> Late Morning | AK14: =IF(Orders[[#This Row],[rain_mode]]=0,"Sunny","Rainy") -> Sunny
A15: 173972919485563 | B15: TRUE | C15: SWIGGYIT | D15: [{"id":"137a1aed-678a-41ce-ac11-088fcce35f29","super_type":"SUPERTYPE_UNSPECIFIED","total_offer_discount":100,"discount_share":{"swiggy_discount":48,"store_discount":52,"alliance_discount":0},"discount_type":"PERCENTAGE","description":"50% off","fixed_charges":{"gp":{"id":"","final_price":0}}}] | E15: 2024-05-06 19:18:39 | F15: 2024-05-06 19:19:03 | G15: 21191609 | H15: Delivered | I15: Puran Singh | J15: 434304 | K15: Paris Panini - Gourmet Sandwiches & Wraps | L15: No.690/A, 14th Main, 100ft Road, JP Nagar 2nd Phase, Bangalore 560078. | M15: JP Nagar | N15: Bangalore | O15: 2041 | P15: 334 | Q15: 334 | R15: 334 | S15: 385 | T15: 42 | U15: 0 | V15: 12.90649867,77.59165435 | W15: 2.1 | X15: SWIGGYIT | Y15: UPICollect | Z15: JP Nagar | AA15: FALSE | AB15: 0 | AC15: =IF(X15="","No Coupon Applied",X15) -> SWIGGYIT | AD15: =VLOOKUP(K15,'restaurant name correction'!$A$1:$B$44,2,0) -> Paris Panini | AE15: =VLOOKUP(Z15,restaurant_area_correction!$A$1:$B$18,2,0) -> JP Nagar | AF15: =VALUE(IFERROR(MID(D15,FIND(":",D15,FIND("total_offer_discount",D15))+1,FIND(",",D15,FIND("total_offer_discount",D15)) - FIND(":",D15,FIND("total_offer_discount",D15))-1),0)) -> 100 | AG15: =DATEVALUE(E15) -> 45418 | AH15: =TIMEVALUE(E15) -> 0.80461806 | AI15: =TEXT(AG15,"dddd") -> Monday | AJ15: =VLOOKUP(HOUR(Orders[[#This Row],[Time]]),$AQ$1:$AR$7,2,1) -> Evening | AK15: =IF(Orders[[#This Row],[rain_mode]]=0,"Sunny","Rainy") -> Sunny
A16: 173961191807457 | B16: FALSE | E16: 2024-05-06 16:03:12 | F16: 2024-05-06 16:03:45 | G16: 21191609 | H16: Delivered | I16: Ash Narayan Das | J16: 694704 | K16: Love And Crumble | L16: NO 307, LALEHZAR APARTMENTS PALACE ROAD SHIVAJINAGARA B.B.M.P EAST KARNATAKA | M16: Lalehzar Apartments Palace Road | N16: Bangalore | O16: 4528 | P16: 509 | Q16: 509 | R16: 509 | S16: 370 | T16: 0 | U16: 0 | V16: 12.98505012,77.5880017 | W16: 10.2 | Y16: UPICollect | Z16: Malleshwaram | AA16: TRUE | AB16: 0 | AC16: =IF(X16="","No Coupon Applied",X16) -> No Coupon Applied | AD16: =VLOOKUP(K16,'restaurant name correction'!$A$1:$B$44,2,0) -> Love And Crumble | AE16: =VLOOKUP(Z16,restaurant_area_correction!$A$1:$B$18,2,0) -> Malleshwaram | AF16: =VALUE(IFERROR(MID(D16,FIND(":",D16,FIND("total_offer_discount",D16))+1,FIND(",",D16,FIND("total_offer_discount",D16)) - FIND(":",D16,FIND("total_offer_discount",D16))-1),0)) -> 0 | AG16: =DATEVALUE(E16) -> 45418 | AH16: =TIMEVALUE(E16) -> 0.66888889 | AI16: =TEXT(AG16,"dddd") -> Monday | AJ16: =VLOOKUP(HOUR(Orders[[#This Row],[Time]]),$AQ$1:$AR$7,2,1) -> Evening | AK16: =IF(Orders[[#This Row],[rain_mode]]=0,"Sunny","Rainy") -> Sunny
A17: 173953404362535 | B17: TRUE | C17: DEALICIOUS | D17: [{"id":"8ecc3140-454d-483f-810e-78be04d68af5","super_type":"SUPERTYPE_UNSPECIFIED","total_offer_discount":124.99,"discount_share":{"swiggy_discount":0,"store_discount":124.99,"alliance_discount":0},"discount_type":"FLAT","description":"FLAT125 off","fixed_charges":{"gp":{"id":"","final_price":0}}}] | E17: 2024-05-06 13:53:24 | F17: 2024-05-06 13:53:46 | G17: 21191609 | H17: Delivered | I17: MRITYUNJAY HALDER | J17: 34381 | K17: Firangi Bake | L17: No 87/15/638/2 Nanjappa garden, Katha no - 1785/87/15/638/2, Arekere Village, begur hobali, Bangalore South taluk, Bangalore - 560076 | M17: Begur Hobali | N17: Bangalore | O17: 3728 | P17: 556 | Q17: 556 | R17: 556 | S17: 624 | T17: 48 | U17: 0 | V17: 12.885643,77.602120 | W17: 3.4 | X17: DEALICIOUS | Y17: UPICollect | Z17: Arekere | AA17: FALSE | AB17: 0 | AC17: =IF(X17="","No Coupon Applied",X17) -> DEALICIOUS | AD17: =VLOOKUP(K17,'restaurant name correction'!$A$1:$B$44,2,0) -> Firangi Bake | AE17: =VLOOKUP(Z17,restaurant_area_correction!$A$1:$B$18,2,0) -> Arekere | AF17: =VALUE(IFERROR(MID(D17,FIND(":",D17,FIND("total_offer_discount",D17))+1,FIND(",",D17,FIND("total_offer_discount",D17)) - FIND(":",D17,FIND("total_offer_discount",D17))-1),0)) -> 124.99 | AG17: =DATEVALUE(E17) -> 45418 | AH17: =TIMEVALUE(E17) -> 0.57875 | AI17: =TEXT(AG17,"dddd") -> Monday | AJ17: =VLOOKUP(HOUR(Orders[[#This Row],[Time]]),$AQ$1:$AR$7,2,1) -> Afternoon | AK17: =IF(Orders[[#This Row],[rain_mode]]=0,"Sunny","Rainy") -> Sunny
A18: 173934793528823 | B18: TRUE | C18: SWIGGYIT | D18: [{"id":"28bf3ebb-4a69-4a92-88a4-f491a5f86e17","super_type":"SUPERTYPE_UNSPECIFIED","total_offer_discount":23.9,"discount_share":{"swiggy_discount":0,"store_discount":23.9,"alliance_discount":0},"discount_type":"PERCENTAGE","description":"10% off","fixed_charges":{"gp":{"id":"","final_price":0}}}] | E18: 2024-05-06 08:43:13 | F18: 2024-05-06 08:43:38 | G18: 21191609 | H18: Delivered | I18: THARUN N | J18: 630473 | K18: Rasayan | L18: 652,13th cross,29th main road BTM 2nd stage,560078, Bangalore Karnataka | M18: Health Bar | N18: Bangalore | O18: 2470 | P18: 242 | Q18: 242 | R18: 242 | S18: 239 | T18: 43 | U18: 0 | V18: 12.907799,77.613487 | W18: 2.5 | X18: SWIGGYIT | Y18: UPICollect | Z18: BTM 2nd Stage | AA18: FALSE | AB18: 0 | AC18: =IF(X18="","No Coupon Applied",X18) -> SWIGGYIT | AD18: =VLOOKUP(K18,'restaurant name correction'!$A$1:$B$44,2,0) -> Rasayan | AE18: =VLOOKUP(Z18,restaurant_area_correction!$A$1:$B$18,2,0) -> BTM | AF18: =VALUE(IFERROR(MID(D18,FIND(":",D18,FIND("total_offer_discount",D18))+1,FIND(",",D18,FIND("total_offer_discount",D18)) - FIND(":",D18,FIND("total_offer_discount",D18))-1),0)) -> 23.9 | AG18: =DATEVALUE(E18) -> 45418 | AH18: =TIMEVALUE(E18) -> 0.36334491 | AI18: =TEXT(AG18,"dddd") -> Monday | AJ18: =VLOOKUP(HOUR(Orders[[#This Row],[Time]]),$AQ$1:$AR$7,2,1) -> Late Morning | AK18: =IF(Orders[[#This Row],[rain_mode]]=0,"Sunny","Rainy") -> Sunny
A19: 173886476249693 | B19: TRUE | C19: SWIGGYIT | D19: [{"id":"28bf3ebb-4a69-4a92-88a4-f491a5f86e17","super_type":"SUPERTYPE_UNSPECIFIED","total_offer_discount":40,"discount_share":{"swiggy_discount":0,"store_discount":40,"alliance_discount":0},"discount_type":"PERCENTAGE","description":"10% off","fixed_charges":{"gp":{"id":"","final_price":0}}}] | E19: 2024-05-05 19:17:56 | F19: 2024-05-05 19:18:22 | G19: 21191609 | H19: Delivered | I19: SrinivasSrini | J19: 630473 | K19: Rasayan | L19: 652,13th cross,29th main road BTM 2nd stage,560078, Bangalore Karnataka | M19: Health Bar | N19: Bangalore | O19: 1594 | P19: 487 | Q19: 487 | R19: 487 | S19: 478 | T19: 36 | U19: 0 | V19: 12.907799,77.613487 | W19: 2.5 | X19: SWIGGYIT | Y19: UPICollect | Z19: BTM 2nd Stage | AA19: TRUE | AB19: 0 | AC19: =IF(X19="","No Coupon Applied",X19) -> SWIGGYIT | AD19: =VLOOKUP(K19,'restaurant name correction'!$A$1:$B$44,2,0) -> Rasayan | AE19: =VLOOKUP(Z19,restaurant_area_correction!$A$1:$B$18,2,0) -> BTM | AF19: =VALUE(IFERROR(MID(D19,FIND(":",D19,FIND("total_offer_discount",D19))+1,FIND(",",D19,FIND("total_offer_discount",D19)) - FIND(":",D19,FIND("total_offer_discount",D19))-1),0)) -> 40 | AG19: =DATEVALUE(E19) -> 45417 | AH19: =TIMEVALUE(E19) -> 0.80412037 | AI19: =TEXT(AG19,"dddd") -> Sunday | AJ19: =VLOOKUP(HOUR(Orders[[#This Row],[Time]]),$AQ$1:$AR$7,2,1) -> Evening | AK19: =IF(Orders[[#This Row],[rain_mode]]=0,"Sunny","Rainy") -> Sunny
A20: 173848012476255 | B20: TRUE | C20: JUMBO | D20: [{"id":"7b5f26f9-18b8-4c51-aed1-b1e142eba2ae","super_type":"SUPERTYPE_UNSPECIFIED","total_offer_discount":149.4,"discount_share":{"swiggy_discount":0,"store_discount":149.4,"alliance_discount":0},"discount_type":"PERCENTAGE","description":"30% off","fixed_charges":{"gp":{"id":"","final_price":0}}}] | E20: 2024-05-05 08:36:52 | F20: 2024-05-05 08:37:10 | G20: 21191609 | H20: Delivered | I20: Rajesh Kumar | J20: 630473 | K20: Rasayan | L20: 652,13th cross,29th main road BTM 2nd stage,560078, Bangalore Karnataka | M20: Health Bar | N20: Bangalore | O20: 2999 | P20: 392 | Q20: 392 | R20: 392 | S20: 498 | T20: 43 | U20: 0 | V20: 12.907799,77.613487 | W20: 2.5 | X20: JUMBO | Y20: UPICollect | Z20: BTM 2nd Stage | AA20: FALSE | AB20: 0 | AC20: =IF(X20="","No Coupon Applied",X20) -> JUMBO | AD20: =VLOOKUP(K20,'restaurant name correction'!$A$1:$B$44,2,0) -> Rasayan | AE20: =VLOOKUP(Z20,restaurant_area_correction!$A$1:$B$18,2,0) -> BTM | AF20: =VALUE(IFERROR(MID(D20,FIND(":",D20,FIND("total_offer_discount",D20))+1,FIND(",",D20,FIND("total_offer_discount",D20)) - FIND(":",D20,FIND("total_offer_discount",D20))-1),0)) -> 149.4 | AG20: =DATEVALUE(E20) -> 45417 | AH20: =TIMEVALUE(E20) -> 0.35893519 | AI20: =TEXT(AG20,"dddd") -> Sunday | AJ20: =VLOOKUP(HOUR(Orders[[#This Row],[Time]]),$AQ$1:$AR$7,2,1) -> Late Morning | AK20: =IF(Orders[[#This Row],[rain_mode]]=0,"Sunny","Rainy") -> Sunny
A21: 173787961265182 | B21: TRUE | C21: TRYNEW | D21: [{"id":"903b3cd1-104b-4bdd-94d3-96daaea1a80b","super_type":"SUPERTYPE_UNSPECIFIED","total_offer_discount":44.99,"discount_share":{"swiggy_discount":0,"store_discount":44.99,"alliance_discount":0},"discount_type":"PERCENTAGE","description":"15% off","fixed_charges":{"gp":{"id":"","final_price":0}}}] | E21: 2024-05-04 15:56:01 | F21: 2024-05-04 15:56:19 | G21: 21191609 | H21: Delivered | I21: Surendra J | J21: 534276 | K21: Naalnaad Mane | L21: 16,2ND FLOOR GOWRY'S BUILDING,ABOVE DOMINO'S,SY NO 13 OF AREKERE VILLAGE,BANNERGHATTA,BANGLAORE,jayanagar,B.B.M.PM south, karnataka - 560076 | M21: Mico Layout | N21: Bangalore | O21: 2684 | P21: 680 | Q21: 680 | R21: 680 | S21: 660 | T21: 33 | U21: 0 | V21: 12.89009167,77.5976944 | W21: 2.7 | X21: TRYNEW | Y21: UPICollect | Z21: Arekere | AA21: TRUE | AB21: 0 | AC21: =IF(X21="","No Coupon Applied",X21) -> TRYNEW | AD21: =VLOOKUP(K21,'restaurant name correction'!$A$1:$B$44,2,0) -> Naalnaad Mane | AE21: =VLOOKUP(Z21,restaurant_area_correction!$A$1:$B$18,2,0) -> Arekere | AF21: =VALUE(IFERROR(MID(D21,FIND(":",D21,FIND("total_offer_discount",D21))+1,FIND(",",D21,FIND("total_offer_discount",D21)) - FIND(":",D21,FIND("total_offer_discount",D21))-1),0)) -> 44.99 | AG21: =DATEVALUE(E21) -> 45416 | AH21: =TIMEVALUE(E21) -> 0.66390046 | AI21: =TEXT(AG21,"dddd") -> Saturday | AJ21: =VLOOKUP(HOUR(Orders[[#This Row],[Time]]),$AQ$1:$AR$7,2,1) -> Afternoon | AK21: =IF(Orders[[#This Row],[rain_mode]]=0,"Sunny","Rainy") -> Sunny
A22: 173627120783219 | B22: TRUE | C22: MISSEDYOU | D22: [{"id":"bcdcaa8c-6d73-46c7-af56-3b6dc93e207a","super_type":"SUPERTYPE_UNSPECIFIED","total_offer_discount":60,"discount_share":{"swiggy_discount":12,"store_discount":48,"alliance_discount":0},"discount_type":"PERCENTAGE","description":"30% off","fixed_charges":{"gp":{"id":"","final_price":0}}}] | E22: 2024-05-02 19:15:20 | F22: 2024-05-02 19:15:26 | G22: 21191609 | H22: Delivered | I22: KAMAL CHETRY | J22: 35953 | K22: Homely | L22: No. 135/14, 100ft Ring Road, 15th Cross, J.P.Nagar, 3rd Phase, Bengaluru.560076 | M22: 3rd Phase | N22: Bangalore | O22: 1654 | P22: 214 | Q22: 214 | R22: 214 | S22: 239 | T22: 54 | U22: 0 | V22: 12.906291,77.596256 | W22: 1.6 | X22: MISSEDYOU | Y22: Cash | Z22: JP Nagar | AA22: TRUE | AB22: 2 | AC22: =IF(X22="","No Coupon Applied",X22) -> MISSEDYOU | AD22: =VLOOKUP(K22,'restaurant name correction'!$A$1:$B$44,2,0) -> Homely | AE22: =VLOOKUP(Z22,restaurant_area_correction!$A$1:$B$18,2,0) -> JP Nagar | AF22: =VALUE(IFERROR(MID(D22,FIND(":",D22,FIND("total_offer_discount",D22))+1,FIND(",",D22,FIND("total_offer_discount",D22)) - FIND(":",D22,FIND("total_offer_discount",D22))-1),0)) -> 60 | AG22: =DATEVALUE(E22) -> 45414 | AH22: =TIMEVALUE(E22) -> 0.80231481 | AI22: =TEXT(AG22,"dddd") -> Thursday | AJ22: =VLOOKUP(HOUR(Orders[[#This Row],[Time]]),$AQ$1:$AR$7,2,1) -> Evening | AK22: =IF(Orders[[#This Row],[rain_mode]]=0,"Sunny","Rainy") -> Rainy
A23: 173528899495632 | B23: TRUE | C23: TRYNEW | D23: [{"id":"6efa58fe-50e0-4c94-aadd-f2cf8ce25c67","super_type":"SUPERTYPE_UNSPECIFIED","total_offer_discount":99.99000000000001,"discount_share":{"swiggy_discount":47.99,"store_discount":52,"alliance_discount":0},"discount_type":"PERCENTAGE","description":"50% off","fixed_charges":{"gp":{"id":"","final_price":0}}}] | E23: 2024-05-01 15:58:19 | F23: 2024-05-01 15:58:57 | G23: 21191609 | H23: Delivered | I23: Sakti Prasad Sundaray | J23: 434304 | K23: Paris Panini - Gourmet Sandwiches & Wraps | L23: No.690/A, 14th Main, 100ft Road, JP Nagar 2nd Phase, Bangalore 560078. | M23: JP Nagar | N23: Bangalore | O23: 2161 | P23: 696 | Q23: 696 | R23: 696 | S23: 680 | T23: 36 | U23: 0 | V23: 12.90649867,77.59165435 | W23: 2.1 | X23: TRYNEW | Y23: UPICollect | Z23: JP Nagar | AA23: FALSE | AB23: 0 | AC23: =IF(X23="","No Coupon Applied",X23) -> TRYNEW | AD23: =VLOOKUP(K23,'restaurant name correction'!$A$1:$B$44,2,0) -> Paris Panini | AE23: =VLOOKUP(Z23,restaurant_area_correction!$A$1:$B$18,2,0) -> JP Nagar | AF23: =VALUE(IFERROR(MID(D23,FIND(":",D23,FIND("total_offer_discount",D23))+1,FIND(",",D23,FIND("total_offer_discount",D23)) - FIND(":",D23,FIND("total_offer_discount",D23))-1),0)) -> 99.99 | AG23: =DATEVALUE(E23) -> 45413 | AH23: =TIMEVALUE(E23) -> 0.66549769 | AI23: =TEXT(AG23,"dddd") -> Wednesday | AJ23: =VLOOKUP(HOUR(Orders[[#This Row],[Time]]),$AQ$1:$AR$7,2,1) -> Afternoon | AK23: =IF(Orders[[#This Row],[rain_mode]]=0,"Sunny","Rainy") -> Sunny
A24: 173508364352211 | B24: TRUE | C24: JUMBO | D24: [{"id":"7b5f26f9-18b8-4c51-aed1-b1e142eba2ae","super_type":"SUPERTYPE_UNSPECIFIED","total_offer_discount":148.8,"discount_share":{"swiggy_discount":0,"store_discount":148.8,"alliance_discount":0},"discount_type":"PERCENTAGE","description":"30% off","fixed_charges":{"gp":{"id":"","final_price":0}}}] | E24: 2024-05-01 10:16:04 | F24: 2024-05-01 10:16:24 | G24: 21191609 | H24: Delivered | I24: Shaik Yaseen | J24: 630473 | K24: Rasayan | L24: 652,13th cross,29th main road BTM 2nd stage,560078, Bangalore Karnataka | M24: Health Bar | N24: Bangalore | O24: 2775 | P24: 399 | Q24: 399 | R24: 399 | S24: 496 | T24: 43 | U24: 0 | V24: 12.907799,77.613487 | W24: 2.5 | X24: JUMBO | Y24: UPICollect | Z24: BTM 2nd Stage | AA24: FALSE | AB24: 0 | AC24: =IF(X24="","No Coupon Applied",X24) -> JUMBO | AD24: =VLOOKUP(K24,'restaurant name correction'!$A$1:$B$44,2,0) -> Rasayan | AE24: =VLOOKUP(Z24,restaurant_area_correction!$A$1:$B$18,2,0) -> BTM | AF24: =VALUE(IFERROR(MID(D24,FIND(":",D24,FIND("total_offer_discount",D24))+1,FIND(",",D24,FIND("total_offer_discount",D24)) - FIND(":",D24,FIND("total_offer_discount",D24))-1),0)) -> 148.8 | AG24: =DATEVALUE(E24) -> 45413 | AH24: =TIMEVALUE(E24) -> 0.42782407 | AI24: =TEXT(AG24,"dddd") -> Wednesday | AJ24: =VLOOKUP(HOUR(Orders[[#This Row],[Time]]),$AQ$1:$AR$7,2,1) -> Late Morning | AK24: =IF(Orders[[#This Row],[rain_mode]]=0,"Sunny","Rainy") -> Sunny
A25: 173162395766364 | B25: TRUE | C25: JUMBO | D25: [{"id":"7b5f26f9-18b8-4c51-aed1-b1e142eba2ae","super_type":"SUPERTYPE_UNSPECIFIED","total_offer_discount":149.99,"discount_share":{"swiggy_discount":0,"store_discount":149.99,"alliance_discount":0},"discount_type":"PERCENTAGE","description":"30% off","fixed_charges":{"gp":{"id":"","final_price":0}}}] | E25: 2024-04-27 10:09:55 | F25: 2024-04-27 10:10:09 | G25: 21191609 | H25: Delivered | I25: RIYAZ AHMED | J25: 630473 | K25: Rasayan | L25: 652,13th cross,29th main road BTM 2nd stage,560078, Bangalore Karnataka | M25: Health Bar | N25: Bangalore | O25: 2197 | P25: 489 | Q25: 489 | R25: 489 | S25: 580 | T25: 43 | U25: 0 | V25: 12.907799,77.613487 | W25: 2.5 | X25: JUMBO | Y25: UPICollect | Z25: BTM 2nd Stage | AA25: FALSE | AB25: 0 | AC25: =IF(X25="","No Coupon Applied",X25) -> JUMBO | AD25: =VLOOKUP(K25,'restaurant name correction'!$A$1:$B$44,2,0) -> Rasayan | AE25: =VLOOKUP(Z25,restaurant_area_correction!$A$1:$B$18,2,0) -> BTM | AF25: =VALUE(IFERROR(MID(D25,FIND(":",D25,FIND("total_offer_discount",D25))+1,FIND(",",D25,FIND("total_offer_discount",D25)) - FIND(":",D25,FIND("total_offer_discount",D25))-1),0)) -> 149.99 | AG25: =DATEVALUE(E25) -> 45409 | AH25: =TIMEVALUE(E25) -> 0.42355324 | AI25: =TEXT(AG25,"dddd") -> Saturday | AJ25: =VLOOKUP(HOUR(Orders[[#This Row],[Time]]),$AQ$1:$AR$7,2,1) -> Late Morning | AK25: =IF(Orders[[#This Row],[rain_mode]]=0,"Sunny","Rainy") -> Sunny
A26: 173162271836174 | B26: FALSE | E26: 2024-04-27 10:07:51 | F26: 2024-04-27 10:08:09 | G26: 21191609 | H26: cancelled | I26: 0 | J26: 630473 | K26: Rasayan | L26: 652,13th cross,29th main road BTM 2nd stage,560078, Bangalore Karnataka | M26: Health Bar | N26: Bangalore | O26: 0 | P26: 646 | Q26: 646 | R26: 646 | S26: 580 | T26: 43 | U26: 0 | V26: 12.907799,77.613487 | W26: 1.9 | Y26: UPICollect | Z26: BTM 2nd Stage | AA26: FALSE | AB26: 0 | AC26: =IF(X26="","No Coupon Applied",X26) -> No Coupon Applied | AD26: =VLOOKUP(K26,'restaurant name correction'!$A$1:$B$44,2,0) -> Rasayan | AE26: =VLOOKUP(Z26,restaurant_area_correction!$A$1:$B$18,2,0) -> BTM | AF26: =VALUE(IFERROR(MID(D26,FIND(":",D26,FIND("total_offer_discount",D26))+1,FIND(",",D26,FIND("total_offer_discount",D26)) - FIND(":",D26,FIND("total_offer_discount",D26))-1),0)) -> 0 | AG26: =DATEVALUE(E26) -> 45409 | AH26: =TIMEVALUE(E26) -> 0.42211806 | AI26: =TEXT(AG26,"dddd") -> Saturday | AJ26: =VLOOKUP(HOUR(Orders[[#This Row],[Time]]),$AQ$1:$AR$7,2,1) -> Late Morning | AK26: =IF(Orders[[#This Row],[rain_mode]]=0,"Sunny","Rainy") -> Sunny
A27: 173021459533483 | B27: TRUE | C27: TRYNEW | D27: [{"id":"f90d8119-321f-4158-a454-d7576a8e0a65","super_type":"SUPERTYPE_UNSPECIFIED","total_offer_discount":75,"discount_share":{"swiggy_discount":18.75,"store_discount":56.25,"alliance_discount":0},"discount_type":"PERCENTAGE","description":"30% off","fixed_charges":{"gp":{"id":"","final_price":0}}}] | E27: 2024-04-25 19:00:59 | F27: 2024-04-25 19:01:33 | G27: 21191609 | H27: Delivered | I27: RAJESH CHETRY | J27: 260968 | K27: Chowman | L27: SAI DURGA ENCLAVE, KATHA NO 1099, AND NO 833/1, GROUND FLOOR, BELLENDUR VILLAGE, VARTHUR HOBLI, BANGALORE, Mahadevapura , B.B.M.P East, Karnataka-560037 | M27: Sai Durga Enclave | N27: Bangalore | O27: 1950 | P27: 208 | Q27: 208 | R27: 208 | S27: 260 | T27: 40 | U27: 0 | V27: 12.92314229,77.6713331 | W27: 3.3 | X27: TRYNEW | Y27: UPICollect | Z27: Bellandur | AA27: TRUE | AB27: 0 | AC27: =IF(X27="","No Coupon Applied",X27) -> TRYNEW | AD27: =VLOOKUP(K27,'restaurant name correction'!$A$1:$B$44,2,0) -> Chowman | AE27: =VLOOKUP(Z27,restaurant_area_correction!$A$1:$B$18,2,0) -> Bellandur | AF27: =VALUE(IFERROR(MID(D27,FIND(":",D27,FIND("total_offer_discount",D27))+1,FIND(",",D27,FIND("total_offer_discount",D27)) - FIND(":",D27,FIND("total_offer_discount",D27))-1),0)) -> 75 | AG27: =DATEVALUE(E27) -> 45407 | AH27: =TIMEVALUE(E27) -> 0.79234954 | AI27: =TEXT(AG27,"dddd") -> Thursday | AJ27: =VLOOKUP(HOUR(Orders[[#This Row],[Time]]),$AQ$1:$AR$7,2,1) -> Evening | AK27: =IF(Orders[[#This Row],[rain_mode]]=0,"Sunny","Rainy") -> Sunny
A28: 172937451496694 | B28: TRUE | C28: MISSEDYOU | D28: [{"id":"12337c67-3996-4380-afdd-b7cf7e3de7a3","super_type":"SUPERTYPE_UNSPECIFIED","total_offer_discount":100,"discount_share":{"swiggy_discount":48,"store_discount":52,"alliance_discount":0},"discount_type":"PERCENTAGE","description":"50% off","fixed_charges":{"gp":{"id":"","final_price":0}}}] | E28: 2024-04-24 19:40:51 | F28: 2024-04-24 19:41:11 | G28: 21191609 | H28: Delivered | I28: K Babu | J28: 742267 | K28: Paris Panini - Gourmet Sandwiches & Wraps | L28: Counter No. 23, 24 & 33, No. 53/2, Doddakannelli Village, Varthur Hobli, Bangalore, Mahadevapura , B.B.M.P East, Karnataka-560038 | M28: Sarjapur Road | N28: Bangalore | O28: 2384 | P28: 344 | Q28: 344 | R28: 344 | S28: 395 | T28: 61 | U28: 0 | V28: 12.90906249,77.68766132 | W28: 5.4 | X28: MISSEDYOU | Y28: UPICollect | Z28: Bellandur Sarjapur | AA28: TRUE | AB28: 0 | AC28: =IF(X28="","No Coupon Applied",X28) -> MISSEDYOU | AD28: =VLOOKUP(K28,'restaurant name correction'!$A$1:$B$44,2,0) -> Paris Panini | AE28: =VLOOKUP(Z28,restaurant_area_correction!$A$1:$B$18,2,0) -> Bellandur | AF28: =VALUE(IFERROR(MID(D28,FIND(":",D28,FIND("total_offer_discount",D28))+1,FIND(",",D28,FIND("total_offer_discount",D28)) - FIND(":",D28,FIND("total_offer_discount",D28))-1),0)) -> 100 | AG28: =DATEVALUE(E28) -> 45406 | AH28: =TIMEVALUE(E28) -> 0.82003472 | AI28: =TEXT(AG28,"dddd") -> Wednesday | AJ28: =VLOOKUP(HOUR(Orders[[#This Row],[Time]]),$AQ$1:$AR$7,2,1) -> Evening | AK28: =IF(Orders[[#This Row],[rain_mode]]=0,"Sunny","Rainy") -> Sunny
A29: 172865582370674 | B29: TRUE | C29: SWIGGYIT | D29: [{"id":"a95119de-61b8-489b-ad8b-1cf7a5d62a5e","super_type":"SUPERTYPE_UNSPECIFIED","total_offer_discount":50,"discount_share":{"swiggy_discount":15,"store_discount":35,"alliance_discount":0},"discount_type":"PERCENTAGE","description":"20% off","fixed_charges":{"gp":{"id":"","final_price":0}}}] | E29: 2024-04-23 23:43:02 | F29: 2024-04-23 23:43:23 | G29: 21191609 | H29: Delivered | I29: Kapsi Mohammed Tufail | J29: 29349 | K29: Frozen Bottle - Milkshakes, Desserts And Ice Cream | L29: 88, Celler Floor, 17th Cross, 14th main, Sector - 4, HSR, Bangalore | M29: HSR Layout | N29: Bangalore | O29: 1985 | P29: 301 | Q29: 301 | R29: 301 | S29: 289 | T29: 50 | U29: 0 | V29: 12.91233118,77.63839138 | W29: 1.7 | X29: SWIGGYIT | Y29: UPICollect | Z29: HSR Layout | AA29: TRUE | AB29: 0 | AC29: =IF(X29="","No Coupon Applied",X29) -> SWIGGYIT | AD29: =VLOOKUP(K29,'restaurant name correction'!$A$1:$B$44,2,0) -> Frozen Bottle | AE29: =VLOOKUP(Z29,restaurant_area_correction!$A$1:$B$18,2,0) -> HSR | AF29: =VALUE(IFERROR(MID(D29,FIND(":",D29,FIND("total_offer_discount",D29))+1,FIND(",",D29,FIND("total_offer_discount",D29)) - FIND(":",D29,FIND("total_offer_discount",D29))-1),0)) -> 50 | AG29: =DATEVALUE(E29) -> 45405 | AH29: =TIMEVALUE(E29) -> 0.98821759 | AI29: =TEXT(AG29,"dddd") -> Tuesday | AJ29: =VLOOKUP(HOUR(Orders[[#This Row],[Time]]),$AQ$1:$AR$7,2,1) -> Night | AK29: =IF(Orders[[#This Row],[rain_mode]]=0,"Sunny","Rainy") -> Sunny
A30: 172849812190412 | B30: TRUE | C30: TRYNEW | D30: [{"id":"768dad50-eef1-40d7-bfd4-5327ee71bb5a","super_type":"SUPERTYPE_UNSPECIFIED","total_offer_discount":60,"discount_share":{"swiggy_discount":0,"store_discount":60,"alliance_discount":0},"discount_type":"PERCENTAGE","description":"30% off","fixed_charges":{"gp":{"id":"","final_price":0}}}] | E30: 2024-04-23 19:20:12 | F30: 2024-04-23 19:20:29 | G30: 21191609 | H30: Delivered | I30: ANSHUMAN DAS | J30: 34366 | K30: Firangi Bake | L30: SHOP NO 2318,HSR LAYOUT SECTOR ONE,NEAR NIFT COLLEGE,BANGALORE | M30: Near NIFT College, Sector 1 | N30: Bangalore | O30: 1375 | P30: 310 | Q30: 310 | R30: 310 | S30: 325 | T30: 35 | U30: 0 | V30: 12.912101,77.65163400000006 | W30: 0.8 | X30: TRYNEW | Y30: UPICollect | Z30: HSR Layout | AA30: FALSE | AB30: 0 | AC30: =IF(X30="","No Coupon Applied",X30) -> TRYNEW | AD30: =VLOOKUP(K30,'restaurant name correction'!$A$1:$B$44,2,0) -> Firangi Bake | AE30: =VLOOKUP(Z30,restaurant_area_correction!$A$1:$B$18,2,0) -> HSR | AF30: =VALUE(IFERROR(MID(D30,FIND(":",D30,FIND("total_offer_discount",D30))+1,FIND(",",D30,FIND("total_offer_discount",D30)) - FIND(":",D30,FIND("total_offer_discount",D30))-1),0)) -> 60 | AG30: =DATEVALUE(E30) -> 45405 | AH30: =TIMEVALUE(E30) -> 0.80569444 | AI30: =TEXT(AG30,"dddd") -> Tuesday | AJ30: =VLOOKUP(HOUR(Orders[[#This Row],[Time]]),$AQ$1:$AR$7,2,1) -> Evening | AK30: =IF(Orders[[#This Row],[rain_mode]]=0,"Sunny","Rainy") -> Sunny
A31: 172765721740638 | B31: TRUE | C31: MDM150 | D31: [{"id":"24ecd13d-e27f-4858-9c2a-bdc2b708cce4","super_type":"SUPERTYPE_UNSPECIFIED","total_offer_discount":150,"discount_share":{"swiggy_discount":75,"store_discount":75,"alliance_discount":0},"discount_type":"FLAT","description":"Flat ₹150 off","fixed_charges":{"gp":{"id":"","final_price":0}}}] | E31: 2024-04-22 19:58:41 | F31: 2024-04-22 19:59:12 | G31: 21191609 | H31: Delivered | I31: SUSHIL MANDAL | J31: 17036 | K31: Leon's - Burgers & Wings (Leon Grill) | L31: No.17, Ground Floor, 18th Cross Road, 3rd Sector, HSR Layout, Bangalore. | M31: HSR Layout | N31: Bangalore | O31: 1703 | P31: 724 | Q31: 724 | R31: 724 | S31: 797.57 | T31: 35 | U31: 0 | V31: 12.91181131,77.64374963 | W31: 1.6 | X31: MDM150 | Y31: UPICollect | Z31: HSR Layout | AA31: FALSE | AB31: 0 | AC31: =IF(X31="","No Coupon Applied",X31) -> MDM150 | AD31: =VLOOKUP(K31,'restaurant name correction'!$A$1:$B$44,2,0) -> Leon's | AE31: =VLOOKUP(Z31,restaurant_area_correction!$A$1:$B$18,2,0) -> HSR | AF31: =VALUE(IFERROR(MID(D31,FIND(":",D31,FIND("total_offer_discount",D31))+1,FIND(",",D31,FIND("total_offer_discount",D31)) - FIND(":",D31,FIND("total_offer_discount",D31))-1),0)) -> 150 | AG31: =DATEVALUE(E31) -> 45404 | AH31: =TIMEVALUE(E31) -> 0.83241898 | AI31: =TEXT(AG31,"dddd") -> Monday | AJ31: =VLOOKUP(HOUR(Orders[[#This Row],[Time]]),$AQ$1:$AR$7,2,1) -> Evening | AK31: =IF(Orders[[#This Row],[rain_mode]]=0,"Sunny","Rainy") -> Sunny
A32: 172415621290914 | B32: TRUE | C32: MDM150 | D32: [{"id":"8cdbbc6c-7669-489e-b255-421d322ec80f","super_type":"SUPERTYPE_UNSPECIFIED","total_offer_discount":150,"discount_share":{"swiggy_discount":75,"store_discount":75,"alliance_discount":0},"discount_type":"FLAT","description":"Flat ₹150 off","fixed_charges":{"gp":{"id":"","final_price":0}}}] | E32: 2024-04-18 18:43:41 | F32: 2024-04-18 18:44:05 | G32: 21191609 | H32: Delivered | I32: Kundan | J32: 17036 | K32: Leon's - Burgers & Wings (Leon Grill) | L32: No.17, Ground Floor, 18th Cross Road, 3rd Sector, HSR Layout, Bangalore. | M32: HSR Layout | N32: Bangalore | O32: 1726 | P32: 252 | Q32: 252 | R32: 252 | S32: 349 | T32: 31 | U32: 0 | V32: 12.91181131,77.64374963 | W32: 0.9 | X32: MDM150 | Y32: UPICollect | Z32: HSR Layout | AA32: TRUE | AB32: 0 | AC32: =IF(X32="","No Coupon Applied",X32) -> MDM150 | AD32: =VLOOKUP(K32,'restaurant name correction'!$A$1:$B$44,2,0) -> Leon's | AE32: =VLOOKUP(Z32,restaurant_area_correction!$A$1:$B$18,2,0) -> HSR | AF32: =VALUE(IFERROR(MID(D32,FIND(":",D32,FIND("total_offer_discount",D32))+1,FIND(",",D32,FIND("total_offer_discount",D32)) - FIND(":",D32,FIND("total_offer_discount",D32))-1),0)) -> 150 | AG32: =DATEVALUE(E32) -> 45400 | AH32: =TIMEVALUE(E32) -> 0.78033565 | AI32: =TEXT(AG32,"dddd") -> Thursday | AJ32: =VLOOKUP(HOUR(Orders[[#This Row],[Time]]),$AQ$1:$AR$7,2,1) -> Evening | AK32: =IF(Orders[[#This Row],[rain_mode]]=0,"Sunny","Rainy") -> Sunny
A33: 171120236353593 | B33: TRUE | C33: MDM150 | D33: [{"id":"8cdbbc6c-7669-489e-b255-421d322ec80f","super_type":"SUPERTYPE_UNSPECIFIED","total_offer_discount":150,"discount_share":{"swiggy_discount":75,"store_discount":75,"alliance_discount":0},"discount_type":"FLAT","description":"Flat ₹150 off","fixed_charges":{"gp":{"id":"","final_price":0}}}] | E33: 2024-04-03 18:53:56 | F33: 2024-04-03 18:54:20 | G33: 21191609 | H33: Delivered | I33: chandan K | J33: 17036 | K33: Leon's - Burgers & Wings (Leon Grill) | L33: No.17, Ground Floor, 18th Cross Road, 3rd Sector, HSR Layout, Bangalore. | M33: HSR Layout | N33: Bangalore | O33: 836 | P33: 252 | Q33: 252 | R33: 252 | S33: 349 | T33: 29 | U33: 0 | V33: 12.91181131,77.64374963 | W33: 0.2 | X33: MDM150 | Y33: UPICollect | Z33: HSR Layout | AA33: TRUE | AB33: 0 | AC33: =IF(X33="","No Coupon Applied",X33) -> MDM150 | AD33: =VLOOKUP(K33,'restaurant name correction'!$A$1:$B$44,2,0) -> Leon's | AE33: =VLOOKUP(Z33,restaurant_area_correction!$A$1:$B$18,2,0) -> HSR | AF33: =VALUE(IFERROR(MID(D33,FIND(":",D33,FIND("total_offer_discount",D33))+1,FIND(",",D33,FIND("total_offer_discount",D33)) - FIND(":",D33,FIND("total_offer_discount",D33))-1),0)) -> 150 | AG33: =DATEVALUE(E33) -> 45385 | AH33: =TIMEVALUE(E33) -> 0.7874537 | AI33: =TEXT(AG33,"dddd") -> Wednesday | AJ33: =VLOOKUP(HOUR(Orders[[#This Row],[Time]]),$AQ$1:$AR$7,2,1) -> Evening | AK33: =IF(Orders[[#This Row],[rain_mode]]=0,"Sunny","Rainy") -> Sunny
A34: 170949181342493 | B34: TRUE | C34: MDM150 | D34: [{"id":"8cdbbc6c-7669-489e-b255-421d322ec80f","super_type":"SUPERTYPE_UNSPECIFIED","total_offer_discount":150,"discount_share":{"swiggy_discount":75,"store_discount":75,"alliance_discount":0},"discount_type":"FLAT","description":"Flat ₹150 off","fixed_charges":{"gp":{"id":"","final_price":0}}}] | E34: 2024-04-01 19:23:01 | F34: 2024-04-01 19:23:06 | G34: 21191609 | H34: Delivered | I34: Noor Azam | J34: 17036 | K34: Leon's - Burgers & Wings (Leon Grill) | L34: No.17, Ground Floor, 18th Cross Road, 3rd Sector, HSR Layout, Bangalore. | M34: HSR Layout | N34: Bangalore | O34: 2224 | P34: 252 | Q34: 252 | R34: 252 | S34: 349 | T34: 34 | U34: 0 | V34: 12.91181131,77.64374963 | W34: 1.6 | X34: MDM150 | Y34: Cash | Z34: HSR Layout | AA34: FALSE | AB34: 0 | AC34: =IF(X34="","No Coupon Applied",X34) -> MDM150 | AD34: =VLOOKUP(K34,'restaurant name correction'!$A$1:$B$44,2,0) -> Leon's | AE34: =VLOOKUP(Z34,restaurant_area_correction!$A$1:$B$18,2,0) -> HSR | AF34: =VALUE(IFERROR(MID(D34,FIND(":",D34,FIND("total_offer_discount",D34))+1,FIND(",",D34,FIND("total_offer_discount",D34)) - FIND(":",D34,FIND("total_offer_discount",D34))-1),0)) -> 150 | AG34: =DATEVALUE(E34) -> 45383 | AH34: =TIMEVALUE(E34) -> 0.80765046 | AI34: =TEXT(AG34,"dddd") -> Monday | AJ34: =VLOOKUP(HOUR(Orders[[#This Row],[Time]]),$AQ$1:$AR$7,2,1) -> Evening | AK34: =IF(Orders[[#This Row],[rain_mode]]=0,"Sunny","Rainy") -> Sunny
A35: 170849767634192 | B35: TRUE | C35: MDM150 | D35: [{"id":"8cdbbc6c-7669-489e-b255-421d322ec80f","super_type":"SUPERTYPE_UNSPECIFIED","total_offer_discount":150,"discount_share":{"swiggy_discount":75,"store_discount":75,"alliance_discount":0},"discount_type":"FLAT","description":"Flat ₹150 off","fixed_charges":{"gp":{"id":"","final_price":0}}}] | E35: 2024-03-31 15:46:07 | F35: 2024-03-31 15:46:25 | G35: 21191609 | H35: Delivered | I35: Bharath R | J35: 17036 | K35: Leon's - Burgers & Wings (Leon Grill) | L35: No.17, Ground Floor, 18th Cross Road, 3rd Sector, HSR Layout, Bangalore. | M35: HSR Layout | N35: Bangalore | O35: 854 | P35: 252 | Q35: 252 | R35: 252 | S35: 349 | T35: 30 | U35: 0 | V35: 12.91181131,77.64374963 | W35: 1.6 | X35: MDM150 | Y35: UPICollect | Z35: HSR Layout | AA35: TRUE | AB35: 0 | AC35: =IF(X35="","No Coupon Applied",X35) -> MDM150 | AD35: =VLOOKUP(K35,'restaurant name correction'!$A$1:$B$44,2,0) -> Leon's | AE35: =VLOOKUP(Z35,restaurant_area_correction!$A$1:$B$18,2,0) -> HSR | AF35: =VALUE(IFERROR(MID(D35,FIND(":",D35,FIND("total_offer_discount",D35))+1,FIND(",",D35,FIND("total_offer_discount",D35)) - FIND(":",D35,FIND("total_offer_discount",D35))-1),0)) -> 150 | AG35: =DATEVALUE(E35) -> 45382 | AH35: =TIMEVALUE(E35) -> 0.65702546 | AI35: =TEXT(AG35,"dddd") -> Sunday | AJ35: =VLOOKUP(HOUR(Orders[[#This Row],[Time]]),$AQ$1:$AR$7,2,1) -> Afternoon | AK35: =IF(Orders[[#This Row],[rain_mode]]=0,"Sunny","Rainy") -> Sunny
A36: 170326417874188 | B36: TRUE | C36: SWIGGYIT | D36: [{"id":"16ef3f62-96d1-48fa-977b-3851da22b190","super_type":"SUPERTYPE_UNSPECIFIED","total_offer_discount":80,"discount_share":{"swiggy_discount":20,"store_discount":60,"alliance_discount":0},"discount_type":"PERCENTAGE","description":"40% off","fixed_charges":{"gp":{"id":"","final_price":0}}}] | E36: 2024-03-25 14:23:37 | F36: 2024-03-25 14:23:54 | G36: 21191609 | H36: Delivered | I36: MAHESH BABU | J36: 2675 | K36: Subway | L36: 36, 3rd Store, 7th Sector, 14th main, HSR Layout | M36: 7th Sector | N36: Bangalore | O36: 779 | P36: 252 | Q36: 252 | R36: 252 | S36: 300 | T36: 32 | U36: 0 | V36: 12.9118135,77.637958 | W36: 0.6 | X36: SWIGGYIT | Y36: UPICollect | Z36: Hsr Layout | AA36: TRUE | AB36: 0 | AC36: =IF(X36="","No Coupon Applied",X36) -> SWIGGYIT | AD36: =VLOOKUP(K36,'restaurant name correction'!$A$1:$B$44,2,0) -> Subway | AE36: =VLOOKUP(Z36,restaurant_area_correction!$A$1:$B$18,2,0) -> HSR | AF36: =VALUE(IFERROR(MID(D36,FIND(":",D36,FIND("total_offer_discount",D36))+1,FIND(",",D36,FIND("total_offer_discount",D36)) - FIND(":",D36,FIND("total_offer_discount",D36))-1),0)) -> 80 | AG36: =DATEVALUE(E36) -> 45376 | AH36: =TIMEVALUE(E36) -> 0.5997338 | AI36: =TEXT(AG36,"dddd") -> Monday | AJ36: =VLOOKUP(HOUR(Orders[[#This Row],[Time]]),$AQ$1:$AR$7,2,1) -> Afternoon | AK36: =IF(Orders[[#This Row],[rain_mode]]=0,"Sunny","Rainy") -> Sunny
A37: 169997934599848 | B37: TRUE | C37: FLATDEAL | D37: [{"id":"20f94987-8858-4c7d-bf7b-c2ff8a327fa8","super_type":"SUPERTYPE_UNSPECIFIED","total_offer_discount":99.99,"discount_share":{"swiggy_discount":0,"store_discount":99.99,"alliance_discount":0},"discount_type":"FLAT","description":"FLAT100 off","fixed_charges":{"gp":{"id":"","final_price":0}}}] | E37: 2024-03-21 19:08:54 | F37: 2024-03-21 19:09:08 | G37: 21191609 | H37: Delivered | I37: Kumar P | J37: 2675 | K37: Subway | L37: 36, 3rd Store, 7th Sector, 14th main, HSR Layout | M37: 7th Sector | N37: Bangalore | O37: 2901 | P37: 596 | Q37: 596 | R37: 596 | S37: 649 | T37: 34 | U37: 0 | V37: 12.9118135,77.637958 | W37: 1.9 | X37: FLATDEAL | Y37: UPICollect | Z37: Hsr Layout | AA37: FALSE | AB37: 0 | AC37: =IF(X37="","No Coupon Applied",X37) -> FLATDEAL | AD37: =VLOOKUP(K37,'restaurant name correction'!$A$1:$B$44,2,0) -> Subway | AE37: =VLOOKUP(Z37,restaurant_area_correction!$A$1:$B$18,2,0) -> HSR | AF37: =VALUE(IFERROR(MID(D37,FIND(":",D37,FIND("total_offer_discount",D37))+1,FIND(",",D37,FIND("total_offer_discount",D37)) - FIND(":",D37,FIND("total_offer_discount",D37))-1),0)) -> 99.99 | AG37: =DATEVALUE(E37) -> 45372 | AH37: =TIMEVALUE(E37) -> 0.79784722 | AI37: =TEXT(AG37,"dddd") -> Thursday | AJ37: =VLOOKUP(HOUR(Orders[[#This Row],[Time]]),$AQ$1:$AR$7,2,1) -> Evening | AK37: =IF(Orders[[#This Row],[rain_mode]]=0,"Sunny","Rainy") -> Sunny
A38: 169054716176265 | B38: TRUE | C38: SWIGGYIT | D38: [{"id":"e7373c56-9ba3-49f4-be3d-f75ecf92675e","super_type":"SUPERTYPE_UNSPECIFIED","total_offer_discount":80,"discount_share":{"swiggy_discount":20,"store_discount":60,"alliance_discount":0},"discount_type":"PERCENTAGE","description":"40% off","fixed_charges":{"gp":{"id":"","final_price":0}}}] | E38: 2024-03-10 21:08:36 | F38: 2024-03-10 21:09:03 | G38: 21191609 | H38: Delivered | I38: Subrath Panda | J38: 2675 | K38: Subway | L38: 36, 3rd Store, 7th Sector, 14th main, HSR Layout | M38: 7th Sector | N38: Bangalore | O38: 4130 | P38: 251 | Q38: 251 | R38: 251 | S38: 300 | T38: 57 | U38: 0 | V38: 12.9118135,77.637958 | W38: 1.9 | X38: SWIGGYIT | Y38: UPICollect | Z38: Hsr Layout | AA38: FALSE | AB38: 0 | AC38: =IF(X38="","No Coupon Applied",X38) -> SWIGGYIT | AD38: =VLOOKUP(K38,'restaurant name correction'!$A$1:$B$44,2,0) -> Subway | AE38: =VLOOKUP(Z38,restaurant_area_correction!$A$1:$B$18,2,0) -> HSR | AF38: =VALUE(IFERROR(MID(D38,FIND(":",D38,FIND("total_offer_discount",D38))+1,FIND(",",D38,FIND("total_offer_discount",D38)) - FIND(":",D38,FIND("total_offer_discount",D38))-1),0)) -> 80 | AG38: =DATEVALUE(E38) -> 45361 | AH38: =TIMEVALUE(E38) -> 0.88097222 | AI38: =TEXT(AG38,"dddd") -> Sunday | AJ38: =VLOOKUP(HOUR(Orders[[#This Row],[Time]]),$AQ$1:$AR$7,2,1) -> Night | AK38: =IF(Orders[[#This Row],[rain_mode]]=0,"Sunny","Rainy") -> Sunny
A39: 168959031219038 | B39: TRUE | C39: SWIGGYIT | D39: [{"id":"e7373c56-9ba3-49f4-be3d-f75ecf92675e","super_type":"SUPERTYPE_UNSPECIFIED","total_offer_discount":80,"discount_share":{"swiggy_discount":20,"store_discount":60,"alliance_discount":0},"discount_type":"PERCENTAGE","description":"40% off","fixed_charges":{"gp":{"id":"","final_price":0}}}] | E39: 2024-03-09 18:33:51 | F39: 2024-03-09 18:34:15 | G39: 21191609 | H39: Delivered | I39: Sreedhar V | J39: 2675 | K39: Subway | L39: 36, 3rd Store, 7th Sector, 14th main, HSR Layout | M39: 7th Sector | N39: Bangalore | O39: 864 | P39: 302 | Q39: 302 | R39: 302 | S39: 349 | T39: 32 | U39: 0 | V39: 12.9118135,77.637958 | W39: 1.9 | X39: SWIGGYIT | Y39: UPICollect | Z39: Hsr Layout | AA39: TRUE | AB39: 0 | AC39: =IF(X39="","No Coupon Applied",X39) -> SWIGGYIT | AD39: =VLOOKUP(K39,'restaurant name correction'!$A$1:$B$44,2,0) -> Subway | AE39: =VLOOKUP(Z39,restaurant_area_correction!$A$1:$B$18,2,0) -> HSR | AF39: =VALUE(IFERROR(MID(D39,FIND(":",D39,FIND("total_offer_discount",D39))+1,FIND(",",D39,FIND("total_offer_discount",D39)) - FIND(":",D39,FIND("total_offer_discount",D39))-1),0)) -> 80 | AG39: =DATEVALUE(E39) -> 45360 | AH39: =TIMEVALUE(E39) -> 0.77350694 | AI39: =TEXT(AG39,"dddd") -> Saturday | AJ39: =VLOOKUP(HOUR(Orders[[#This Row],[Time]]),$AQ$1:$AR$7,2,1) -> Evening | AK39: =IF(Orders[[#This Row],[rain_mode]]=0,"Sunny","Rainy") -> Sunny
A40: 168877172918547 | B40: FALSE | E40: 2024-03-08 19:49:32 | F40: 2024-03-08 19:49:59 | G40: 21191609 | H40: Delivered | I40: BIRENDRA DHAMI | J40: 464830 | K40: Bowl Soul | L40: No 526/A,Ganesh Complex,Ground floor,18th Main Road,HSR 3rd sector,Bangalore:560102 | M40: 3rd Sector | N40: Bangalore | O40: 2660 | P40: 154 | Q40: 154 | R40: 154 | S40: 249 | T40: 36 | U40: 0 | V40: 12.9054065,77.64410799999996 | W40: 1.8 | Y40: UPICollect | Z40: HSR Layout | AA40: FALSE | AB40: 0 | AC40: =IF(X40="","No Coupon Applied",X40) -> No Coupon Applied | AD40: =VLOOKUP(K40,'restaurant name correction'!$A$1:$B$44,2,0) -> Bowl Soul | AE40: =VLOOKUP(Z40,restaurant_area_correction!$A$1:$B$18,2,0) -> HSR | AF40: =VALUE(IFERROR(MID(D40,FIND(":",D40,FIND("total_offer_discount",D40))+1,FIND(",",D40,FIND("total_offer_discount",D40)) - FIND(":",D40,FIND("total_offer_discount",D40))-1),0)) -> 0 | AG40: =DATEVALUE(E40) -> 45359 | AH40: =TIMEVALUE(E40) -> 0.82606481 | AI40: =TEXT(AG40,"dddd") -> Friday | AJ40: =VLOOKUP(HOUR(Orders[[#This Row],[Time]]),$AQ$1:$AR$7,2,1) -> Evening | AK40: =IF(Orders[[#This Row],[rain_mode]]=0,"Sunny","Rainy") -> Sunny
A41: 168622214022977 | B41: TRUE | C41: SWIGGYIT | D41: [{"id":"68fb12f6-cd47-465f-8695-896e48e6c41d","super_type":"SUPERTYPE_UNSPECIFIED","total_offer_discount":80,"discount_share":{"swiggy_discount":20,"store_discount":60,"alliance_discount":0},"discount_type":"PERCENTAGE","description":"40% off","fixed_charges":{"gp":{"id":"","final_price":0}}}] | E41: 2024-03-05 21:00:14 | F41: 2024-03-05 21:00:40 | G41: 21191609 | H41: Delivered | I41: bhagyavanth | J41: 2675 | K41: Subway | L41: 36, 3rd Store, 7th Sector, 14th main, HSR Layout | M41: 7th Sector | N41: Bangalore | O41: 2107 | P41: 302 | Q41: 302 | R41: 302 | S41: 349 | T41: 36 | U41: 0 | V41: 12.9118135,77.637958 | W41: 1.7 | X41: SWIGGYIT | Y41: UPICollect | Z41: Hsr Layout | AA41: TRUE | AB41: 0 | AC41: =IF(X41="","No Coupon Applied",X41) -> SWIGGYIT | AD41: =VLOOKUP(K41,'restaurant name correction'!$A$1:$B$44,2,0) -> Subway | AE41: =VLOOKUP(Z41,restaurant_area_correction!$A$1:$B$18,2,0) -> HSR | AF41: =VALUE(IFERROR(MID(D41,FIND(":",D41,FIND("total_offer_discount",D41))+1,FIND(",",D41,FIND("total_offer_discount",D41)) - FIND(":",D41,FIND("total_offer_discount",D41))-1),0)) -> 80 | AG41: =DATEVALUE(E41) -> 45356 | AH41: =TIMEVALUE(E41) -> 0.87516204 | AI41: =TEXT(AG41,"dddd") -> Tuesday | AJ41: =VLOOKUP(HOUR(Orders[[#This Row],[Time]]),$AQ$1:$AR$7,2,1) -> Night | AK41: =IF(Orders[[#This Row],[rain_mode]]=0,"Sunny","Rainy") -> Sunny
A42: 168513609258675 | B42: FALSE | E42: 2024-03-04 14:50:09 | F42: 2024-03-04 14:50:43 | G42: 21191609 | H42: Delivered | I42: BHARKATH ALI A | J42: 18973 | K42: Nandhana Palace | L42: Koramangala, 7, Mahakavi Vemana Rd, KHB Block Koramangala, Koramangala 4-B Block, Koramangala, Bengaluru, Karnataka 560034 | M42: Koramangala | N42: Bangalore | O42: 3667 | P42: 537 | Q42: 537 | R42: 537 | S42: 525 | T42: 44 | U42: 0 | V42: 12.93171741,77.6229908 | W42: 4.8 | Y42: UPICollect | Z42: Koramangala | AA42: FALSE | AB42: 0 | AC42: =IF(X42="","No Coupon Applied",X42) -> No Coupon Applied | AD42: =VLOOKUP(K42,'restaurant name correction'!$A$1:$B$44,2,0) -> Nandhana Palace | AE42: =VLOOKUP(Z42,restaurant_area_correction!$A$1:$B$18,2,0) -> Koramangala | AF42: =VALUE(IFERROR(MID(D42,FIND(":",D42,FIND("total_offer_discount",D42))+1,FIND(",",D42,FIND("total_offer_discount",D42)) - FIND(":",D42,FIND("total_offer_discount",D42))-1),0)) -> 0 | AG42: =DATEVALUE(E42) -> 45355 | AH42: =TIMEVALUE(E42) -> 0.61815972 | AI42: =TEXT(AG42,"dddd") -> Monday | AJ42: =VLOOKUP(HOUR(Orders[[#This Row],[Time]]),$AQ$1:$AR$7,2,1) -> Afternoon | AK42: =IF(Orders[[#This Row],[rain_mode]]=0,"Sunny","Rainy") -> Sunny
A43: 168438354785516 | B43: FALSE | E43: 2024-03-03 17:55:54 | F43: 2024-03-03 17:56:20 | G43: 21191609 | H43: Delivered | I43: KESHAV RAJ BHATTA | J43: 254655 | K43: Daily Sushi | L43: No.1212, SBM Fortune, 4th Floor, 22nd Cross Road, 14th Main Rd, 3rd Sector, HSR Layout, Bengaluru, Karnataka 560102, India | M43: 3rd Sector | N43: Bangalore | O43: 1348 | P43: 466 | Q43: 466 | R43: 466 | S43: 400 | T43: 39 | U43: 0 | V43: 12.90942041,77.63866215 | W43: 2.1 | Y43: UPICollect | Z43: HSR Layout | AA43: TRUE | AB43: 0 | AC43: =IF(X43="","No Coupon Applied",X43) -> No Coupon Applied | AD43: =VLOOKUP(K43,'restaurant name correction'!$A$1:$B$44,2,0) -> Daily Sushi | AE43: =VLOOKUP(Z43,restaurant_area_correction!$A$1:$B$18,2,0) -> HSR | AF43: =VALUE(IFERROR(MID(D43,FIND(":",D43,FIND("total_offer_discount",D43))+1,FIND(",",D43,FIND("total_offer_discount",D43)) - FIND(":",D43,FIND("total_offer_discount",D43))-1),0)) -> 0 | AG43: =DATEVALUE(E43) -> 45354 | AH43: =TIMEVALUE(E43) -> 0.74715278 | AI43: =TEXT(AG43,"dddd") -> Sunday | AJ43: =VLOOKUP(HOUR(Orders[[#This Row],[Time]]),$AQ$1:$AR$7,2,1) -> Evening | AK43: =IF(Orders[[#This Row],[rain_mode]]=0,"Sunny","Rainy") -> Sunny
A44: 168293863851738 | B44: FALSE | E44: 2024-03-02 01:47:43 | F44: 2024-03-02 01:49:00 | G44: 21191609 | H44: Delivered | I44: DEBAJIT SAHA | J44: 621134 | K44: Sundae Everyday Ice Creams | L44: Bharadwaj Ventures No.2007,Next to Park Villa, Behind Amul Parlour, Near Venkateshwara College, Vidya Nagar, Bengaluru North 562157, Bangalore North, Bangalore Urban, Karnataka-562157 | M44: Vidya Nagar | N44: Bangalore | O44: 1954 | P44: 568 | Q44: 568 | R44: 568 | S44: 518 | T44: 67 | U44: 0 | V44: 13.16024,77.6351 | W44: 5.1 | Y44: UPICollect | Z44: Yelahanka | AA44: TRUE | AB44: 0 | AC44: =IF(X44="","No Coupon Applied",X44) -> No Coupon Applied | AD44: =VLOOKUP(K44,'restaurant name correction'!$A$1:$B$44,2,0) -> Sundae Everyday Ice Creams | AE44: =VLOOKUP(Z44,restaurant_area_correction!$A$1:$B$18,2,0) -> Yelahanka | AF44: =VALUE(IFERROR(MID(D44,FIND(":",D44,FIND("total_offer_discount",D44))+1,FIND(",",D44,FIND("total_offer_discount",D44)) - FIND(":",D44,FIND("total_offer_discount",D44))-1),0)) -> 0 | AG44: =DATEVALUE(E44) -> 45353 | AH44: =TIMEVALUE(E44) -> 0.074803241 | AI44: =TEXT(AG44,"dddd") -> Saturday | AJ44: =VLOOKUP(HOUR(Orders[[#This Row],[Time]]),$AQ$1:$AR$7,2,1) -> Early Morning | AK44: =IF(Orders[[#This Row],[rain_mode]]=0,"Sunny","Rainy") -> Sunny
A45: 168028113662672 | B45: TRUE | C45: SWIGGYIT | D45: [{"id":"ba56dab2-1b4c-454a-87c7-66ccaab3091f","super_type":"SUPERTYPE_UNSPECIFIED","total_offer_discount":20.9,"discount_share":{"swiggy_discount":0,"store_discount":20.9,"alliance_discount":0},"discount_type":"PERCENTAGE","description":"10% off","fixed_charges":{"gp":{"id":"","final_price":0}}}] | E45: 2024-02-27 23:58:33 | F45: 2024-02-27 23:58:54 | G45: 21191609 | H45: Delivered | I45: Md Majir Uddin Hachayini | J45: 647582 | K45: Smoky Docky | L45: 130, 17th H Main Rd, KHB Colony, M.I.G, 5th Block, Koramangala, Bengaluru, Karnataka 560095, India | M45: Koramangala | N45: Bangalore | O45: 1074 | P45: 212 | Q45: 212 | R45: 212 | S45: 209 | T45: 66 | U45: 0 | V45: 12.934678,77.616812 | W45: 5.9 | X45: SWIGGYIT | Y45: UPICollect | Z45: Koramangala | AA45: TRUE | AB45: 0 | AC45: =IF(X45="","No Coupon Applied",X45) -> SWIGGYIT | AD45: =VLOOKUP(K45,'restaurant name correction'!$A$1:$B$44,2,0) -> Smoky Docky | AE45: =VLOOKUP(Z45,restaurant_area_correction!$A$1:$B$18,2,0) -> Koramangala | AF45: =VALUE(IFERROR(MID(D45,FIND(":",D45,FIND("total_offer_discount",D45))+1,FIND(",",D45,FIND("total_offer_discount",D45)) - FIND(":",D45,FIND("total_offer_discount",D45))-1),0)) -> 20.9 | AG45: =DATEVALUE(E45) -> 45349 | AH45: =TIMEVALUE(E45) -> 0.99899306 | AI45: =TEXT(AG45,"dddd") -> Tuesday | AJ45: =VLOOKUP(HOUR(Orders[[#This Row],[Time]]),$AQ$1:$AR$7,2,1) -> Night | AK45: =IF(Orders[[#This Row],[rain_mode]]=0,"Sunny","Rainy") -> Sunny
A46: 168013539245633 | B46: TRUE | C46: SWIGGYIT | D46: [{"id":"5ba597b1-287c-4335-9317-451a632f4519","super_type":"SUPERTYPE_UNSPECIFIED","total_offer_discount":75,"discount_share":{"swiggy_discount":18.75,"store_discount":56.25,"alliance_discount":0},"discount_type":"PERCENTAGE","description":"30% off","fixed_charges":{"gp":{"id":"","final_price":0}}}] | E46: 2024-02-27 19:55:39 | F46: 2024-02-27 19:56:01 | G46: 21191609 | H46: Delivered | I46: Dipak Basnet | J46: 656392 | K46: Subway | L46: CNA Arcade, Ground Floor, No. 37, 1st Main, 1st Block, Koramangala, Bangalore-560034 | M46: 1st Block | N46: Bangalore | O46: 1143 | P46: 307 | Q46: 307 | R46: 307 | S46: 349 | T46: 43 | U46: 0 | V46: 12.928999,77.635218 | W46: 3.4 | X46: SWIGGYIT | Y46: UPICollect | Z46: Koramangala | AA46: TRUE | AB46: 0 | AC46: =IF(X46="","No Coupon Applied",X46) -> SWIGGYIT | AD46: =VLOOKUP(K46,'restaurant name correction'!$A$1:$B$44,2,0) -> Subway | AE46: =VLOOKUP(Z46,restaurant_area_correction!$A$1:$B$18,2,0) -> Koramangala | AF46: =VALUE(IFERROR(MID(D46,FIND(":",D46,FIND("total_offer_discount",D46))+1,FIND(",",D46,FIND("total_offer_discount",D46)) - FIND(":",D46,FIND("total_offer_discount",D46))-1),0)) -> 75 | AG46: =DATEVALUE(E46) -> 45349 | AH46: =TIMEVALUE(E46) -> 0.8303125 | AI46: =TEXT(AG46,"dddd") -> Tuesday | AJ46: =VLOOKUP(HOUR(Orders[[#This Row],[Time]]),$AQ$1:$AR$7,2,1) -> Evening | AK46: =IF(Orders[[#This Row],[rain_mode]]=0,"Sunny","Rainy") -> Sunny
A47: 167927988529759 | B47: TRUE | C47: SWIGGYIT | D47: [{"id":"ba56dab2-1b4c-454a-87c7-66ccaab3091f","super_type":"SUPERTYPE_UNSPECIFIED","total_offer_discount":20.9,"discount_share":{"swiggy_discount":0,"store_discount":20.9,"alliance_discount":0},"discount_type":"PERCENTAGE","description":"10% off","fixed_charges":{"gp":{"id":"","final_price":0}}}] | E47: 2024-02-26 20:09:48 | F47: 2024-02-26 20:12:01 | G47: 21191609 | H47: Delivered | I47: Rajendra Sahoo | J47: 647582 | K47: Smoky Docky | L47: 130, 17th H Main Rd, KHB Colony, M.I.G, 5th Block, Koramangala, Bengaluru, Karnataka 560095, India | M47: Koramangala | N47: Bangalore | O47: 2408 | P47: 212 | Q47: 212 | R47: 212 | S47: 209 | T47: 60 | U47: 0 | V47: 12.934678,77.616812 | W47: 5.9 | X47: SWIGGYIT | Y47: UPICollect | Z47: Koramangala | AA47: FALSE | AB47: 0 | AC47: =IF(X47="","No Coupon Applied",X47) -> SWIGGYIT | AD47: =VLOOKUP(K47,'restaurant name correction'!$A$1:$B$44,2,0) -> Smoky Docky | AE47: =VLOOKUP(Z47,restaurant_area_correction!$A$1:$B$18,2,0) -> Koramangala | AF47: =VALUE(IFERROR(MID(D47,FIND(":",D47,FIND("total_offer_discount",D47))+1,FIND(",",D47,FIND("total_offer_discount",D47)) - FIND(":",D47,FIND("total_offer_discount",D47))-1),0)) -> 20.9 | AG47: =DATEVALUE(E47) -> 45348 | AH47: =TIMEVALUE(E47) -> 0.84013889 | AI47: =TEXT(AG47,"dddd") -> Monday | AJ47: =VLOOKUP(HOUR(Orders[[#This Row],[Time]]),$AQ$1:$AR$7,2,1) -> Night | AK47: =IF(Orders[[#This Row],[rain_mode]]=0,"Sunny","Rainy") -> Sunny
A48: 167230102604894 | B48: TRUE | C48: SWIGGYIT | D48: [{"id":"c43b8888-f483-43af-9935-7d4034582849","super_type":"SUPERTYPE_UNSPECIFIED","total_offer_discount":35.7,"discount_share":{"swiggy_discount":0,"store_discount":35.7,"alliance_discount":0},"discount_type":"PERCENTAGE","description":"10% off","fixed_charges":{"gp":{"id":"","final_price":0}}}] | E48: 2024-02-18 18:18:22 | F48: 2024-02-18 18:18:57 | G48: 21191609 | H48: Delivered | I48: ChandraSheaker Raju | J48: 144115 | K48: The Ganache Factory - Cakes & Desserts | L48: Parcel 5 Food Court, Embassy Tech Village, Outer Ring Road, Near New Horizon College, Devarabeesanahalli, Varthur Hobli, Bangalore , Mahadevapura , B.B.M.P East, Karnataka-560103 | M48: Bellandur Sarjapur | N48: Bangalore | O48: 2856 | P48: 341 | Q48: 341 | R48: 341 | S48: 357 | T48: 77 | U48: 0 | V48: 12.927366,77.692146 | W48: 6.2 | X48: SWIGGYIT | Y48: UPICollect | Z48: Devarabeesanahalli | AA48: FALSE | AB48: 0 | AC48: =IF(X48="","No Coupon Applied",X48) -> SWIGGYIT | AD48: =VLOOKUP(K48,'restaurant name correction'!$A$1:$B$44,2,0) -> The Ganache Factory | AE48: =VLOOKUP(Z48,restaurant_area_correction!$A$1:$B$18,2,0) -> Devarabeesanahalli | AF48: =VALUE(IFERROR(MID(D48,FIND(":",D48,FIND("total_offer_discount",D48))+1,FIND(",",D48,FIND("total_offer_discount",D48)) - FIND(":",D48,FIND("total_offer_discount",D48))-1),0)) -> 35.7 | AG48: =DATEVALUE(E48) -> 45340 | AH48: =TIMEVALUE(E48) -> 0.76275463 | AI48: =TEXT(AG48,"dddd") -> Sunday | AJ48: =VLOOKUP(HOUR(Orders[[#This Row],[Time]]),$AQ$1:$AR$7,2,1) -> Evening | AK48: =IF(Orders[[#This Row],[rain_mode]]=0,"Sunny","Rainy") -> Sunny
A49: 167065261006312 | B49: FALSE | E49: 2024-02-16 20:31:01 | F49: 2024-02-16 20:31:06 | G49: 21191609 | H49: Delivered | I49: MUJAHIDUL ISLAM LASKAR | J49: 254655 | K49: Daily Sushi | L49: No.1212, SBM Fortune, 4th Floor, 22nd Cross Road, 14th Main Rd, 3rd Sector, HSR Layout, Bengaluru, Karnataka 560102, India | M49: 3rd Sector | N49: Bangalore | O49: 1383 | P49: 650 | Q49: 650 | R49: 650 | S49: 560 | T49: 43 | U49: 0 | V49: 12.90942041,77.63866215 | W49: 2 | Y49: Cash | Z49: HSR Layout | AA49: TRUE | AB49: 0 | AC49: =IF(X49="","No Coupon Applied",X49) -> No Coupon Applied | AD49: =VLOOKUP(K49,'restaurant name correction'!$A$1:$B$44,2,0) -> Daily Sushi | AE49: =VLOOKUP(Z49,restaurant_area_correction!$A$1:$B$18,2,0) -> HSR | AF49: =VALUE(IFERROR(MID(D49,FIND(":",D49,FIND("total_offer_discount",D49))+1,FIND(",",D49,FIND("total_offer_discount",D49)) - FIND(":",D49,FIND("total_offer_discount",D49))-1),0)) -> 0 | AG49: =DATEVALUE(E49) -> 45338 | AH49: =TIMEVALUE(E49) -> 0.85487269 | AI49: =TEXT(AG49,"dddd") -> Friday | AJ49: =VLOOKUP(HOUR(Orders[[#This Row],[Time]]),$AQ$1:$AR$7,2,1) -> Night | AK49: =IF(Orders[[#This Row],[rain_mode]]=0,"Sunny","Rainy") -> Sunny
A50: 167041647226680 | B50: TRUE | C50: SWIGGYIT | D50: [{"id":"14a3b6c3-fe74-4f29-9b89-a2368550fb25","super_type":"SUPERTYPE_UNSPECIFIED","total_offer_discount":80,"discount_share":{"swiggy_discount":20,"store_discount":60,"alliance_discount":0},"discount_type":"PERCENTAGE","description":"40% off","fixed_charges":{"gp":{"id":"","final_price":0}}}] | E50: 2024-02-16 13:57:27 | F50: 2024-02-16 13:57:55 | G50: 21191609 | H50: Delivered | I50: Jitendra Kumar Nayak | J50: 2675 | K50: Subway | L50: 36, 3rd Store, 7th Sector, 14th main, HSR Layout | M50: 7th Sector | N50: Bangalore | O50: 1410 | P50: 302 | Q50: 302 | R50: 302 | S50: 349 | T50: 31 | U50: 0 | V50: 12.9118135,77.637958 | W50: 1.9 | X50: SWIGGYIT | Y50: UPICollect | Z50: Hsr Layout | AA50: TRUE | AB50: 0 | AC50: =IF(X50="","No Coupon Applied",X50) -> SWIGGYIT | AD50: =VLOOKUP(K50,'restaurant name correction'!$A$1:$B$44,2,0) -> Subway | AE50: =VLOOKUP(Z50,restaurant_area_correction!$A$1:$B$18,2,0) -> HSR | AF50: =VALUE(IFERROR(MID(D50,FIND(":",D50,FIND("total_offer_discount",D50))+1,FIND(",",D50,FIND("total_offer_discount",D50)) - FIND(":",D50,FIND("total_offer_discount",D50))-1),0)) -> 80 | AG50: =DATEVALUE(E50) -> 45338 | AH50: =TIMEVALUE(E50) -> 0.5815625 | AI50: =TEXT(AG50,"dddd") -> Friday | AJ50: =VLOOKUP(HOUR(Orders[[#This Row],[Time]]),$AQ$1:$AR$7,2,1) -> Afternoon | AK50: =IF(Orders[[#This Row],[rain_mode]]=0,"Sunny","Rainy") -> Sunny
A51: 166952305677312 | B51: TRUE | C51: SWIGGYIT | D51: [{"id":"c43b8888-f483-43af-9935-7d4034582849","super_type":"SUPERTYPE_UNSPECIFIED","total_offer_discount":40,"discount_share":{"swiggy_discount":0,"store_discount":40,"alliance_discount":0},"discount_type":"PERCENTAGE","description":"10% off","fixed_charges":{"gp":{"id":"","final_price":0}}}] | E51: 2024-02-15 13:08:25 | F51: 2024-02-15 13:08:43 | G51: 21191609 | H51: Delivered | I51: Naresh C | J51: 144115 | K51: The Ganache Factory - Cakes & Desserts | L51: Parcel 5 Food Court, Embassy Tech Village, Outer Ring Road, Near New Horizon College, Devarabeesanahalli, Varthur Hobli, Bangalore , Mahadevapura , B.B.M.P East, Karnataka-560103 | M51: Bellandur Sarjapur | N51: Bangalore | O51: 2633 | P51: 809 | Q51: 809 | R51: 809 | S51: 787.5 | T51: 79 | U51: 0 | V51: 12.927366,77.692146 | W51: 7.1 | X51: SWIGGYIT | Y51: UPICollect | Z51: Devarabeesanahalli | AA51: TRUE | AB51: 0 | AC51: =IF(X51="","No Coupon Applied",X51) -> SWIGGYIT | AD51: =VLOOKUP(K51,'restaurant name correction'!$A$1:$B$44,2,0) -> The Ganache Factory | AE51: =VLOOKUP(Z51,restaurant_area_correction!$A$1:$B$18,2,0) -> Devarabeesanahalli | AF51: =VALUE(IFERROR(MID(D51,FIND(":",D51,FIND("total_offer_discount",D51))+1,FIND(",",D51,FIND("total_offer_discount",D51)) - FIND(":",D51,FIND("total_offer_discount",D51))-1),0)) -> 40 | AG51: =DATEVALUE(E51) -> 45337 | AH51: =TIMEVALUE(E51) -> 0.54751157 | AI51: =TEXT(AG51,"dddd") -> Thursday | AJ51: =VLOOKUP(HOUR(Orders[[#This Row],[Time]]),$AQ$1:$AR$7,2,1) -> Afternoon | AK51: =IF(Orders[[#This Row],[rain_mode]]=0,"Sunny","Rainy") -> Sunny
A52: 166803724653459 | B52: TRUE | C52: SWIGGYIT | D52: [{"id":"14a3b6c3-fe74-4f29-9b89-a2368550fb25","super_type":"SUPERTYPE_UNSPECIFIED","total_offer_discount":80,"discount_share":{"swiggy_discount":20,"store_discount":60,"alliance_discount":0},"discount_type":"PERCENTAGE","description":"40% off","fixed_charges":{"gp":{"id":"","final_price":0}}}] | E52: 2024-02-13 19:52:04 | F52: 2024-02-13 19:52:39 | G52: 21191609 | H52: Delivered | I52: SANJIT TATUA | J52: 2675 | K52: Subway | L52: 36, 3rd Store, 7th Sector, 14th main, HSR Layout | M52: 7th Sector | N52: Bangalore | O52: 2219 | P52: 198 | Q52: 198 | R52: 198 | S52: 250 | T52: 34 | U52: 0 | V52: 12.9118135,77.637958 | W52: 1.9 | X52: SWIGGYIT | Y52: UPICollect | Z52: Hsr Layout | AA52: FALSE | AB52: 0 | AC52: =IF(X52="","No Coupon Applied",X52) -> SWIGGYIT | AD52: =VLOOKUP(K52,'restaurant name correction'!$A$1:$B$44,2,0) -> Subway | AE52: =VLOOKUP(Z52,restaurant_area_correction!$A$1:$B$18,2,0) -> HSR | AF52: =VALUE(IFERROR(MID(D52,FIND(":",D52,FIND("total_offer_discount",D52))+1,FIND(",",D52,FIND("total_offer_discount",D52)) - FIND(":",D52,FIND("total_offer_discount",D52))-1),0)) -> 80 | AG52: =DATEVALUE(E52) -> 45335 | AH52: =TIMEVALUE(E52) -> 0.82782407 | AI52: =TEXT(AG52,"dddd") -> Tuesday | AJ52: =VLOOKUP(HOUR(Orders[[#This Row],[Time]]),$AQ$1:$AR$7,2,1) -> Evening | AK52: =IF(Orders[[#This Row],[rain_mode]]=0,"Sunny","Rainy") -> Sunny
A53: 165960896748502 | B53: TRUE | C53: TRYNEW | D53: [{"id":"a06ad688-47c7-4d07-b1e6-983b5c122814","super_type":"SUPERTYPE_UNSPECIFIED","total_offer_discount":111.6,"discount_share":{"swiggy_discount":22.32,"store_discount":89.28,"alliance_discount":0},"discount_type":"PERCENTAGE","description":"60% off","fixed_charges":{"gp":{"id":"","final_price":0}}}] | E53: 2024-02-04 01:44:56 | F53: 2024-02-04 01:45:34 | G53: 21191609 | H53: Delivered | I53: VIVEK KANTU RATHOD | J53: 418488 | K53: NOTO - Ice Creams & Desserts | L53: #345, kaikondrahalli Sarjapura main road Bangalore 560056, Mahadevpura, B.B.M.P East, Karnataka - 560056 | M53: Kaikondrahalli | N53: Bangalore | O53: 805 | P53: 115 | Q53: 115 | R53: 115 | S53: 186 | T53: 50 | U53: 0 | V53: 12.913087,77.678681 | W53: 4.4 | X53: TRYNEW | Y53: UPICollect | Z53: Bellandur Sarjapur | AA53: TRUE | AB53: 0 | AC53: =IF(X53="","No Coupon Applied",X53) -> TRYNEW | AD53: =VLOOKUP(K53,'restaurant name correction'!$A$1:$B$44,2,0) -> NOTO | AE53: =VLOOKUP(Z53,restaurant_area_correction!$A$1:$B$18,2,0) -> Bellandur | AF53: =VALUE(IFERROR(MID(D53,FIND(":",D53,FIND("total_offer_discount",D53))+1,FIND(",",D53,FIND("total_offer_discount",D53)) - FIND(":",D53,FIND("total_offer_discount",D53))-1),0)) -> 111.6 | AG53: =DATEVALUE(E53) -> 45326 | AH53: =TIMEVALUE(E53) -> 0.07287037 | AI53: =TEXT(AG53,"dddd") -> Sunday | AJ53: =VLOOKUP(HOUR(Orders[[#This Row],[Time]]),$AQ$1:$AR$7,2,1) -> Early Morning | AK53: =IF(Orders[[#This Row],[rain_mode]]=0,"Sunny","Rainy") -> Sunny
A54: 165923274381702 | B54: FALSE | E54: 2024-02-03 15:17:54 | F54: 2024-02-03 15:18:26 | G54: 21191609 | H54: Delivered | I54: Satish kumar | J54: 422128 | K54: Baba Ganoush | L54: KORMANGALA, 6th block, 80ft main road Shop no 2, NA chambers 2 , 478, 6th Block, Koramangala, Bengaluru, Karnataka 560095, India | M54: 6th Block | N54: Bangalore | O54: 1851 | P54: 222 | Q54: 222 | R54: 222 | S54: 199 | T54: 46 | U54: 0 | V54: 12.9398836,77.6252951 | W54: 5 | Y54: UPICollect | Z54: Koramangala | AA54: FALSE | AB54: 0 | AC54: =IF(X54="","No Coupon Applied",X54) -> No Coupon Applied | AD54: =VLOOKUP(K54,'restaurant name correction'!$A$1:$B$44,2,0) -> Baba Ganoush | AE54: =VLOOKUP(Z54,restaurant_area_correction!$A$1:$B$18,2,0) -> Koramangala | AF54: =VALUE(IFERROR(MID(D54,FIND(":",D54,FIND("total_offer_discount",D54))+1,FIND(",",D54,FIND("total_offer_discount",D54)) - FIND(":",D54,FIND("total_offer_discount",D54))-1),0)) -> 0 | AG54: =DATEVALUE(E54) -> 45325 | AH54: =TIMEVALUE(E54) -> 0.63743056 | AI54: =TEXT(AG54,"dddd") -> Saturday | AJ54: =VLOOKUP(HOUR(Orders[[#This Row],[Time]]),$AQ$1:$AR$7,2,1) -> Afternoon | AK54: =IF(Orders[[#This Row],[rain_mode]]=0,"Sunny","Rainy") -> Sunny
A55: 165854296189400 | B55: TRUE | C55: SWIGGYIT | D55: [{"id":"ba56dab2-1b4c-454a-87c7-66ccaab3091f","super_type":"SUPERTYPE_UNSPECIFIED","total_offer_discount":20.9,"discount_share":{"swiggy_discount":0,"store_discount":20.9,"alliance_discount":0},"discount_type":"PERCENTAGE","description":"10% off","fixed_charges":{"gp":{"id":"","final_price":0}}}] | E55: 2024-02-02 20:08:16 | F55: 2024-02-02 20:09:12 | G55: 21191609 | H55: Delivered | I55: yogeesha s | J55: 647582 | K55: Smoky Docky | L55: 130, 17th H Main Rd, KHB Colony, M.I.G, 5th Block, Koramangala, Bengaluru, Karnataka 560095, India | M55: KHB Colony | N55: Bangalore | O55: 3484 | P55: 212 | Q55: 212 | R55: 212 | S55: 209 | T55: 56 | U55: 0 | V55: 12.934678,77.616812 | W55: 5.9 | X55: SWIGGYIT | Y55: UPICollect | Z55: Koramangala | AA55: FALSE | AB55: 0 | AC55: =IF(X55="","No Coupon Applied",X55) -> SWIGGYIT | AD55: =VLOOKUP(K55,'restaurant name correction'!$A$1:$B$44,2,0) -> Smoky Docky | AE55: =VLOOKUP(Z55,restaurant_area_correction!$A$1:$B$18,2,0) -> Koramangala | AF55: =VALUE(IFERROR(MID(D55,FIND(":",D55,FIND("total_offer_discount",D55))+1,FIND(",",D55,FIND("total_offer_discount",D55)) - FIND(":",D55,FIND("total_offer_discount",D55))-1),0)) -> 20.9 | AG55: =DATEVALUE(E55) -> 45324 | AH55: =TIMEVALUE(E55) -> 0.83907407 | AI55: =TEXT(AG55,"dddd") -> Friday | AJ55: =VLOOKUP(HOUR(Orders[[#This Row],[Time]]),$AQ$1:$AR$7,2,1) -> Night | AK55: =IF(Orders[[#This Row],[rain_mode]]=0,"Sunny","Rainy") -> Sunny
A56: 165409130967084 | B56: FALSE | E56: 2024-01-28 16:28:50 | F56: 2024-01-28 16:28:56 | G56: 21191609 | H56: Delivered | I56: JAGANNATH MOHANTA | J56: 647582 | K56: Smoky Docky | L56: 130, 17th H Main Rd, KHB Colony, M.I.G, 5th Block, Koramangala, Bengaluru, Karnataka 560095, India | M56: KHB Colony | N56: Bangalore | O56: 1732 | P56: 233 | Q56: 233 | R56: 233 | S56: 209 | T56: 62 | U56: 0 | V56: 12.934678,77.616812 | W56: 5.9 | Y56: Cash | Z56: Koramangala | AA56: TRUE | AB56: 0 | AC56: =IF(X56="","No Coupon Applied",X56) -> No Coupon Applied | AD56: =VLOOKUP(K56,'restaurant name correction'!$A$1:$B$44,2,0) -> Smoky Docky | AE56: =VLOOKUP(Z56,restaurant_area_correction!$A$1:$B$18,2,0) -> Koramangala | AF56: =VALUE(IFERROR(MID(D56,FIND(":",D56,FIND("total_offer_discount",D56))+1,FIND(",",D56,FIND("total_offer_discount",D56)) - FIND(":",D56,FIND("total_offer_discount",D56))-1),0)) -> 0 | AG56: =DATEVALUE(E56) -> 45319 | AH56: =TIMEVALUE(E56) -> 0.68668981 | AI56: =TEXT(AG56,"dddd") -> Sunday | AJ56: =VLOOKUP(HOUR(Orders[[#This Row],[Time]]),$AQ$1:$AR$7,2,1) -> Evening | AK56: =IF(Orders[[#This Row],[rain_mode]]=0,"Sunny","Rainy") -> Sunny
A57: 165341581288776 | B57: TRUE | C57: SWIGGYIT | D57: [{"id":"0d0cbd02-407f-4bb6-9c39-91b66ef5c01e","super_type":"SUPERTYPE_UNSPECIFIED","total_offer_discount":50,"discount_share":{"swiggy_discount":0,"store_discount":50,"alliance_discount":0},"discount_type":"PERCENTAGE","description":"20% off","fixed_charges":{"gp":{"id":"","final_price":0}}}] | E57: 2024-01-27 21:43:01 | F57: 2024-01-27 21:43:42 | G57: 21191609 | H57: Delivered | I57: 0 | J57: 23805 | K57: Domino's Pizza | L57: Ground Floor, # 1573, Sector 1(Agara), HSR Layout,,Bangalore - 560102 | M57: 1st Sector | N57: Bangalore | O57: 1409 | P57: 599 | Q57: 599 | R57: 599 | S57: 578 | T57: 0 | U57: 0 | V57: 12.923037,77.646448 | W57: 0 | X57: SWIGGYIT | Y57: UPICollect | Z57: HSR Layout | AA57: FALSE | AB57: 0 | AC57: =IF(X57="","No Coupon Applied",X57) -> SWIGGYIT | AD57: =VLOOKUP(K57,'restaurant name correction'!$A$1:$B$44,2,0) -> Domino's Pizza | AE57: =VLOOKUP(Z57,restaurant_area_correction!$A$1:$B$18,2,0) -> HSR | AF57: =VALUE(IFERROR(MID(D57,FIND(":",D57,FIND("total_offer_discount",D57))+1,FIND(",",D57,FIND("total_offer_discount",D57)) - FIND(":",D57,FIND("total_offer_discount",D57))-1),0)) -> 50 | AG57: =DATEVALUE(E57) -> 45318 | AH57: =TIMEVALUE(E57) -> 0.90487269 | AI57: =TEXT(AG57,"dddd") -> Saturday | AJ57: =VLOOKUP(HOUR(Orders[[#This Row],[Time]]),$AQ$1:$AR$7,2,1) -> Night | AK57: =IF(Orders[[#This Row],[rain_mode]]=0,"Sunny","Rainy") -> Sunny
A58: 164743294943602 | B58: TRUE | C58: TRYNEW | D58: [{"id":"66f89a57-1f02-4c46-a99b-8fc3b891874a","super_type":"SUPERTYPE_UNSPECIFIED","total_offer_discount":49.99,"discount_share":{"swiggy_discount":7.5,"store_discount":42.49,"alliance_discount":0},"discount_type":"PERCENTAGE","description":"20% off","fixed_charges":{"gp":{"id":"","final_price":0}}}] | E58: 2024-01-20 23:31:34 | F58: 2024-01-20 23:31:48 | G58: 21191609 | H58: Delivered | I58: RAVI KUMAR MANDAL | J58: 502673 | K58: The Belgian Waffle Co. | L58: Near VI store, 647, 27th main road, sector 2, sector 5, 1st sector HSR Layout, Bengaluru Karnataka - 560102 | M58: 2nd Sector | N58: Bangalore | O58: 1413 | P58: 588 | Q58: 588 | R58: 588 | S58: 586.67 | T58: 36 | U58: 0 | V58: 12.916097,77.65184 | W58: 0.5 | X58: TRYNEW | Y58: UPICollect | Z58: HSR Layout | AA58: TRUE | AB58: 0 | AC58: =IF(X58="","No Coupon Applied",X58) -> TRYNEW | AD58: =VLOOKUP(K58,'restaurant name correction'!$A$1:$B$44,2,0) -> The Belgian Waffle Co. | AE58: =VLOOKUP(Z58,restaurant_area_correction!$A$1:$B$18,2,0) -> HSR | AF58: =VALUE(IFERROR(MID(D58,FIND(":",D58,FIND("total_offer_discount",D58))+1,FIND(",",D58,FIND("total_offer_discount",D58)) - FIND(":",D58,FIND("total_offer_discount",D58))-1),0)) -> 49.99 | AG58: =DATEVALUE(E58) -> 45311 | AH58: =TIMEVALUE(E58) -> 0.98025463 | AI58: =TEXT(AG58,"dddd") -> Saturday | AJ58: =VLOOKUP(HOUR(Orders[[#This Row],[Time]]),$AQ$1:$AR$7,2,1) -> Night | AK58: =IF(Orders[[#This Row],[rain_mode]]=0,"Sunny","Rainy") -> Sunny
A59: 164714296625099 | B59: FALSE | E59: 2024-01-20 15:28:16 | F59: 2024-01-20 15:28:43 | G59: 21191609 | H59: Delivered | I59: Imdadul Hoque Laskar | J59: 647582 | K59: Smoky Docky | L59: 130, 17th H Main Rd, KHB Colony, M.I.G, 5th Block, Koramangala, Bengaluru, Karnataka 560095, India | M59: KHB Colony | N59: Bangalore | O59: 2746 | P59: 233 | Q59: 233 | R59: 233 | S59: 209 | T59: 58 | U59: 0 | V59: 12.934678,77.616812 | W59: 5.9 | Y59: UPICollect | Z59: Koramangala | AA59: FALSE | AB59: 0 | AC59: =IF(X59="","No Coupon Applied",X59) -> No Coupon Applied | AD59: =VLOOKUP(K59,'restaurant name correction'!$A$1:$B$44,2,0) -> Smoky Docky | AE59: =VLOOKUP(Z59,restaurant_area_correction!$A$1:$B$18,2,0) -> Koramangala | AF59: =VALUE(IFERROR(MID(D59,FIND(":",D59,FIND("total_offer_discount",D59))+1,FIND(",",D59,FIND("total_offer_discount",D59)) - FIND(":",D59,FIND("total_offer_discount",D59))-1),0)) -> 0 | AG59: =DATEVALUE(E59) -> 45311 | AH59: =TIMEVALUE(E59) -> 0.64462963 | AI59: =TEXT(AG59,"dddd") -> Saturday | AJ59: =VLOOKUP(HOUR(Orders[[#This Row],[Time]]),$AQ$1:$AR$7,2,1) -> Afternoon | AK59: =IF(Orders[[#This Row],[rain_mode]]=0,"Sunny","Rainy") -> Sunny
A60: 164376172877898 | B60: TRUE | C60: FLAT100 | D60: [{"id":"c5767fa3-4c94-4be2-88d4-9b923f4a2e14","super_type":"SUPERTYPE_UNSPECIFIED","total_offer_discount":99.99,"discount_share":{"swiggy_discount":0,"store_discount":99.99,"alliance_discount":0},"discount_type":"FLAT","description":"Flat ₹100 off","fixed_charges":{"gp":{"id":"","final_price":0}}}] | E60: 2024-01-16 17:32:52 | F60: 2024-01-16 17:33:03 | G60: 21191609 | H60: Delivered | I60: Pravin Kumar | J60: 144115 | K60: The Ganache Factory - Cakes & Desserts | L60: Parcel 5 Food Court, Embassy Tech Village, Outer Ring Road, Near New Horizon College, Devarabeesanahalli, Varthur Hobli, Bangalore , Mahadevapura , B.B.M.P East, Karnataka-560103 | M60: Bellandur Sarjapur | N60: Bangalore | O60: 2411 | P60: 886 | Q60: 886 | R60: 886 | S60: 913.5 | T60: 78 | U60: 0 | V60: 12.927366,77.692146 | W60: 6.2 | X60: FLAT100 | Y60: UPICollect | Z60: Devarabeesanahalli | AA60: TRUE | AB60: 0 | AC60: =IF(X60="","No Coupon Applied",X60) -> FLAT100 | AD60: =VLOOKUP(K60,'restaurant name correction'!$A$1:$B$44,2,0) -> The Ganache Factory | AE60: =VLOOKUP(Z60,restaurant_area_correction!$A$1:$B$18,2,0) -> Devarabeesanahalli | AF60: =VALUE(IFERROR(MID(D60,FIND(":",D60,FIND("total_offer_discount",D60))+1,FIND(",",D60,FIND("total_offer_discount",D60)) - FIND(":",D60,FIND("total_offer_discount",D60))-1),0)) -> 99.99 | AG60: =DATEVALUE(E60) -> 45307 | AH60: =TIMEVALUE(E60) -> 0.73115741 | AI60: =TEXT(AG60,"dddd") -> Tuesday | AJ60: =VLOOKUP(HOUR(Orders[[#This Row],[Time]]),$AQ$1:$AR$7,2,1) -> Evening | AK60: =IF(Orders[[#This Row],[rain_mode]]=0,"Sunny","Rainy") -> Sunny
A61: 164376027513893 | B61: TRUE | C61: FLAT100 | D61: [{"id":"4102e284-fde9-40d3-b050-82926746d231","super_type":"SUPERTYPE_UNSPECIFIED","total_offer_discount":99.99,"discount_share":{"swiggy_discount":0,"store_discount":99.99,"alliance_discount":0},"discount_type":"FLAT","description":"Flat ₹100 off","fixed_charges":{"gp":{"id":"","final_price":0}}}] | E61: 2024-01-16 17:30:27 | F61: 2024-01-16 17:30:32 | G61: 21191609 | H61: cancelled | I61: 0 | J61: 15250 | K61: The Ganache Factory - Cakes & Desserts | L61: #156, 43rd Cross, 8th Block, Next to Udupi Hub Resto, Jayanagar, Bangalore | M61: 8th Block | N61: Bangalore | O61: 0 | P61: 885 | Q61: 885 | R61: 885 | S61: 913.5 | T61: 92 | U61: 0 | V61: 12.91835714,77.578127 | W61: 8.4 | X61: FLAT100 | Y61: UPICollect | Z61: Jayanagar | AA61: FALSE | AB61: 0 | AC61: =IF(X61="","No Coupon Applied",X61) -> FLAT100 | AD61: =VLOOKUP(K61,'restaurant name correction'!$A$1:$B$44,2,0) -> The Ganache Factory | AE61: =VLOOKUP(Z61,restaurant_area_correction!$A$1:$B$18,2,0) -> Jayanagar | AF61: =VALUE(IFERROR(MID(D61,FIND(":",D61,FIND("total_offer_discount",D61))+1,FIND(",",D61,FIND("total_offer_discount",D61)) - FIND(":",D61,FIND("total_offer_discount",D61))-1),0)) -> 99.99 | AG61: =DATEVALUE(E61) -> 45307 | AH61: =TIMEVALUE(E61) -> 0.72947917 | AI61: =TEXT(AG61,"dddd") -> Tuesday | AJ61: =VLOOKUP(HOUR(Orders[[#This Row],[Time]]),$AQ$1:$AR$7,2,1) -> Evening | AK61: =IF(Orders[[#This Row],[rain_mode]]=0,"Sunny","Rainy") -> Sunny
A62: 164191765873335 | B62: TRUE | C62: FLATDEAL | D62: [{"id":"e869bbb4-07f7-44d5-a519-1acaeadf5e53","super_type":"SUPERTYPE_UNSPECIFIED","total_offer_discount":99.99,"discount_share":{"swiggy_discount":29.99,"store_discount":70,"alliance_discount":0},"discount_type":"FLAT","description":"FLAT100 off","fixed_charges":{"gp":{"id":"","final_price":0}}}] | E62: 2024-01-14 14:19:25 | F62: 2024-01-14 14:19:42 | G62: 21191609 | H62: Delivered | I62: Siddartha U | J62: 375045 | K62: Paratha Envy | L62: NO.504, 2ND FLOOR, 6TH CROSS, 6TH BLOCK, KORAMANGALA BANGALORE., BTM Layout, B.B.M.P South, Karnataka-560095 | M62: 6th Block | N62: Bangalore | O62: 3551 | P62: 466 | Q62: 466 | R62: 466 | S62: 496 | T62: 52 | U62: 0 | V62: 12.937246,77.624643 | W62: 5.2 | X62: FLATDEAL | Y62: UPICollect | Z62: Koramangala | AA62: FALSE | AB62: 0 | AC62: =IF(X62="","No Coupon Applied",X62) -> FLATDEAL | AD62: =VLOOKUP(K62,'restaurant name correction'!$A$1:$B$44,2,0) -> Paratha Envy | AE62: =VLOOKUP(Z62,restaurant_area_correction!$A$1:$B$18,2,0) -> Koramangala | AF62: =VALUE(IFERROR(MID(D62,FIND(":",D62,FIND("total_offer_discount",D62))+1,FIND(",",D62,FIND("total_offer_discount",D62)) - FIND(":",D62,FIND("total_offer_discount",D62))-1),0)) -> 99.99 | AG62: =DATEVALUE(E62) -> 45305 | AH62: =TIMEVALUE(E62) -> 0.59681713 | AI62: =TEXT(AG62,"dddd") -> Sunday | AJ62: =VLOOKUP(HOUR(Orders[[#This Row],[Time]]),$AQ$1:$AR$7,2,1) -> Afternoon | AK62: =IF(Orders[[#This Row],[rain_mode]]=0,"Sunny","Rainy") -> Sunny
A63: 163711888473406 | B63: FALSE | E63: 2024-01-09 01:01:28 | F63: 2024-01-09 01:01:48 | G63: 21191609 | H63: Delivered | I63: Binoy Debbarma | J63: 23682 | K63: McDonald's | L63: HSR Layout #1, 14th Main,HSR LSector VII, Bengaluru- 56102. | M63: HSR Layout | N63: Bangalore | O63: 1000 | P63: 270 | Q63: 270 | R63: 270 | S63: 220 | T63: 36 | U63: 0 | V63: 12.91207388,77.6380679 | W63: 0.4 | Y63: UPICollect | Z63: HSR Layout | AA63: FALSE | AB63: 0 | AC63: =IF(X63="","No Coupon Applied",X63) -> No Coupon Applied | AD63: =VLOOKUP(K63,'restaurant name correction'!$A$1:$B$44,2,0) -> McDonald's | AE63: =VLOOKUP(Z63,restaurant_area_correction!$A$1:$B$18,2,0) -> HSR | AF63: =VALUE(IFERROR(MID(D63,FIND(":",D63,FIND("total_offer_discount",D63))+1,FIND(",",D63,FIND("total_offer_discount",D63)) - FIND(":",D63,FIND("total_offer_discount",D63))-1),0)) -> 0 | AG63: =DATEVALUE(E63) -> 45300 | AH63: =TIMEVALUE(E63) -> 0.042685185 | AI63: =TEXT(AG63,"dddd") -> Tuesday | AJ63: =VLOOKUP(HOUR(Orders[[#This Row],[Time]]),$AQ$1:$AR$7,2,1) -> Early Morning | AK63: =IF(Orders[[#This Row],[rain_mode]]=0,"Sunny","Rainy") -> Sunny
A64: 163004675209983 | B64: TRUE | C64: TRYNEW | D64: [{"id":"c5752e1c-f5c2-4414-85fa-57de3a043c19","super_type":"SUPERTYPE_UNSPECIFIED","total_offer_discount":35.7,"discount_share":{"swiggy_discount":0,"store_discount":35.7,"alliance_discount":0},"discount_type":"PERCENTAGE","description":"10% off","fixed_charges":{"gp":{"id":"","final_price":0}}}] | E64: 2023-12-31 20:34:35 | F64: 2023-12-31 20:34:53 | G64: 21191609 | H64: Delivered | I64: SUMANMANDAL | J64: 144115 | K64: The Ganache Factory - Cakes & Desserts | L64: Parcel 5 Food Court, Embassy Tech Village, Outer Ring Road, Near New Horizon College, Devarabeesanahalli, Varthur Hobli, Bangalore , Mahadevapura , B.B.M.P East, Karnataka-560103 | M64: Bellandur Sarjapur | N64: Bangalore | O64: 2664 | P64: 342 | Q64: 342 | R64: 342 | S64: 357 | T64: 76 | U64: 0 | V64: 12.927366,77.692146 | W64: 6.2 | X64: TRYNEW | Y64: UPICollect | Z64: Devarabeesanahalli | AA64: FALSE | AB64: 0 | AC64: =IF(X64="","No Coupon Applied",X64) -> TRYNEW | AD64: =VLOOKUP(K64,'restaurant name correction'!$A$1:$B$44,2,0) -> The Ganache Factory | AE64: =VLOOKUP(Z64,restaurant_area_correction!$A$1:$B$18,2,0) -> Devarabeesanahalli | AF64: =VALUE(IFERROR(MID(D64,FIND(":",D64,FIND("total_offer_discount",D64))+1,FIND(",",D64,FIND("total_offer_discount",D64)) - FIND(":",D64,FIND("total_offer_discount",D64))-1),0)) -> 35.7 | AG64: =DATEVALUE(E64) -> 45291 | AH64: =TIMEVALUE(E64) -> 0.85734954 | AI64: =TEXT(AG64,"dddd") -> Sunday | AJ64: =VLOOKUP(HOUR(Orders[[#This Row],[Time]]),$AQ$1:$AR$7,2,1) -> Night | AK64: =IF(Orders[[#This Row],[rain_mode]]=0,"Sunny","Rainy") -> Sunny
A65: 163004361179135 | B65: FALSE | E65: 2023-12-31 20:29:21 | F65: 2023-12-31 20:29:27 | G65: 21191609 | H65: Delivered | I65: Mohammad Wasim Akram | J65: 254655 | K65: Daily Sushi | L65: No.1212, SBM Fortune, 4th Floor, 22nd Cross Road, 14th Main Rd, 3rd Sector, HSR Layout, Bengaluru, Karnataka 560102, India | M65: 3rd Sector | N65: Bangalore | O65: 1889 | P65: 467 | Q65: 467 | R65: 467 | S65: 400 | T65: 31 | U65: 0 | V65: 12.909368,77.638656 | W65: 2.1 | Y65: UPICollect | Z65: HSR Layout | AA65: FALSE | AB65: 0 | AC65: =IF(X65="","No Coupon Applied",X65) -> No Coupon Applied | AD65: =VLOOKUP(K65,'restaurant name correction'!$A$1:$B$44,2,0) -> Daily Sushi | AE65: =VLOOKUP(Z65,restaurant_area_correction!$A$1:$B$18,2,0) -> HSR | AF65: =VALUE(IFERROR(MID(D65,FIND(":",D65,FIND("total_offer_discount",D65))+1,FIND(",",D65,FIND("total_offer_discount",D65)) - FIND(":",D65,FIND("total_offer_discount",D65))-1),0)) -> 0 | AG65: =DATEVALUE(E65) -> 45291 | AH65: =TIMEVALUE(E65) -> 0.85371528 | AI65: =TEXT(AG65,"dddd") -> Sunday | AJ65: =VLOOKUP(HOUR(Orders[[#This Row],[Time]]),$AQ$1:$AR$7,2,1) -> Night | AK65: =IF(Orders[[#This Row],[rain_mode]]=0,"Sunny","Rainy") -> Sunny
A66: 162553743923962 | B66: TRUE | C66: CELEBRATIONS | D66: [{"id":"0cf35ab8-1dc8-4c78-8500-44beda4d0877","super_type":"SUPERTYPE_UNSPECIFIED","total_offer_discount":174.99,"discount_share":{"swiggy_discount":52.5,"store_discount":122.49,"alliance_discount":0},"discount_type":"FLAT","description":"Flat ₹175 off","fixed_charges":{"gp":{"id":"","final_price":0}}}] | E66: 2023-12-26 15:19:03 | F66: 2023-12-26 15:19:25 | G66: 21191609 | H66: Delivered | I66: UMESH | J66: 398360 | K66: Burger Seigneur | L66: #717, 10th main road 2nd cross Hosapalya Opposite of Subodhini English high school ITI layout sector 7. | M66: MANGAMMANAPALYA | N66: Bangalore | O66: 1788 | P66: 788 | Q66: 788 | R66: 788 | S66: 920 | T66: 40 | U66: 0 | V66: 12.90073452,77.6400283 | W66: 2.8 | X66: CELEBRATIONS | Y66: UPICollect | Z66: ITI layout, Hosapalya | AA66: FALSE | AB66: 0 | AC66: =IF(X66="","No Coupon Applied",X66) -> CELEBRATIONS | AD66: =VLOOKUP(K66,'restaurant name correction'!$A$1:$B$44,2,0) -> Burger Seigneur | AE66: =VLOOKUP(Z66,restaurant_area_correction!$A$1:$B$18,2,0) -> Hosapalya | AF66: =VALUE(IFERROR(MID(D66,FIND(":",D66,FIND("total_offer_discount",D66))+1,FIND(",",D66,FIND("total_offer_discount",D66)) - FIND(":",D66,FIND("total_offer_discount",D66))-1),0)) -> 174.99 | AG66: =DATEVALUE(E66) -> 45286 | AH66: =TIMEVALUE(E66) -> 0.63822917 | AI66: =TEXT(AG66,"dddd") -> Tuesday | AJ66: =VLOOKUP(HOUR(Orders[[#This Row],[Time]]),$AQ$1:$AR$7,2,1) -> Afternoon | AK66: =IF(Orders[[#This Row],[rain_mode]]=0,"Sunny","Rainy") -> Sunny
A67: 162461263812077 | B67: TRUE | C67: MISSEDYOU | D67: [{"id":"8493942f-3551-4789-a766-bd2e8eab5603","super_type":"SUPERTYPE_UNSPECIFIED","total_offer_discount":80,"discount_share":{"swiggy_discount":12,"store_discount":68,"alliance_discount":0},"discount_type":"PERCENTAGE","description":"40% off","fixed_charges":{"gp":{"id":"","final_price":0}}}] | E67: 2023-12-25 13:37:43 | F67: 2023-12-25 13:38:02 | G67: 21191609 | H67: Delivered | I67: UNOOSE YUSUF | J67: 398360 | K67: Burger Seigneur | L67: #717, 10th main road 2nd cross Hosapalya Opposite of Subodhini English high school ITI layout sector 7. | M67: MANGAMMANAPALYA | N67: Bangalore | O67: 1389 | P67: 372 | Q67: 372 | R67: 372 | S67: 430 | T67: 40 | U67: 0 | V67: 12.90073452,77.6400283 | W67: 2.7 | X67: MISSEDYOU | Y67: UPICollect | Z67: ITI layout, Hosapalya | AA67: TRUE | AB67: 0 | AC67: =IF(X67="","No Coupon Applied",X67) -> MISSEDYOU | AD67: =VLOOKUP(K67,'restaurant name correction'!$A$1:$B$44,2,0) -> Burger Seigneur | AE67: =VLOOKUP(Z67,restaurant_area_correction!$A$1:$B$18,2,0) -> Hosapalya | AF67: =VALUE(IFERROR(MID(D67,FIND(":",D67,FIND("total_offer_discount",D67))+1,FIND(",",D67,FIND("total_offer_discount",D67)) - FIND(":",D67,FIND("total_offer_discount",D67))-1),0)) -> 80 | AG67: =DATEVALUE(E67) -> 45285 | AH67: =TIMEVALUE(E67) -> 0.5678588 | AI67: =TEXT(AG67,"dddd") -> Monday | AJ67: =VLOOKUP(HOUR(Orders[[#This Row],[Time]]),$AQ$1:$AR$7,2,1) -> Afternoon | AK67: =IF(Orders[[#This Row],[rain_mode]]=0,"Sunny","Rainy") -> Sunny
A68: 161080636531967 | B68: TRUE | C68: SWIGGYIT | D68: [{"id":"485642ce-1796-4eab-9811-3ff5e4b7d538","super_type":"SUPERTYPE_UNSPECIFIED","total_offer_discount":80,"discount_share":{"swiggy_discount":28,"store_discount":52,"alliance_discount":0},"discount_type":"PERCENTAGE","description":"40% off","fixed_charges":{"gp":{"id":"","final_price":0}}}] | E68: 2023-12-09 14:07:16 | F68: 2023-12-09 14:07:34 | G68: 21191609 | H68: Delivered | I68: Irfanirfu | J68: 2675 | K68: Subway | L68: 36, 3rd Store, 7th Sector, 14th main, HSR Layout | M68: 7th Sector | N68: Bangalore | O68: 1080 | P68: 355 | Q68: 355 | R68: 355 | S68: 399 | T68: 33 | U68: 0 | V68: 12.9118135,77.637958 | W68: 1.9 | X68: SWIGGYIT | Y68: UPICollect | Z68: Hsr Layout | AA68: TRUE | AB68: 0 | AC68: =IF(X68="","No Coupon Applied",X68) -> SWIGGYIT | AD68: =VLOOKUP(K68,'restaurant name correction'!$A$1:$B$44,2,0) -> Subway | AE68: =VLOOKUP(Z68,restaurant_area_correction!$A$1:$B$18,2,0) -> HSR | AF68: =VALUE(IFERROR(MID(D68,FIND(":",D68,FIND("total_offer_discount",D68))+1,FIND(",",D68,FIND("total_offer_discount",D68)) - FIND(":",D68,FIND("total_offer_discount",D68))-1),0)) -> 80 | AG68: =DATEVALUE(E68) -> 45269 | AH68: =TIMEVALUE(E68) -> 0.58837963 | AI68: =TEXT(AG68,"dddd") -> Saturday | AJ68: =VLOOKUP(HOUR(Orders[[#This Row],[Time]]),$AQ$1:$AR$7,2,1) -> Afternoon | AK68: =IF(Orders[[#This Row],[rain_mode]]=0,"Sunny","Rainy") -> Sunny
A69: 160474594456670 | B69: TRUE | C69: MISSEDYOU | D69: [{"id":"bf585ef3-1522-4981-b7a7-5e366761dbce","super_type":"SUPERTYPE_UNSPECIFIED","total_offer_discount":80,"discount_share":{"swiggy_discount":28,"store_discount":52,"alliance_discount":0},"discount_type":"PERCENTAGE","description":"40% off","fixed_charges":{"gp":{"id":"","final_price":0}}}] | E69: 2023-12-02 13:46:34 | F69: 2023-12-02 13:46:52 | G69: 21191609 | H69: Delivered | I69: SIKENDAR KUMAR YADAV | J69: 2675 | K69: Subway | L69: 36, 3rd Store, 7th Sector, 14th main, HSR Layout | M69: 7th Sector | N69: Bangalore | O69: 2671 | P69: 354 | Q69: 354 | R69: 354 | S69: 398 | T69: 32 | U69: 0 | V69: 12.9118135,77.637958 | W69: 1.9 | X69: MISSEDYOU | Y69: UPICollect | Z69: Hsr Layout | AA69: FALSE | AB69: 0 | AC69: =IF(X69="","No Coupon Applied",X69) -> MISSEDYOU | AD69: =VLOOKUP(K69,'restaurant name correction'!$A$1:$B$44,2,0) -> Subway | AE69: =VLOOKUP(Z69,restaurant_area_correction!$A$1:$B$18,2,0) -> HSR | AF69: =VALUE(IFERROR(MID(D69,FIND(":",D69,FIND("total_offer_discount",D69))+1,FIND(",",D69,FIND("total_offer_discount",D69)) - FIND(":",D69,FIND("total_offer_discount",D69))-1),0)) -> 80 | AG69: =DATEVALUE(E69) -> 45262 | AH69: =TIMEVALUE(E69) -> 0.57400463 | AI69: =TEXT(AG69,"dddd") -> Saturday | AJ69: =VLOOKUP(HOUR(Orders[[#This Row],[Time]]),$AQ$1:$AR$7,2,1) -> Afternoon | AK69: =IF(Orders[[#This Row],[rain_mode]]=0,"Sunny","Rainy") -> Sunny
A70: 159955886050893 | B70: TRUE | C70: SWIGGYIT | D70: [{"id":"a17455c6-6016-48b5-95c0-933ae258bf5c","super_type":"SUPERTYPE_UNSPECIFIED","total_offer_discount":120,"discount_share":{"swiggy_discount":36,"store_discount":84,"alliance_discount":0},"discount_type":"PERCENTAGE","description":"60% off","fixed_charges":{"gp":{"id":"","final_price":0}}}] | E70: 2023-11-26 13:41:26 | F70: 2023-11-26 13:41:50 | G70: 21191609 | H70: Delivered | I70: Rajasekar Reddy | J70: 81810 | K70: Tharavadu family restaurant | L70: 1st FLOOR, NO.116/1, HOSUR MAIN ROAD, MANGAMMANAPALYA CROSS, BOMMANAHALLI , Bommenahalli , Bangalore South, Bangalore Urban, Karnataka-560068 | M70: Hosur Main Road | N70: Bangalore | O70: 1550 | P70: 284 | Q70: 284 | R70: 284 | S70: 375 | T70: 41 | U70: 0 | V70: 12.906146,77.629745 | W70: 3.3 | X70: SWIGGYIT | Y70: UPICollect | Z70: Bommanahalli | AA70: FALSE | AB70: 0 | AC70: =IF(X70="","No Coupon Applied",X70) -> SWIGGYIT | AD70: =VLOOKUP(K70,'restaurant name correction'!$A$1:$B$44,2,0) -> Tharavadu family restaurant | AE70: =VLOOKUP(Z70,restaurant_area_correction!$A$1:$B$18,2,0) -> Bommanahalli | AF70: =VALUE(IFERROR(MID(D70,FIND(":",D70,FIND("total_offer_discount",D70))+1,FIND(",",D70,FIND("total_offer_discount",D70)) - FIND(":",D70,FIND("total_offer_discount",D70))-1),0)) -> 120 | AG70: =DATEVALUE(E70) -> 45256 | AH70: =TIMEVALUE(E70) -> 0.57043981 | AI70: =TEXT(AG70,"dddd") -> Sunday | AJ70: =VLOOKUP(HOUR(Orders[[#This Row],[Time]]),$AQ$1:$AR$7,2,1) -> Afternoon | AK70: =IF(Orders[[#This Row],[rain_mode]]=0,"Sunny","Rainy") -> Sunny
A71: 159700431113615 | B71: TRUE | C71: FLATDEAL | D71: [{"id":"3be8626e-f3e3-4950-bcca-639767fe94cf","super_type":"SUPERTYPE_UNSPECIFIED","total_offer_discount":100,"discount_share":{"swiggy_discount":0,"store_discount":100,"alliance_discount":0},"discount_type":"FLAT","description":"FLAT100 off","fixed_charges":{"gp":{"id":"","final_price":0}}}] | E71: 2023-11-23 14:43:51 | F71: 2023-11-23 14:44:09 | G71: 21191609 | H71: Delivered | I71: Jayadev Behera | J71: 700113 | K71: The Best Thickshakes Co | L71: 1237, Sri Sai Crystal 17th cross, 5th Main Rd, HSR Layout, Bengaluru, Karnataka 560102 | M71: 5th Main Rd | N71: Bangalore | O71: 1673 | P71: 455 | Q71: 455 | R71: 455 | S71: 530 | T71: 29 | U71: 0 | V71: 12.912028,77.632327 | W71: 2.3 | X71: FLATDEAL | Y71: UPICollect | Z71: HSR | AA71: FALSE | AB71: 0 | AC71: =IF(X71="","No Coupon Applied",X71) -> FLATDEAL | AD71: =VLOOKUP(K71,'restaurant name correction'!$A$1:$B$44,2,0) -> The Best Thickshakes Co | AE71: =VLOOKUP(Z71,restaurant_area_correction!$A$1:$B$18,2,0) -> HSR | AF71: =VALUE(IFERROR(MID(D71,FIND(":",D71,FIND("total_offer_discount",D71))+1,FIND(",",D71,FIND("total_offer_discount",D71)) - FIND(":",D71,FIND("total_offer_discount",D71))-1),0)) -> 100 | AG71: =DATEVALUE(E71) -> 45253 | AH71: =TIMEVALUE(E71) -> 0.61378472 | AI71: =TEXT(AG71,"dddd") -> Thursday | AJ71: =VLOOKUP(HOUR(Orders[[#This Row],[Time]]),$AQ$1:$AR$7,2,1) -> Afternoon | AK71: =IF(Orders[[#This Row],[rain_mode]]=0,"Sunny","Rainy") -> Sunny
A72: 159024606634682 | B72: TRUE | C72: KINGK50 | D72: [{"id":"03ca3c14-fff6-467e-ae52-d8c251b67a76","super_type":"SUPERTYPE_UNSPECIFIED","total_offer_discount":50.01,"discount_share":{"swiggy_discount":50.01,"store_discount":0,"alliance_discount":0},"discount_type":"FLAT","description":"Flat ₹200 off","fixed_charges":{"gp":{"id":"","final_price":0}},"applied_as":"SHADOW","base_offers":[{"offer_id":"92c138b0-4008-4a46-83f9-f28b6636521d","coupon_code":"WORLDCUPMANIA"}]},{"id":"92c138b0-4008-4a46-83f9-f28b6636521d","super_type":"SUPERTYPE_UNSPECIFIED","total_offer_discount":149.97,"discount_share":{"swiggy_discount":30.01,"store_discount":119.96,"alliance_discount":0},"discount_type":"FLAT","description":"FLAT150 off","fixed_charges":{"gp":{"id":"","final_price":0}}}] | E72: 2023-11-15 19:00:06 | F72: 2023-11-15 19:00:24 | G72: 21191609 | H72: Delivered | I72: MOSTAFIZAR RAHAMAN | J72: 81810 | K72: Tharavadu family restaurant | L72: 1st FLOOR, NO.116/1, HOSUR MAIN ROAD, MANGAMMANAPALYA CROSS, BOMMANAHALLI , Bommenahalli , Bangalore South, Bangalore Urban, Karnataka-560068 | M72: Hosur Main Road | N72: Bangalore | O72: 2047 | P72: 380 | Q72: 380 | R72: 380 | S72: 540 | T72: 44 | U72: 0 | V72: 12.906146,77.629745 | W72: 3.3 | X72: KINGK50 | Y72: UPICollect | Z72: Bommanahalli | AA72: FALSE | AB72: 0 | AC72: =IF(X72="","No Coupon Applied",X72) -> KINGK50 | AD72: =VLOOKUP(K72,'restaurant name correction'!$A$1:$B$44,2,0) -> Tharavadu family restaurant | AE72: =VLOOKUP(Z72,restaurant_area_correction!$A$1:$B$18,2,0) -> Bommanahalli | AF72: =VALUE(IFERROR(MID(D72,FIND(":",D72,FIND("total_offer_discount",D72))+1,FIND(",",D72,FIND("total_offer_discount",D72)) - FIND(":",D72,FIND("total_offer_discount",D72))-1),0)) -> 50.01 | AG72: =DATEVALUE(E72) -> 45245 | AH72: =TIMEVALUE(E72) -> 0.79173611 | AI72: =TEXT(AG72,"dddd") -> Wednesday | AJ72: =VLOOKUP(HOUR(Orders[[#This Row],[Time]]),$AQ$1:$AR$7,2,1) -> Evening | AK72: =IF(Orders[[#This Row],[rain_mode]]=0,"Sunny","Rainy") -> Sunny
A73: 158421216354293 | B73: FALSE | E73: 2023-11-08 19:23:36 | F73: 2023-11-08 19:23:57 | G73: 21191609 | H73: Delivered | I73: Eresha | J73: 244004 | K73: Wow! Momo | L73: WOW MOMO NO1 120 14th main road 5th sector HSR layout Bangalore BTM layout BBMP south Karnataka 560102 | M73: 5th sector | N73: Bangalore | O73: 2006 | P73: 221 | Q73: 221 | R73: 221 | S73: 268 | T73: 32 | U73: 0 | V73: 12.9161961,77.6377847 | W73: 2.1 | Y73: UPICollect | Z73: HSR Layout | AA73: FALSE | AB73: 0 | AC73: =IF(X73="","No Coupon Applied",X73) -> No Coupon Applied | AD73: =VLOOKUP(K73,'restaurant name correction'!$A$1:$B$44,2,0) -> Wow! Momo | AE73: =VLOOKUP(Z73,restaurant_area_correction!$A$1:$B$18,2,0) -> HSR | AF73: =VALUE(IFERROR(MID(D73,FIND(":",D73,FIND("total_offer_discount",D73))+1,FIND(",",D73,FIND("total_offer_discount",D73)) - FIND(":",D73,FIND("total_offer_discount",D73))-1),0)) -> 0 | AG73: =DATEVALUE(E73) -> 45238 | AH73: =TIMEVALUE(E73) -> 0.80805556 | AI73: =TEXT(AG73,"dddd") -> Wednesday | AJ73: =VLOOKUP(HOUR(Orders[[#This Row],[Time]]),$AQ$1:$AR$7,2,1) -> Evening | AK73: =IF(Orders[[#This Row],[rain_mode]]=0,"Sunny","Rainy") -> Sunny
A74: 158334414702466 | B74: FALSE | E74: 2023-11-07 19:16:54 | F74: 2023-11-07 19:17:27 | G74: 21191609 | H74: Delivered | I74: Hasnul Hoque Choudhury | J74: 742267 | K74: Paris Panini - Gourmet Sandwiches & Wraps | L74: Counter No. 23, 24 & 33, No. 53/2, Doddakannelli Village, Varthur Hobli, Bangalore, Mahadevapura , B.B.M.P East, Karnataka-560038 | M74: Doddakanneli Village | N74: Bangalore | O74: 3013 | P74: 287 | Q74: 287 | R74: 287 | S74: 245 | T74: 72 | U74: 0 | V74: 12.9092988,77.6877346 | W74: 5.4 | Y74: UPICollect | Z74: Bellandur Sarjapur | AA74: FALSE | AB74: 2 | AC74: =IF(X74="","No Coupon Applied",X74) -> No Coupon Applied | AD74: =VLOOKUP(K74,'restaurant name correction'!$A$1:$B$44,2,0) -> Paris Panini | AE74: =VLOOKUP(Z74,restaurant_area_correction!$A$1:$B$18,2,0) -> Bellandur | AF74: =VALUE(IFERROR(MID(D74,FIND(":",D74,FIND("total_offer_discount",D74))+1,FIND(",",D74,FIND("total_offer_discount",D74)) - FIND(":",D74,FIND("total_offer_discount",D74))-1),0)) -> 0 | AG74: =DATEVALUE(E74) -> 45237 | AH74: =TIMEVALUE(E74) -> 0.80340278 | AI74: =TEXT(AG74,"dddd") -> Tuesday | AJ74: =VLOOKUP(HOUR(Orders[[#This Row],[Time]]),$AQ$1:$AR$7,2,1) -> Evening | AK74: =IF(Orders[[#This Row],[rain_mode]]=0,"Sunny","Rainy") -> Rainy
A75: 158133339719955 | B75: TRUE | C75: WORLDCUPMANIA | D75: [{"id":"fcc09378-6922-4b80-a505-f2cda5e1f89c","super_type":"SUPERTYPE_UNSPECIFIED","total_offer_discount":150,"discount_share":{"swiggy_discount":75,"store_discount":75,"alliance_discount":0},"discount_type":"FLAT","description":"FLAT150 off","fixed_charges":{"gp":{"id":"","final_price":0}}}] | E75: 2023-11-05 11:25:39 | F75: 2023-11-05 11:25:54 | G75: 21191609 | H75: Delivered | I75: SAYAD SAHABUDDIN ALLI | J75: 17036 | K75: Leon's - Burgers & Wings (Leon Grill) | L75: No.17, Ground Floor, 18th Cross Road, 3rd Sector, HSR Layout, Bangalore. | M75: HSR Layout | N75: Bangalore | O75: 1495 | P75: 251 | Q75: 251 | R75: 251 | S75: 349 | T75: 31 | U75: 0 | V75: 12.91183127,77.64382903 | W75: 1.6 | X75: WORLDCUPMANIA | Y75: UPICollect | Z75: HSR Layout | AA75: FALSE | AB75: 0 | AC75: =IF(X75="","No Coupon Applied",X75) -> WORLDCUPMANIA | AD75: =VLOOKUP(K75,'restaurant name correction'!$A$1:$B$44,2,0) -> Leon's | AE75: =VLOOKUP(Z75,restaurant_area_correction!$A$1:$B$18,2,0) -> HSR | AF75: =VALUE(IFERROR(MID(D75,FIND(":",D75,FIND("total_offer_discount",D75))+1,FIND(",",D75,FIND("total_offer_discount",D75)) - FIND(":",D75,FIND("total_offer_discount",D75))-1),0)) -> 150 | AG75: =DATEVALUE(E75) -> 45235 | AH75: =TIMEVALUE(E75) -> 0.47614583 | AI75: =TEXT(AG75,"dddd") -> Sunday | AJ75: =VLOOKUP(HOUR(Orders[[#This Row],[Time]]),$AQ$1:$AR$7,2,1) -> Late Morning | AK75: =IF(Orders[[#This Row],[rain_mode]]=0,"Sunny","Rainy") -> Sunny
A76: 158078123542130 | B76: TRUE | C76: WORLDCUPMANIA | D76: [{"id":"078f55cb-bc8e-4ef0-bdc1-3980cdc6873c","super_type":"SUPERTYPE_UNSPECIFIED","total_offer_discount":150,"discount_share":{"swiggy_discount":45,"store_discount":105,"alliance_discount":0},"discount_type":"FLAT","description":"FLAT150 off","fixed_charges":{"gp":{"id":"","final_price":0}}}] | E76: 2023-11-04 20:05:23 | F76: 2023-11-04 20:05:40 | G76: 21191609 | H76: Delivered | I76: Susanta Das | J76: 254655 | K76: Daily Sushi | L76: No.1212, SBM Fortune, 4th Floor, 22nd Cross Road, 14th Main Rd, 3rd Sector, HSR Layout, Bengaluru, Karnataka 560102, India | M76: 3rd Sector | N76: Bangalore | O76: 2736 | P76: 333 | Q76: 333 | R76: 333 | S76: 420 | T76: 40 | U76: 0 | V76: 12.909368,77.638656 | W76: 2.1 | X76: WORLDCUPMANIA | Y76: UPICollect | Z76: HSR Layout | AA76: TRUE | AB76: 0 | AC76: =IF(X76="","No Coupon Applied",X76) -> WORLDCUPMANIA | AD76: =VLOOKUP(K76,'restaurant name correction'!$A$1:$B$44,2,0) -> Daily Sushi | AE76: =VLOOKUP(Z76,restaurant_area_correction!$A$1:$B$18,2,0) -> HSR | AF76: =VALUE(IFERROR(MID(D76,FIND(":",D76,FIND("total_offer_discount",D76))+1,FIND(",",D76,FIND("total_offer_discount",D76)) - FIND(":",D76,FIND("total_offer_discount",D76))-1),0)) -> 150 | AG76: =DATEVALUE(E76) -> 45234 | AH76: =TIMEVALUE(E76) -> 0.83707176 | AI76: =TEXT(AG76,"dddd") -> Saturday | AJ76: =VLOOKUP(HOUR(Orders[[#This Row],[Time]]),$AQ$1:$AR$7,2,1) -> Night | AK76: =IF(Orders[[#This Row],[rain_mode]]=0,"Sunny","Rainy") -> Sunny
A77: 158041541026826 | B77: FALSE | E77: 2023-11-04 09:55:41 | F77: 2023-11-04 09:55:59 | G77: 21191609 | H77: Delivered | I77: MANAS KUMAR SETHI | J77: 62430 | K77: Dosa Chicken & Tiffins | L77: 235, 9th Main Road, Sector 7, HSR Layout, Sector 7, HSR Layout, Bengaluru, Karnataka 560102 | M77: 7th Sector | N77: Bangalore | O77: 2540 | P77: 191 | Q77: 191 | R77: 191 | S77: 169 | T77: 33 | U77: 0 | V77: 12.912837,77.63510900000006 | W77: 2.1 | Y77: UPICollect | Z77: HSR Layout | AA77: FALSE | AB77: 0 | AC77: =IF(X77="","No Coupon Applied",X77) -> No Coupon Applied | AD77: =VLOOKUP(K77,'restaurant name correction'!$A$1:$B$44,2,0) -> Dosa Chicken & Tiffins | AE77: =VLOOKUP(Z77,restaurant_area_correction!$A$1:$B$18,2,0) -> HSR | AF77: =VALUE(IFERROR(MID(D77,FIND(":",D77,FIND("total_offer_discount",D77))+1,FIND(",",D77,FIND("total_offer_discount",D77)) - FIND(":",D77,FIND("total_offer_discount",D77))-1),0)) -> 0 | AG77: =DATEVALUE(E77) -> 45234 | AH77: =TIMEVALUE(E77) -> 0.41366898 | AI77: =TEXT(AG77,"dddd") -> Saturday | AJ77: =VLOOKUP(HOUR(Orders[[#This Row],[Time]]),$AQ$1:$AR$7,2,1) -> Late Morning | AK77: =IF(Orders[[#This Row],[rain_mode]]=0,"Sunny","Rainy") -> Sunny
A78: 157279336071863 | B78: TRUE | C78: SWIGGYIT | D78: [{"id":"56bb9bfb-bb7d-4334-9bfa-0b49fa1625e7","super_type":"SUPERTYPE_UNSPECIFIED","total_offer_discount":50,"discount_share":{"swiggy_discount":25,"store_discount":25,"alliance_discount":0},"discount_type":"PERCENTAGE","description":"20% off","fixed_charges":{"gp":{"id":"","final_price":0}}}] | E78: 2023-10-26 14:12:16 | F78: 2023-10-26 14:12:30 | G78: 21191609 | H78: Delivered | I78: danush | J78: 17036 | K78: Leon's - Burgers & Wings (Leon Grill) | L78: No.17, Ground Floor, 18th Cross Road, 3rd Sector, HSR Layout, Bangalore. | M78: HSR Layout | N78: Bangalore | O78: 782 | P78: 298 | Q78: 298 | R78: 298 | S78: 295.86 | T78: 30 | U78: 0 | V78: 12.91183127,77.64382903 | W78: 0.2 | X78: SWIGGYIT | Y78: UPICollect | Z78: HSR Layout | AA78: TRUE | AB78: 0 | AC78: =IF(X78="","No Coupon Applied",X78) -> SWIGGYIT | AD78: =VLOOKUP(K78,'restaurant name correction'!$A$1:$B$44,2,0) -> Leon's | AE78: =VLOOKUP(Z78,restaurant_area_correction!$A$1:$B$18,2,0) -> HSR | AF78: =VALUE(IFERROR(MID(D78,FIND(":",D78,FIND("total_offer_discount",D78))+1,FIND(",",D78,FIND("total_offer_discount",D78)) - FIND(":",D78,FIND("total_offer_discount",D78))-1),0)) -> 50 | AG78: =DATEVALUE(E78) -> 45225 | AH78: =TIMEVALUE(E78) -> 0.59185185 | AI78: =TEXT(AG78,"dddd") -> Thursday | AJ78: =VLOOKUP(HOUR(Orders[[#This Row],[Time]]),$AQ$1:$AR$7,2,1) -> Afternoon | AK78: =IF(Orders[[#This Row],[rain_mode]]=0,"Sunny","Rainy") -> Sunny
A79: 157212479386394 | B79: FALSE | E79: 2023-10-25 19:37:59 | F79: 2023-10-25 19:38:20 | G79: 21191609 | H79: Delivered | I79: Periyasami | J79: 488099 | K79: The Himalayan Momo Company | L79: 73, 27 th Main Road,Phase 3, Agara Village,1 st Sector | M79: 1st Sector | N79: Bangalore | O79: 661 | P79: 167 | Q79: 167 | R79: 167 | S79: 149 | T79: 42 | U79: 0 | V79: 12.920751,77.650396 | W79: 0.6 | Y79: UPICollect | Z79: HSR Layout | AA79: TRUE | AB79: 0 | AC79: =IF(X79="","No Coupon Applied",X79) -> No Coupon Applied | AD79: =VLOOKUP(K79,'restaurant name correction'!$A$1:$B$44,2,0) -> The Himalayan Momo Company | AE79: =VLOOKUP(Z79,restaurant_area_correction!$A$1:$B$18,2,0) -> HSR | AF79: =VALUE(IFERROR(MID(D79,FIND(":",D79,FIND("total_offer_discount",D79))+1,FIND(",",D79,FIND("total_offer_discount",D79)) - FIND(":",D79,FIND("total_offer_discount",D79))-1),0)) -> 0 | AG79: =DATEVALUE(E79) -> 45224 | AH79: =TIMEVALUE(E79) -> 0.81804398 | AI79: =TEXT(AG79,"dddd") -> Wednesday | AJ79: =VLOOKUP(HOUR(Orders[[#This Row],[Time]]),$AQ$1:$AR$7,2,1) -> Evening | AK79: =IF(Orders[[#This Row],[rain_mode]]=0,"Sunny","Rainy") -> Sunny
A80: 157095860714592 | B80: TRUE | C80: LUNCHBINGE | D80: [{"id":"ea6bee14-f548-4089-84e7-e3203d403723","super_type":"SUPERTYPE_UNSPECIFIED","total_offer_discount":99.99,"discount_share":{"swiggy_discount":30,"store_discount":69.99,"alliance_discount":0},"discount_type":"FLAT","description":"FLAT100 off","fixed_charges":{"gp":{"id":"","final_price":0}}}] | E80: 2023-10-24 11:14:20 | F80: 2023-10-24 11:14:46 | G80: 21191609 | H80: Delivered | I80: SATHISHIUMAR G S | J80: 348329 | K80: Paratha Envy | L80: NO.1560/1435/33, K SOMASHEKHAR REDDY, KAIKONDRAHALLI, BANGALORE., Mahadevapura , B.B.M.P East, Karnataka-560035 | M80: Kaikondrahalli | N80: Bangalore | O80: 2007 | P80: 300 | Q80: 300 | R80: 300 | S80: 357 | T80: 41 | U80: 0 | V80: 12.9075344,77.67582123 | W80: 5 | X80: LUNCHBINGE | Y80: UPIIntent | Z80: Sarjapur Road | AA80: TRUE | AB80: 0 | AC80: =IF(X80="","No Coupon Applied",X80) -> LUNCHBINGE | AD80: =VLOOKUP(K80,'restaurant name correction'!$A$1:$B$44,2,0) -> Paratha Envy | AE80: =VLOOKUP(Z80,restaurant_area_correction!$A$1:$B$18,2,0) -> Sarjapur | AF80: =VALUE(IFERROR(MID(D80,FIND(":",D80,FIND("total_offer_discount",D80))+1,FIND(",",D80,FIND("total_offer_discount",D80)) - FIND(":",D80,FIND("total_offer_discount",D80))-1),0)) -> 99.99 | AG80: =DATEVALUE(E80) -> 45223 | AH80: =TIMEVALUE(E80) -> 0.46828704 | AI80: =TEXT(AG80,"dddd") -> Tuesday | AJ80: =VLOOKUP(HOUR(Orders[[#This Row],[Time]]),$AQ$1:$AR$7,2,1) -> Late Morning | AK80: =IF(Orders[[#This Row],[rain_mode]]=0,"Sunny","Rainy") -> Sunny
A81: 156956128612767 | B81: TRUE | C81: WORLDCUPMANIA | D81: [{"id":"3bd1bb74-de3a-4270-a72c-02c43dcf7ce4","super_type":"SUPERTYPE_UNSPECIFIED","total_offer_discount":150,"discount_share":{"swiggy_discount":75,"store_discount":75,"alliance_discount":0},"discount_type":"FLAT","description":"FLAT150 off","fixed_charges":{"gp":{"id":"","final_price":0}}}] | E81: 2023-10-22 20:25:28 | F81: 2023-10-22 20:25:40 | G81: 21191609 | H81: Delivered | I81: RAHULB B | J81: 17036 | K81: Leon's - Burgers & Wings (Leon Grill) | L81: No.17, Ground Floor, 18th Cross Road, 3rd Sector, HSR Layout, Bangalore. | M81: HSR Layout | N81: Bangalore | O81: 927 | P81: 221 | Q81: 221 | R81: 221 | S81: 320.86 | T81: 33 | U81: 0 | V81: 12.91183127,77.64382903 | W81: 1.3 | X81: WORLDCUPMANIA | Y81: UPIIntent | Z81: HSR Layout | AA81: FALSE | AB81: 0 | AC81: =IF(X81="","No Coupon Applied",X81) -> WORLDCUPMANIA | AD81: =VLOOKUP(K81,'restaurant name correction'!$A$1:$B$44,2,0) -> Leon's | AE81: =VLOOKUP(Z81,restaurant_area_correction!$A$1:$B$18,2,0) -> HSR | AF81: =VALUE(IFERROR(MID(D81,FIND(":",D81,FIND("total_offer_discount",D81))+1,FIND(",",D81,FIND("total_offer_discount",D81)) - FIND(":",D81,FIND("total_offer_discount",D81))-1),0)) -> 150 | AG81: =DATEVALUE(E81) -> 45221 | AH81: =TIMEVALUE(E81) -> 0.85101852 | AI81: =TEXT(AG81,"dddd") -> Sunday | AJ81: =VLOOKUP(HOUR(Orders[[#This Row],[Time]]),$AQ$1:$AR$7,2,1) -> Night | AK81: =IF(Orders[[#This Row],[rain_mode]]=0,"Sunny","Rainy") -> Sunny
A82: 156923241346336 | B82: TRUE | C82: WORLDCUPMANIA | D82: [{"id":"8f719de5-eb1b-4866-993e-5d0ef85a8583","super_type":"SUPERTYPE_UNSPECIFIED","total_offer_discount":149.98000000000002,"discount_share":{"swiggy_discount":30,"store_discount":119.98,"alliance_discount":0},"discount_type":"FLAT","description":"FLAT150 off","fixed_charges":{"gp":{"id":"","final_price":0}}}] | E82: 2023-10-22 11:17:21 | F82: 2023-10-22 11:17:36 | G82: 21191609 | H82: Delivered | I82: Rajesh das | J82: 81810 | K82: Tharavadu family restaurant | L82: 1st FLOOR, NO.116/1, HOSUR MAIN ROAD, MANGAMMANAPALYA CROSS, BOMMANAHALLI , Bommenahalli , Bangalore South, Bangalore Urban, Karnataka-560068 | M82: Hosur Main Road | N82: Bangalore | O82: 1957 | P82: 289 | Q82: 289 | R82: 289 | S82: 410 | T82: 41 | U82: 0 | V82: 12.906146,77.629745 | W82: 3.3 | X82: WORLDCUPMANIA | Y82: UPIIntent | Z82: Bommanahalli | AA82: FALSE | AB82: 0 | AC82: =IF(X82="","No Coupon Applied",X82) -> WORLDCUPMANIA | AD82: =VLOOKUP(K82,'restaurant name correction'!$A$1:$B$44,2,0) -> Tharavadu family restaurant | AE82: =VLOOKUP(Z82,restaurant_area_correction!$A$1:$B$18,2,0) -> Bommanahalli | AF82: =VALUE(IFERROR(MID(D82,FIND(":",D82,FIND("total_offer_discount",D82))+1,FIND(",",D82,FIND("total_offer_discount",D82)) - FIND(":",D82,FIND("total_offer_discount",D82))-1),0)) -> 149.98 | AG82: =DATEVALUE(E82) -> 45221 | AH82: =TIMEVALUE(E82) -> 0.47038194 | AI82: =TEXT(AG82,"dddd") -> Sunday | AJ82: =VLOOKUP(HOUR(Orders[[#This Row],[Time]]),$AQ$1:$AR$7,2,1) -> Late Morning | AK82: =IF(Orders[[#This Row],[rain_mode]]=0,"Sunny","Rainy") -> Sunny
A83: 156864275866899 | B83: FALSE | E83: 2023-10-21 18:54:35 | F83: 2023-10-21 18:54:52 | G83: 21191609 | H83: Delivered | I83: Dibyajit Phukan | J83: 55737 | K83: Kairali Restaurant | L83: 32/21 near Maruti showroom outer ring road belladur Bangalore | M83: Outer Ring Road | N83: Bangalore | O83: 2025 | P83: 265 | Q83: 265 | R83: 265 | S83: 239 | T83: 49 | U83: 0 | V83: 12.928069,77.679204 | W83: 4.2 | Y83: UPIIntent | Z83: Bellandur | AA83: FALSE | AB83: 0 | AC83: =IF(X83="","No Coupon Applied",X83) -> No Coupon Applied | AD83: =VLOOKUP(K83,'restaurant name correction'!$A$1:$B$44,2,0) -> Kairali Restaurant | AE83: =VLOOKUP(Z83,restaurant_area_correction!$A$1:$B$18,2,0) -> Bellandur | AF83: =VALUE(IFERROR(MID(D83,FIND(":",D83,FIND("total_offer_discount",D83))+1,FIND(",",D83,FIND("total_offer_discount",D83)) - FIND(":",D83,FIND("total_offer_discount",D83))-1),0)) -> 0 | AG83: =DATEVALUE(E83) -> 45220 | AH83: =TIMEVALUE(E83) -> 0.78790509 | AI83: =TEXT(AG83,"dddd") -> Saturday | AJ83: =VLOOKUP(HOUR(Orders[[#This Row],[Time]]),$AQ$1:$AR$7,2,1) -> Evening | AK83: =IF(Orders[[#This Row],[rain_mode]]=0,"Sunny","Rainy") -> Sunny
A84: 156652104418064 | B84: TRUE | C84: TRYNEW-XL | D84: [{"id":"b78bb0be-4ca2-4b04-af1e-66e991460b12","super_type":"SUPERTYPE_UNSPECIFIED","total_offer_discount":62.099999999999994,"discount_share":{"swiggy_discount":18.63,"store_discount":43.47,"alliance_discount":0},"discount_type":"PERCENTAGE","description":"30% off","fixed_charges":{"gp":{"id":"","final_price":0}}}] | E84: 2023-10-19 07:58:24 | F84: 2023-10-19 07:58:54 | G84: 21191609 | H84: Delivered | I84: Debasish Mahapatra | J84: 201224 | K84: Asha tiffins | L84: Asha Tiffins, 5th Main Road, Sector 7, HSR Layout, Bengaluru, Karnataka, India | M84: 7th Sector | N84: Bangalore | O84: 753 | P84: 189 | Q84: 189 | R84: 189 | S84: 207 | T84: 30 | U84: 0 | V84: 12.911856,77.6325489999999 | W84: 2.4 | X84: TRYNEW-XL | Y84: UPICollect | Z84: Hsr Layout | AA84: TRUE | AB84: 0 | AC84: =IF(X84="","No Coupon Applied",X84) -> TRYNEW-XL | AD84: =VLOOKUP(K84,'restaurant name correction'!$A$1:$B$44,2,0) -> Asha tiffins | AE84: =VLOOKUP(Z84,restaurant_area_correction!$A$1:$B$18,2,0) -> HSR | AF84: =VALUE(IFERROR(MID(D84,FIND(":",D84,FIND("total_offer_discount",D84))+1,FIND(",",D84,FIND("total_offer_discount",D84)) - FIND(":",D84,FIND("total_offer_discount",D84))-1),0)) -> 62.1 | AG84: =DATEVALUE(E84) -> 45218 | AH84: =TIMEVALUE(E84) -> 0.33222222 | AI84: =TEXT(AG84,"dddd") -> Thursday | AJ84: =VLOOKUP(HOUR(Orders[[#This Row],[Time]]),$AQ$1:$AR$7,2,1) -> Morning | AK84: =IF(Orders[[#This Row],[rain_mode]]=0,"Sunny","Rainy") -> Sunny
A85: 155826395288522 | B85: TRUE | C85: SWIGGYIT | D85: [{"id":"6ee62658-3aa8-497e-8248-ac41eba5d5ef","super_type":"SUPERTYPE_UNSPECIFIED","total_offer_discount":50,"discount_share":{"swiggy_discount":15,"store_discount":35,"alliance_discount":0},"discount_type":"PERCENTAGE","description":"20% off","fixed_charges":{"gp":{"id":"","final_price":0}}}] | E85: 2023-10-09 18:36:35 | F85: 2023-10-09 18:36:50 | G85: 21191609 | H85: Delivered | I85: Anil Kumar Yadav | J85: 709170 | K85: Imperio Restaurant | L85: imperio restaurant , 495, 17th Cross Rd, Parangi Palaya, Sector 2, HSR Layout, Bengaluru, Karnataka | M85: Sector 2 | N85: Bangalore | O85: 1001 | P85: 229 | Q85: 229 | R85: 229 | S85: 258 | T85: 48 | U85: 0 | V85: 12.91181824,77.6495233 | W85: 0.7 | X85: SWIGGYIT | Y85: UPIIntent | Z85: HSR | AA85: TRUE | AB85: 2 | AC85: =IF(X85="","No Coupon Applied",X85) -> SWIGGYIT | AD85: =VLOOKUP(K85,'restaurant name correction'!$A$1:$B$44,2,0) -> Imperio Restaurant | AE85: =VLOOKUP(Z85,restaurant_area_correction!$A$1:$B$18,2,0) -> HSR | AF85: =VALUE(IFERROR(MID(D85,FIND(":",D85,FIND("total_offer_discount",D85))+1,FIND(",",D85,FIND("total_offer_discount",D85)) - FIND(":",D85,FIND("total_offer_discount",D85))-1),0)) -> 50 | AG85: =DATEVALUE(E85) -> 45208 | AH85: =TIMEVALUE(E85) -> 0.77540509 | AI85: =TEXT(AG85,"dddd") -> Monday | AJ85: =VLOOKUP(HOUR(Orders[[#This Row],[Time]]),$AQ$1:$AR$7,2,1) -> Evening | AK85: =IF(Orders[[#This Row],[rain_mode]]=0,"Sunny","Rainy") -> Rainy
A86: 154933952448406 | B86: FALSE | E86: 2023-09-29 10:42:32 | F86: 2023-09-29 10:42:49 | G86: 21191609 | H86: Delivered | I86: Jaydev nath | J86: 348329 | K86: Paratha Envy | L86: NO.1560/1435/33, K SOMASHEKHAR REDDY, KAIKONDRAHALLI, BANGALORE., Mahadevapura , B.B.M.P East, Karnataka-560035 | M86: Kaikondrahalli | N86: Bangalore | O86: 2566 | P86: 553 | Q86: 553 | R86: 553 | S86: 535 | T86: 44 | U86: 0 | V86: 12.9075344,77.67582123 | W86: 5 | Y86: UPICollect | Z86: Sarjapur Road | AA86: TRUE | AB86: 0 | AC86: =IF(X86="","No Coupon Applied",X86) -> No Coupon Applied | AD86: =VLOOKUP(K86,'restaurant name correction'!$A$1:$B$44,2,0) -> Paratha Envy | AE86: =VLOOKUP(Z86,restaurant_area_correction!$A$1:$B$18,2,0) -> Sarjapur | AF86: =VALUE(IFERROR(MID(D86,FIND(":",D86,FIND("total_offer_discount",D86))+1,FIND(",",D86,FIND("total_offer_discount",D86)) - FIND(":",D86,FIND("total_offer_discount",D86))-1),0)) -> 0 | AG86: =DATEVALUE(E86) -> 45198 | AH86: =TIMEVALUE(E86) -> 0.4462037 | AI86: =TEXT(AG86,"dddd") -> Friday | AJ86: =VLOOKUP(HOUR(Orders[[#This Row],[Time]]),$AQ$1:$AR$7,2,1) -> Late Morning | AK86: =IF(Orders[[#This Row],[rain_mode]]=0,"Sunny","Rainy") -> Sunny
A87: 178713153585 | B87: TRUE | C87: TRYNEW | D87: [{"id":"60385055-547d-4c3b-bef2-75f14c9cfb0d","super_type":"SUPERTYPE_UNSPECIFIED","total_offer_discount":119.99,"discount_share":{"swiggy_discount":36,"store_discount":83.99,"alliance_discount":0},"discount_type":"PERCENTAGE","description":"60% off","fixed_charges":{"gp":{"id":"","final_price":0}}}] | E87: 2023-09-25 16:02:34 | F87: 2023-09-25 16:03:35 | G87: 21191609 | H87: Delivered | I87: Prakash Dalabehera | J87: 81810 | K87: Tharavadu family restaurant | L87: 1st FLOOR, NO.116/1, HOSUR MAIN ROAD, MANGAMMANAPALYA CROSS, BOMMANAHALLI , Bommenahalli , Bangalore South, Bangalore Urban, Karnataka-560068 | M87: Hosur Main Road | N87: Bangalore | O87: 1467 | P87: 362 | Q87: 362 | R87: 362 | S87: 441 | T87: 34 | U87: 0 | V87: 12.906146,77.629745 | W87: 3.3 | X87: TRYNEW | Y87: UPICollect | Z87: Bommanahalli | AA87: TRUE | AB87: 0 | AC87: =IF(X87="","No Coupon Applied",X87) -> TRYNEW | AD87: =VLOOKUP(K87,'restaurant name correction'!$A$1:$B$44,2,0) -> Tharavadu family restaurant | AE87: =VLOOKUP(Z87,restaurant_area_correction!$A$1:$B$18,2,0) -> Bommanahalli | AF87: =VALUE(IFERROR(MID(D87,FIND(":",D87,FIND("total_offer_discount",D87))+1,FIND(",",D87,FIND("total_offer_discount",D87)) - FIND(":",D87,FIND("total_offer_discount",D87))-1),0)) -> 119.99 | AG87: =DATEVALUE(E87) -> 45194 | AH87: =TIMEVALUE(E87) -> 0.66844907 | AI87: =TEXT(AG87,"dddd") -> Monday | AJ87: =VLOOKUP(HOUR(Orders[[#This Row],[Time]]),$AQ$1:$AR$7,2,1) -> Evening | AK87: =IF(Orders[[#This Row],[rain_mode]]=0,"Sunny","Rainy") -> Sunny
A88: 178539970232 | B88: FALSE | E88: 2023-09-23 15:56:11 | F88: 2023-09-23 15:56:34 | G88: 21191609 | H88: Delivered | I88: Akshay Akshay | J88: 567783 | K88: HSR Freshcane Juice | L88: NO 2333, 24TH MAIN,17TH CROSS SECTOR NO 1, HSR LAYOUT, Bommanahalli , B.B.M.P South, , Karnataka, 560102 | M88: 1st Sector | N88: Bangalore | O88: 1835 | P88: 281 | Q88: 281 | R88: 281 | S88: 256 | T88: 31 | U88: 0 | V88: 12.912110164242,77.648900840197 | W88: 0.5 | Y88: UPICollect | Z88: Hsr Layout | AA88: FALSE | AB88: 0 | AC88: =IF(X88="","No Coupon Applied",X88) -> No Coupon Applied | AD88: =VLOOKUP(K88,'restaurant name correction'!$A$1:$B$44,2,0) -> HSR Freshcane Juice | AE88: =VLOOKUP(Z88,restaurant_area_correction!$A$1:$B$18,2,0) -> HSR | AF88: =VALUE(IFERROR(MID(D88,FIND(":",D88,FIND("total_offer_discount",D88))+1,FIND(",",D88,FIND("total_offer_discount",D88)) - FIND(":",D88,FIND("total_offer_discount",D88))-1),0)) -> 0 | AG88: =DATEVALUE(E88) -> 45192 | AH88: =TIMEVALUE(E88) -> 0.6640162 | AI88: =TEXT(AG88,"dddd") -> Saturday | AJ88: =VLOOKUP(HOUR(Orders[[#This Row],[Time]]),$AQ$1:$AR$7,2,1) -> Afternoon | AK88: =IF(Orders[[#This Row],[rain_mode]]=0,"Sunny","Rainy") -> Sunny
A89: 178180906036 | B89: TRUE | C89: TRYNEW | D89: [{"id":"0c2819fc-1836-431a-8677-00e94af123b8","super_type":"SUPERTYPE_UNSPECIFIED","total_offer_discount":49.99,"discount_share":{"swiggy_discount":15,"store_discount":34.99,"alliance_discount":0},"discount_type":"PERCENTAGE","description":"20% off","fixed_charges":{"gp":{"id":"","final_price":0}}}] | E89: 2023-09-19 12:11:47 | F89: 2023-09-19 12:12:10 | G89: 21191609 | H89: Delivered | I89: Santakar Santapriya | J89: 709170 | K89: Imperio Restaurant | L89: imperio restaurant , 495, 17th Cross Rd, Parangi Palaya, Sector 2, HSR Layout, Bengaluru, Karnataka | M89: Sector 2 | N89: Bangalore | O89: 971 | P89: 301 | Q89: 301 | R89: 301 | S89: 318 | T89: 28 | U89: 0 | V89: 12.91181824,77.6495233 | W89: 0.7 | X89: TRYNEW | Y89: UPICollect | Z89: HSR | AA89: TRUE | AB89: 0 | AC89: =IF(X89="","No Coupon Applied",X89) -> TRYNEW | AD89: =VLOOKUP(K89,'restaurant name correction'!$A$1:$B$44,2,0) -> Imperio Restaurant | AE89: =VLOOKUP(Z89,restaurant_area_correction!$A$1:$B$18,2,0) -> HSR | AF89: =VALUE(IFERROR(MID(D89,FIND(":",D89,FIND("total_offer_discount",D89))+1,FIND(",",D89,FIND("total_offer_discount",D89)) - FIND(":",D89,FIND("total_offer_discount",D89))-1),0)) -> 49.99 | AG89: =DATEVALUE(E89) -> 45188 | AH89: =TIMEVALUE(E89) -> 0.50818287 | AI89: =TEXT(AG89,"dddd") -> Tuesday | AJ89: =VLOOKUP(HOUR(Orders[[#This Row],[Time]]),$AQ$1:$AR$7,2,1) -> Afternoon | AK89: =IF(Orders[[#This Row],[rain_mode]]=0,"Sunny","Rainy") -> Sunny
A90: 178090781440 | B90: FALSE | E90: 2023-09-18 11:09:42 | F90: 2023-09-18 11:10:02 | G90: 21191609 | H90: Delivered | I90: Ramesh K | J90: 62430 | K90: Dosa Chicken & Tiffins | L90: 235, 9th Main Road, Sector 7, HSR Layout, Sector 7, HSR Layout, Bengaluru, Karnataka 560102 | M90: 7th Sector | N90: Bangalore | O90: 2783 | P90: 190 | Q90: 190 | R90: 190 | S90: 169 | T90: 28 | U90: 0 | V90: 12.912837,77.63510900000006 | W90: 2 | Y90: UPICollect | Z90: HSR Layout | AA90: TRUE | AB90: 0 | AC90: =IF(X90="","No Coupon Applied",X90) -> No Coupon Applied | AD90: =VLOOKUP(K90,'restaurant name correction'!$A$1:$B$44,2,0) -> Dosa Chicken & Tiffins | AE90: =VLOOKUP(Z90,restaurant_area_correction!$A$1:$B$18,2,0) -> HSR | AF90: =VALUE(IFERROR(MID(D90,FIND(":",D90,FIND("total_offer_discount",D90))+1,FIND(",",D90,FIND("total_offer_discount",D90)) - FIND(":",D90,FIND("total_offer_discount",D90))-1),0)) -> 0 | AG90: =DATEVALUE(E90) -> 45187 | AH90: =TIMEVALUE(E90) -> 0.46506944 | AI90: =TEXT(AG90,"dddd") -> Monday | AJ90: =VLOOKUP(HOUR(Orders[[#This Row],[Time]]),$AQ$1:$AR$7,2,1) -> Late Morning | AK90: =IF(Orders[[#This Row],[rain_mode]]=0,"Sunny","Rainy") -> Sunny
A91: 177591184372 | B91: TRUE | C91: SPECIALS | D91: [{"id":"73f920b6-b8d2-4b29-b4a9-72846208860d","super_type":"SUPERTYPE_UNSPECIFIED","total_offer_discount":80,"discount_share":{"swiggy_discount":32,"store_discount":48,"alliance_discount":0},"discount_type":"PERCENTAGE","description":"40% off","fixed_charges":{"gp":{"id":"","final_price":0}}}] | E91: 2023-09-12 16:23:04 | F91: 2023-09-12 16:23:21 | G91: 21191609 | H91: Delivered | I91: Avverahalli Mallesh Basavesh | J91: 2675 | K91: Subway | L91: 36, 3rd Store, 7th Sector, 14th main, HSR Layout | M91: 7th Sector | N91: Bangalore | O91: 1091 | P91: 244 | Q91: 244 | R91: 244 | S91: 299 | T91: 28 | U91: 0 | V91: 12.9118135,77.637958 | W91: 1.7 | X91: SPECIALS | Y91: UPICollect | Z91: Hsr Layout | AA91: TRUE | AB91: 0 | AC91: =IF(X91="","No Coupon Applied",X91) -> SPECIALS | AD91: =VLOOKUP(K91,'restaurant name correction'!$A$1:$B$44,2,0) -> Subway | AE91: =VLOOKUP(Z91,restaurant_area_correction!$A$1:$B$18,2,0) -> HSR | AF91: =VALUE(IFERROR(MID(D91,FIND(":",D91,FIND("total_offer_discount",D91))+1,FIND(",",D91,FIND("total_offer_discount",D91)) - FIND(":",D91,FIND("total_offer_discount",D91))-1),0)) -> 80 | AG91: =DATEVALUE(E91) -> 45181 | AH91: =TIMEVALUE(E91) -> 0.68268519 | AI91: =TEXT(AG91,"dddd") -> Tuesday | AJ91: =VLOOKUP(HOUR(Orders[[#This Row],[Time]]),$AQ$1:$AR$7,2,1) -> Evening | AK91: =IF(Orders[[#This Row],[rain_mode]]=0,"Sunny","Rainy") -> Sunny
A92: 177445532607 | B92: TRUE | C92: PARTY | D92: [{"id":"1178c39c-98d9-4510-b5b7-122edfb7e4fc","super_type":"SUPERTYPE_UNSPECIFIED","total_offer_discount":138,"discount_share":{"swiggy_discount":0,"store_discount":138,"alliance_discount":0},"discount_type":"PERCENTAGE","description":"10% off","fixed_charges":{"gp":{"id":"","final_price":0}}}] | E92: 2023-09-10 23:55:33 | F92: 2023-09-10 23:55:52 | G92: 21191609 | H92: Delivered | I92: Amitabh Kumar Pavan | J92: 395574 | K92: Plan B | L92: No 2324, 17th Cross Road, 1st Sector, HSR Layout, Bengaluru, Karnataka 560012 | M92: 1st Sector | N92: Bangalore | O92: 2259 | P92: 1369 | Q92: 1369 | R92: 1369 | S92: 1380 | T92: 41 | U92: 0 | V92: 12.912120631518187,77.65069759736535 | W92: 0.8 | X92: PARTY | Y92: UPICollect | Z92: HSR Layout | AA92: TRUE | AB92: 0 | AC92: =IF(X92="","No Coupon Applied",X92) -> PARTY | AD92: =VLOOKUP(K92,'restaurant name correction'!$A$1:$B$44,2,0) -> Plan B | AE92: =VLOOKUP(Z92,restaurant_area_correction!$A$1:$B$18,2,0) -> HSR | AF92: =VALUE(IFERROR(MID(D92,FIND(":",D92,FIND("total_offer_discount",D92))+1,FIND(",",D92,FIND("total_offer_discount",D92)) - FIND(":",D92,FIND("total_offer_discount",D92))-1),0)) -> 138 | AG92: =DATEVALUE(E92) -> 45179 | AH92: =TIMEVALUE(E92) -> 0.99690972 | AI92: =TEXT(AG92,"dddd") -> Sunday | AJ92: =VLOOKUP(HOUR(Orders[[#This Row],[Time]]),$AQ$1:$AR$7,2,1) -> Night | AK92: =IF(Orders[[#This Row],[rain_mode]]=0,"Sunny","Rainy") -> Sunny
A93: 177265186487 | B93: TRUE | C93: PARTY | D93: [{"id":"1178c39c-98d9-4510-b5b7-122edfb7e4fc","super_type":"SUPERTYPE_UNSPECIFIED","total_offer_discount":197,"discount_share":{"swiggy_discount":0,"store_discount":197,"alliance_discount":0},"discount_type":"PERCENTAGE","description":"10% off","fixed_charges":{"gp":{"id":"","final_price":0}}}] | E93: 2023-09-08 21:49:47 | F93: 2023-09-08 21:50:07 | G93: 21191609 | H93: Delivered | I93: Monirul Hoque | J93: 395574 | K93: Plan B | L93: No 2324, 17th Cross Road, 1st Sector, HSR Layout, Bengaluru, Karnataka 560012 | M93: 1st Sector | N93: Bangalore | O93: 2907 | P93: 1905 | Q93: 1905 | R93: 1905 | S93: 1970 | T93: 37 | U93: 0 | V93: 12.912120631518187,77.65069759736535 | W93: 0.7 | X93: PARTY | Y93: UPICollect | Z93: HSR Layout | AA93: TRUE | AB93: 0 | AC93: =IF(X93="","No Coupon Applied",X93) -> PARTY | AD93: =VLOOKUP(K93,'restaurant name correction'!$A$1:$B$44,2,0) -> Plan B | AE93: =VLOOKUP(Z93,restaurant_area_correction!$A$1:$B$18,2,0) -> HSR | AF93: =VALUE(IFERROR(MID(D93,FIND(":",D93,FIND("total_offer_discount",D93))+1,FIND(",",D93,FIND("total_offer_discount",D93)) - FIND(":",D93,FIND("total_offer_discount",D93))-1),0)) -> 197 | AG93: =DATEVALUE(E93) -> 45177 | AH93: =TIMEVALUE(E93) -> 0.90957176 | AI93: =TEXT(AG93,"dddd") -> Friday | AJ93: =VLOOKUP(HOUR(Orders[[#This Row],[Time]]),$AQ$1:$AR$7,2,1) -> Night | AK93: =IF(Orders[[#This Row],[rain_mode]]=0,"Sunny","Rainy") -> Sunny
A94: 176793394432 | B94: TRUE | C94: TRYNEW | D94: [{"id":"6ca97531-301c-4632-a58f-646d0afd9e01","super_type":"SUPERTYPE_UNSPECIFIED","total_offer_discount":39.8,"discount_share":{"swiggy_discount":0,"store_discount":39.8,"alliance_discount":0},"discount_type":"PERCENTAGE","description":"10% off","fixed_charges":{"gp":{"id":"","final_price":0}}}] | E94: 2023-09-03 10:46:35 | F94: 0 | G94: 21191609 | H94: Delivered | I94: Priyabrata Jena | J94: 298606 | K94: Drunken Monkey | L94: No.634 ground floor,5th cross,15th main ,4th block,kormangala (near chinmaya vidyalaya school),bangalore 560034 | M94: 4th Block | N94: Bangalore | O94: 1712 | P94: 399 | Q94: 399 | R94: 399 | S94: 398 | T94: 44 | U94: 0 | V94: 12.934488559072948,77.62886978481599 | W94: 4.4 | X94: TRYNEW | Y94: UPIIntent | Z94: Koramangala | AA94: FALSE | AB94: 0 | AC94: =IF(X94="","No Coupon Applied",X94) -> TRYNEW | AD94: =VLOOKUP(K94,'restaurant name correction'!$A$1:$B$44,2,0) -> Drunken Monkey | AE94: =VLOOKUP(Z94,restaurant_area_correction!$A$1:$B$18,2,0) -> Koramangala | AF94: =VALUE(IFERROR(MID(D94,FIND(":",D94,FIND("total_offer_discount",D94))+1,FIND(",",D94,FIND("total_offer_discount",D94)) - FIND(":",D94,FIND("total_offer_discount",D94))-1),0)) -> 39.8 | AG94: =DATEVALUE(E94) -> 45172 | AH94: =TIMEVALUE(E94) -> 0.4490162 | AI94: =TEXT(AG94,"dddd") -> Sunday | AJ94: =VLOOKUP(HOUR(Orders[[#This Row],[Time]]),$AQ$1:$AR$7,2,1) -> Late Morning | AK94: =IF(Orders[[#This Row],[rain_mode]]=0,"Sunny","Rainy") -> Sunny
A95: 176745115332 | B95: TRUE | C95: TRYNEW | D95: [{"id":"f80596b9-9db2-47d0-98be-dbdde4df4855","super_type":"SUPERTYPE_UNSPECIFIED","total_offer_discount":100,"discount_share":{"swiggy_discount":0,"store_discount":100,"alliance_discount":0},"discount_type":"PERCENTAGE","description":"50% off","fixed_charges":{"gp":{"id":"","final_price":0}}}] | E95: 2023-09-02 21:21:56 | F95: 0 | G95: 21191609 | H95: Delivered | I95: Manoj Kumar H M | J95: 254655 | K95: Daily Sushi | L95: No.1212, SBM Fortune, 4th Floor, 22nd Cross Road, 14th Main Rd, 3rd Sector, HSR Layout, Bengaluru, Karnataka 560102, India | M95: 3rd Sector | N95: Bangalore | O95: 2738 | P95: 359 | Q95: 359 | R95: 359 | S95: 400 | T95: 36 | U95: 0 | V95: 12.909368,77.638656 | W95: 2.1 | X95: TRYNEW | Y95: UPIIntent | Z95: HSR Layout | AA95: FALSE | AB95: 0 | AC95: =IF(X95="","No Coupon Applied",X95) -> TRYNEW | AD95: =VLOOKUP(K95,'restaurant name correction'!$A$1:$B$44,2,0) -> Daily Sushi | AE95: =VLOOKUP(Z95,restaurant_area_correction!$A$1:$B$18,2,0) -> HSR | AF95: =VALUE(IFERROR(MID(D95,FIND(":",D95,FIND("total_offer_discount",D95))+1,FIND(",",D95,FIND("total_offer_discount",D95)) - FIND(":",D95,FIND("total_offer_discount",D95))-1),0)) -> 100 | AG95: =DATEVALUE(E95) -> 45171 | AH95: =TIMEVALUE(E95) -> 0.89023148 | AI95: =TEXT(AG95,"dddd") -> Saturday | AJ95: =VLOOKUP(HOUR(Orders[[#This Row],[Time]]),$AQ$1:$AR$7,2,1) -> Night | AK95: =IF(Orders[[#This Row],[rain_mode]]=0,"Sunny","Rainy") -> Sunny
A96: 176716772573 | B96: TRUE | C96: WEEKENDS | D96: [{"id":"e7ca910b-b1f7-4fca-81aa-29bb167a90b0","super_type":"SUPERTYPE_UNSPECIFIED","total_offer_discount":125,"discount_share":{"swiggy_discount":50,"store_discount":75,"alliance_discount":0},"discount_type":"FLAT","description":"Flat ₹125 off","fixed_charges":{"gp":{"id":"","final_price":0}}}] | E96: 2023-09-02 13:29:33 | F96: 0 | G96: 21191609 | H96: Delivered | I96: Raghunatha | J96: 341895 | K96: Burger Seigneur | L96: NO.35, 80FEET ROAD, HAL 3RD STAGE, BANGALORE B.B.M.P East Karnataka 560075 | M96: Indiranagar | N96: Bangalore | O96: 2483 | P96: 356 | Q96: 356 | R96: 356 | S96: 460 | T96: 34 | U96: 0 | V96: 12.97107,77.647521 | W96: 1.5 | X96: WEEKENDS | Y96: UPIIntent | Z96: Indiranagar | AA96: TRUE | AB96: 0 | AC96: =IF(X96="","No Coupon Applied",X96) -> WEEKENDS | AD96: =VLOOKUP(K96,'restaurant name correction'!$A$1:$B$44,2,0) -> Burger Seigneur | AE96: =VLOOKUP(Z96,restaurant_area_correction!$A$1:$B$18,2,0) -> Indiranagar | AF96: =VALUE(IFERROR(MID(D96,FIND(":",D96,FIND("total_offer_discount",D96))+1,FIND(",",D96,FIND("total_offer_discount",D96)) - FIND(":",D96,FIND("total_offer_discount",D96))-1),0)) -> 125 | AG96: =DATEVALUE(E96) -> 45171 | AH96: =TIMEVALUE(E96) -> 0.5621875 | AI96: =TEXT(AG96,"dddd") -> Saturday | AJ96: =VLOOKUP(HOUR(Orders[[#This Row],[Time]]),$AQ$1:$AR$7,2,1) -> Afternoon | AK96: =IF(Orders[[#This Row],[rain_mode]]=0,"Sunny","Rainy") -> Sunny
A97: 176451044220 | B97: FALSE | E97: 2023-08-30 11:40:45 | F97: 0 | G97: 21191609 | H97: Delivered | I97: Kumar R | J97: 47603 | K97: Truffles | L97: BUNDL TECHNOLOGIES PVT LTD, 1ST FLOOR, SITE NO.164, KHATA NO.684, PID NO: 658/668/684/1/164/1, BELLANDURVILLAGE, VARTHUR HOBLI, BANGALORE EAST TALUK 560103 | M97: Green Glen Layout | N97: Bangalore | O97: 1839 | P97: 301 | Q97: 301 | R97: 301 | S97: 261.90997 | T97: 39 | U97: 0 | V97: 12.927332,77.669014 | W97: 4.9 | Y97: UPIIntent | Z97: Bellandur | AA97: FALSE | AB97: 0 | AC97: =IF(X97="","No Coupon Applied",X97) -> No Coupon Applied | AD97: =VLOOKUP(K97,'restaurant name correction'!$A$1:$B$44,2,0) -> Truffles | AE97: =VLOOKUP(Z97,restaurant_area_correction!$A$1:$B$18,2,0) -> Bellandur | AF97: =VALUE(IFERROR(MID(D97,FIND(":",D97,FIND("total_offer_discount",D97))+1,FIND(",",D97,FIND("total_offer_discount",D97)) - FIND(":",D97,FIND("total_offer_discount",D97))-1),0)) -> 0 | AG97: =DATEVALUE(E97) -> 45168 | AH97: =TIMEVALUE(E97) -> 0.48663194 | AI97: =TEXT(AG97,"dddd") -> Wednesday | AJ97: =VLOOKUP(HOUR(Orders[[#This Row],[Time]]),$AQ$1:$AR$7,2,1) -> Late Morning | AK97: =IF(Orders[[#This Row],[rain_mode]]=0,"Sunny","Rainy") -> Sunny
A98: 176221057630 | B98: FALSE | E98: 2023-08-27 19:47:38 | F98: 0 | G98: 21191609 | H98: Delivered | I98: Paresh Kumar Mohanty | J98: 498292 | K98: Istah - The Mediterranean Way | L98: 88/1, Ward No, 66, Swiggy Koramangala Super Hub building, Sarjapur Road, Jakkasandra Village, Bangalore 560034 | M98: 1st Block | N98: Bangalore | O98: 2187 | P98: 164 | Q98: 164 | R98: 164 | S98: 199 | T98: 41 | U98: 0 | V98: 12.925114189248388,77.6370633020997 | W98: 3.1 | Y98: UPIIntent | Z98: Koramangala | AA98: FALSE | AB98: 0 | AC98: =IF(X98="","No Coupon Applied",X98) -> No Coupon Applied | AD98: =VLOOKUP(K98,'restaurant name correction'!$A$1:$B$44,2,0) -> Istah | AE98: =VLOOKUP(Z98,restaurant_area_correction!$A$1:$B$18,2,0) -> Koramangala | AF98: =VALUE(IFERROR(MID(D98,FIND(":",D98,FIND("total_offer_discount",D98))+1,FIND(",",D98,FIND("total_offer_discount",D98)) - FIND(":",D98,FIND("total_offer_discount",D98))-1),0)) -> 0 | AG98: =DATEVALUE(E98) -> 45165 | AH98: =TIMEVALUE(E98) -> 0.82474537 | AI98: =TEXT(AG98,"dddd") -> Sunday | AJ98: =VLOOKUP(HOUR(Orders[[#This Row],[Time]]),$AQ$1:$AR$7,2,1) -> Evening | AK98: =IF(Orders[[#This Row],[rain_mode]]=0,"Sunny","Rainy") -> Sunny
A99: 175968970700 | B99: TRUE | C99: JUMBO | D99: [{"id":"299a513a-6f7c-458c-86bb-38f205d6dbd9","super_type":"SUPERTYPE_UNSPECIFIED","total_offer_discount":109.5,"discount_share":{"swiggy_discount":21.9,"store_discount":87.6,"alliance_discount":0},"discount_type":"PERCENTAGE","description":"25% off","fixed_charges":{"gp":{"id":"","final_price":0}}}] | E99: 2023-08-24 21:46:11 | F99: 0 | G99: 21191609 | H99: cancelled | J99: 405903 | K99: The Thick Shake Factory | L99: #NO.104, SHIVALAYA, 17TH C MAIN ROAD, 5TH CROSS, KORAMANGALA, 5 TH BLOCK, BANGALORE,560095,Next to Acura Speciality Hospital,pivotal 4th floor. Karnataka - 560095 | M99: 5th Block | N99: Bangalore | O99: 0 | P99: 369 | Q99: 369 | R99: 369 | S99: 438 | T99: 55 | U99: 0 | V99: 12.935401,77.620598 | W99: 5.4 | X99: JUMBO | Y99: UPIIntent | Z99: Koramangala | AA99: FALSE | AB99: 0 | AC99: =IF(X99="","No Coupon Applied",X99) -> JUMBO | AD99: =VLOOKUP(K99,'restaurant name correction'!$A$1:$B$44,2,0) -> The Thick Shake Factory | AE99: =VLOOKUP(Z99,restaurant_area_correction!$A$1:$B$18,2,0) -> Koramangala | AF99: =VALUE(IFERROR(MID(D99,FIND(":",D99,FIND("total_offer_discount",D99))+1,FIND(",",D99,FIND("total_offer_discount",D99)) - FIND(":",D99,FIND("total_offer_discount",D99))-1),0)) -> 109.5 | AG99: =DATEVALUE(E99) -> 45162 | AH99: =TIMEVALUE(E99) -> 0.90707176 | AI99: =TEXT(AG99,"dddd") -> Thursday | AJ99: =VLOOKUP(HOUR(Orders[[#This Row],[Time]]),$AQ$1:$AR$7,2,1) -> Night | AK99: =IF(Orders[[#This Row],[rain_mode]]=0,"Sunny","Rainy") -> Sunny
A100: 175192473312 | B100: FALSE | E100: 2023-08-15 22:04:33 | F100: 0 | G100: 21191609 | H100: Delivered | I100: Asif Alli | J100: 64914 | K100: Kerala Panoor Restaurant | L100: Devarabeesanahalli Flyover, Devarabisanahalli, Bellandur, Bengaluru, Karnataka 560103 | M100: Devarabisanahalli | N100: Bangalore | O100: 1654 | P100: 504 | Q100: 504 | R100: 504 | S100: 465 | T100: 54 | U100: 0 | V100: 12.930556,77.68499199999997 | W100: 5 | Y100: UPIIntent | Z100: Bellandur | AA100: FALSE | AB100: 0 | AC100: =IF(X100="","No Coupon Applied",X100) -> No Coupon Applied | AD100: =VLOOKUP(K100,'restaurant name correction'!$A$1:$B$44,2,0) -> Kerala Panoor Restaurant | AE100: =VLOOKUP(Z100,restaurant_area_correction!$A$1:$B$18,2,0) -> Bellandur | AF100: =VALUE(IFERROR(MID(D100,FIND(":",D100,FIND("total_offer_discount",D100))+1,FIND(",",D100,FIND("total_offer_discount",D100)) - FIND(":",D100,FIND("total_offer_discount",D100))-1),0)) -> 0 | AG100: =DATEVALUE(E100) -> 45153 | AH100: =TIMEVALUE(E100) -> 0.91982639 | AI100: =TEXT(AG100,"dddd") -> Tuesday | AJ100: =VLOOKUP(HOUR(Orders[[#This Row],[Time]]),$AQ$1:$AR$7,2,1) -> Night | AK100: =IF(Orders[[#This Row],[rain_mode]]=0,"Sunny","Rainy") -> Sunny
...

Sheet Swiggy Order Items
A1: order_id | B1: order_items.name | C1: order_items.is_veg | D1: order_items.quantity | E1: Category
A2: 175244332362622 | B2: Michel (Chicken & Mozza Sandwich) | C2: 0 | D2: 1 | E2: =IF(C2=0,"Non_Veg","Veg") -> Non_Veg
A3: 175167017704058 | B3: Supreme Boneless Chicken Biryani | C3: 0 | D3: 1 | E3: =IF(C3=0,"Non_Veg","Veg") -> Non_Veg
A4: 175167017704058 | B4: Mutton Bone Soup | C4: 0 | D4: 1 | E4: =IF(C4=0,"Non_Veg","Veg") -> Non_Veg
A5: 175017114796029 | B5: Mississippi Mud Pie | C5: 0 | D5: 1 | E5: =IF(C5=0,"Non_Veg","Veg") -> Non_Veg
A6: 175017114796029 | B6: Apple Crumble Pie | C6: 1 | D6: 1 | E6: =IF(C6=0,"Non_Veg","Veg") -> Veg
A7: 174973046023416 | B7: Dark Chocolate Smoothie Bowl. | C7: 1 | D7: 1 | E7: =IF(C7=0,"Non_Veg","Veg") -> Veg
A8: 174973046023416 | B8: Banana Peanutbutter Overnight Oats [350kcals][20gm protein] | C8: 1 | D8: 1 | E8: =IF(C8=0,"Non_Veg","Veg") -> Veg
A9: 174906705849277 | B9: Chicken Kheema Lasagne | C9: 0 | D9: 1 | E9: =IF(C9=0,"Non_Veg","Veg") -> Non_Veg
A10: 174906705849277 | B10: Corn & Pepper Lasagne | C10: 1 | D10: 1 | E10: =IF(C10=0,"Non_Veg","Veg") -> Veg
A11: 174329455765789 | B11: Veg. Ramyun | C11: 1 | D11: 1 | E11: =IF(C11=0,"Non_Veg","Veg") -> Veg
A12: 174329455765789 | B12: Chicken Katsu Ramyun | C12: 0 | D12: 1 | E12: =IF(C12=0,"Non_Veg","Veg") -> Non_Veg
A13: 174318296922309 | B13: Onion Rings | C13: 1 | D13: 1 | E13: =IF(C13=0,"Non_Veg","Veg") -> Veg
... A171: 171863054117 | B171: Open Butter Masala Dosa | C171: 1 | D171: 1 | E171: =IF(C171=0,"Non_Veg","Veg") -> Veg

Sheet restaurant name correction
A1: restaurant_name | B1: restaurant_name_updated
A2: Paris Panini - Gourmet Sandwiches & Wraps | B2: =IFERROR(LEFT(A2,FIND("-",A2)-1),A2) -> Paris Panini
A3: Nandhana Palace | B3: =IFERROR(LEFT(A3,FIND("-",A3)-1),A3) -> Nandhana Palace
A4: The Ganache Factory - Cakes & Desserts | B4: =IFERROR(LEFT(A4,FIND("-",A4)-1),A4) -> The Ganache Factory
A5: Rasayan | B5: =IFERROR(LEFT(A5,FIND("-",A5)-1),A5) -> Rasayan
A6: Firangi Bake | B6: =IFERROR(LEFT(A6,FIND("-",A6)-1),A6) -> Firangi Bake
A7: Daily Sushi | B7: =IFERROR(LEFT(A7,FIND("-",A7)-1),A7) -> Daily Sushi
A8: Naalnaad Mane | B8: =IFERROR(LEFT(A8,FIND("-",A8)-1),A8) -> Naalnaad Mane
A9: Theobroma | B9: =IFERROR(LEFT(A9,FIND("-",A9)-1),A9) -> Theobroma
A10: Love And Crumble | B10: =IFERROR(LEFT(A10,FIND("-",A10)-1),A10) -> Love And Crumble
A11: Homely | B11: =IFERROR(LEFT(A11,FIND("-",A11)-1),A11) -> Homely
A12: Chowman | B12: =IFERROR(LEFT(A12,FIND("-",A12)-1),A12) -> Chowman
A13: Frozen Bottle - Milkshakes, Desserts And Ice Cream | B13: =IFERROR(LEFT(A13,FIND("-",A13)-1),A13) -> Frozen Bottle
... A44: Table for Tous | B44: =IFERROR(LEFT(A44,FIND("-",A44)-1),A44) -> Table for Tous

Sheet restaurant_area_correction
A1: restaurant_area_name | B1: restaurant_area_name_updated
A2: JP Nagar | B2: JP Nagar
A3: Jayanagar | B3: Jayanagar
A4: BTM 2nd Stage | B4: BTM
A5: BTM 1st Stage | B5: BTM
A6: Arekere | B6: Arekere
A7: HSR Layout | B7: HSR
A8: Malleshwaram | B8: Malleshwaram
A9: Bellandur | B9: Bellandur
A10: Bellandur Sarjapur | B10: Bellandur
A11: Koramangala | B11: Koramangala
A12: Yelahanka | B12: Yelahanka
... A18: Indiranagar | B18: Indiranagar

Sheet Data Prep
A1: Total Spend | B1: Sum of net_total | G1: Total Savings | H1: Sum of Discount | I1: Sum of free_delivery_discount_hit
B2: 25567 | H2: 4083.88 | I2: 2626 | J2: =GETPIVOTDATA("Sum of Discount",$H$1)+GETPIVOTDATA("Sum of free_delivery_discount_hit",$H$1) -> 6709.88
A4: Total Orders | B4: Count of order_id | G4: Preferred Food item | H4: Row Labels | I4: Count of order_id
B5: 62 | H5: Single Lamb Cheese Burger | I5: 6
H6: Grand Total | I6: 6
A8: AOV | B8: Average of net_total
B9: 412.37097
G10: Preferred Restaurant | H10: Row Labels | I10: Count of order_id
H11: Rasayan | I11: 8
A12: Avg Delivery Time | B12: Average of delivery_time_in_seconds | C12: Mins | H12: Subway | I12: 8
B13: 2124.5806 | C13: =GETPIVOTDATA("delivery_time_in_seconds",$B$12)/60 -> 35.409677 | H13: Grand Total | I13: 16
G16: Preferred Payment Mode | H16: Row Labels | I16: Count of order_id
A17: Avg Delivery Distance | B17: Average of restaurant_customer_distance | H17: UPICollect | I17: 56
B18: 3.1451613 | H18: Grand Total | I18: 56
B23: Which discounts(Coupon Codes) usually prefer to Order?
B25: Row Labels | C25: Count of order_id
B26: SWIGGYIT | C26: 0.37096774
B27: No Coupon Applied | C27: 0.22580645
B28: TRYNEW | C28: 0.11290323
B29: MDM150 | C29: 0.096774194
B30: JUMBO | C30: 0.048387097
B31: MISSEDYOU | C31: 0.048387097
B32: FLATDEAL | C32: 0.032258065
B33: DEALICIOUS | C33: 0.032258065
B34: FLAT100 | C34: 0.032258065
B35: Grand Total | C35: 1
B48: MOM Orders/Revenue
B51: Row Labels | C51: Count of order_id | D51: Sum of net_total
B52: 2024 | C52: 62 | D52: 25567
B53: Qtr1 | C53: 29 | D53: 11420
B54: Jan | C54: 8 | D54: 4160
B55: Feb | C55: 11 | D55: 3580
B56: Mar | C56: 10 | D56: 3680
B57: Qtr2 | C57: 33 | D57: 14147
B58: Apr | C58: 10 | D58: 3778
B59: May | C59: 23 | D59: 10369
B60: Grand Total | C60: 62 | D60: 25567
B74: Veg vs Non Veg Orders
B77: Row Labels | C77: Count of order_id
B78: Non_Veg | C78: 0.6
B79: Veg | C79: 0.4
B80: Grand Total | C80: 1
B89: Delivered vs Cancelled Orders | E89: --> Slicer
B93: When do you order?
D94: 1. Which day of the week.
D95: 2. What time of the data
B98: 1. Which day of the week.
C100: Row Labels | D100: Count of order_id
C101: Tuesday | D101: 0.24193548
C102: Saturday | D102: 0.17741935
C103: Monday | D103: 0.16129032
C104: Sunday | D104: 0.14516129
C105: Friday | D105: 0.11290323
C106: Thursday | D106: 0.080645161
C107: Wednesday | D107: 0.080645161
C108: Grand Total | D108: 1
B114: 2. What time of the data
C116: Row Labels | D116: Count of order_id
C117: Evening | D117: 0.37096774
C118: Afternoon | D118: 0.24193548
C119: Night | D119: 0.20967742
C120: Late Morning | D120: 0.12903226
C121: Early Morning | D121: 0.048387097
C122: Grand Total | D122: 1

Sheet Dashboard
A1: SWIGGY ORDERS
A3: Total Spend | B3: =GETPIVOTDATA("net_total",'Data Prep'!$B$1) -> 25567 | D3: Total Savings | E3: ='Data Prep'!J2 -> 6709.88 | G3: Avg Delivery Time | H3: ='Data Prep'!C13 -> 35.409677
A4: Total Orders | B4: =GETPIVOTDATA("order_id",'Data Prep'!$B$4) -> 62 | D4: Preferred Food item | E4: ='Data Prep'!H5 -> Single Lamb Cheese Burger | G4: Avg Delivery Distance | H4: =GETPIVOTDATA("restaurant_customer_distance",'Data Prep'!$B$17) -> 3.1451613
A5: AOV | B5: =GETPIVOTDATA("net_total",'Data Prep'!$B$8) -> 412.37097 | D5: Preferred Restaurant | E5: ='Data Prep'!H11 -> Rasayan | G5: Preferred Payment Mode | H5: ='Data Prep'!H17 -> UPICollect

Sheet Protection
C2: Unprotected | E2: By default all the cells are locked in excel and protection is applied on locked cells

Sheet Dynamic Named Range
B3: Dynamic Named Range
E4: 1. Convert to Table
E5: 2. Using Offset
